Workbook

Sheet 月度培训数据-经理复盘会
A1: 营销中心《月度培训数据》
A2: 统计规则：商学院系统数据
A3: 月份 | B3: 城市 | C3: 培训类别 | D3: 线下培训（集团） | L3: 自主培训 | O3: 商学院
D4: 计划完成场次 （天数） | E4: 培训场次 （累计天数） | F4: 完成率（%） | G4: 培训人数（累计） | H4: 到场率 （平均） | I4: 考试平均分 （累计） | J4: 讲师满意度 （平均） | K4: 课程满意度 （平均） | L4: 培训场次（累计） | M4: 培训人数（累计） | N4: 讲师满意度 （平均） | O4: 《每日一练》 | R4: 《每周一通》 | U4: 《每周一练》
O5: 应完成数量 | P5: 实际完成数量 | Q5: 完成率 | R5: 应完成数量 | S5: 实际完成数量 | T5: 完成率 | U5: 应完成数量 | V5: 实际完成数量 | W5: 完成率
A6: 1月 | B6: 甘肃 | C6: 销售新人入职培训 | D6: 1 | E6: 1 | F6: 1 | G6: 1 | H6: 1 | I6: 97.5 | J6: 5 | K6: 5 | L6: 9 | M6: 33 | N6: 5 | O6: 111 | P6: 104 | Q6: =P6/O6 -> 0.93693694 | R6: 15 | S6: 15 | T6: =S6/R6 -> 1 | U6: 4 | V6: 4 | W6: =V6/U6 -> 1
A7: 1月 | B7: 河北 | C7: 销售新人入职培训 | D7: 1 | E7: 3 | F7: 1 | G7: 3 | H7: 0.75 | I7: 62.3125 | J7: 5 | K7: 5 | L7: 12 | M7: 32 | N7: 5 | O7: 383 | P7: 374 | Q7: =P7/O7 -> 0.97650131 | R7: 58 | S7: 57 | T7: =S7/R7 -> 0.98275862 | U7: 16 | V7: 16 | W7: =V7/U7 -> 1
C8: 销售提升训 | D8: 1 | F8: 1 | G8: 2 | H8: 1 | I8: 82.333333 | J8: 5 | K8: 5
C9: 销售经理培训 | D9: 1 | F9: 1 | G9: 2 | H9: 1 | I9: 0 | J9: 5 | K9: 5
A10: 1月 | B10: 河南 | C10: 销售新人入职培训 | D10: 1 | E10: 9 | F10: 1 | G10: 5 | H10: 0.83333333 | I10: 76.875 | J10: 5 | K10: 5 | L10: 21 | M10: 95 | N10: 5 | O10: 845 | P10: 776 | Q10: =P10/O10 -> 0.9183432 | R10: 127 | S10: 125 | T10: =S10/R10 -> 0.98425197 | U10: 28 | V10: 25 | W10: =V10/U10 -> 0.89285714
C11: 销售提升训 | D11: 1 | F11: 1 | G11: 3 | H11: 1 | I11: 85.888889 | J11: 5 | K11: 5
C12: B岗培训 | D12: 6 | F12: 1 | G12: 3 | H12: 1 | I12: 0 | J12: 5 | K12: 5
C13: 销售经理培训 | D13: 1 | F13: 1 | G13: 3 | H13: 1 | I13: 0 | J13: 5 | K13: 5
A14: 1月 | B14: 湖北 | C14: 销售新人入职培训 | D14: 1 | E14: 9 | F14: 1 | G14: 3 | H14: 1 | I14: 92.083333 | J14: 5 | K14: 5 | L14: 38 | M14: 125 | N14: 5 | O14: 1389 | P14: 1313 | Q14: =P14/O14 -> 0.94528438 | R14: 206 | S14: 199 | T14: =S14/R14 -> 0.96601942 | U14: 46 | V14: 43 | W14: =V14/U14 -> 0.93478261
C15: 销售提升训 | D15: 1 | F15: 1 | G15: 0 | H15: 0 | I15: 0 | J15: 0 | K15: 0
C16: B岗培训 | D16: 6 | F16: 1 | G16: 12 | H16: 1 | I16: 0 | J16: 5 | K16: 5
C17: 销售经理培训 | D17: 1 | F17: 1 | G17: 3 | H17: 1 | I17: 0 | J17: 5 | K17: 5
A18: 1月 | B18: 湖南 | C18: 销售新人入职培训 | D18: 1 | E18: 9 | F18: 1 | G18: 3 | H18: 0.5 | I18: 47.375 | J18: 5 | K18: 5 | L18: 37 | M18: 119 | N18: 5 | O18: 1094 | P18: 1052 | Q18: =P18/O18 -> 0.96160878 | R18: 160 | S18: 152 | T18: =S18/R18 -> 0.95 | U18: 44 | V18: 42 | W18: =V18/U18 -> 0.95454545
C19: 销售提升训 | D19: 1 | F19: 1 | G19: 2 | H19: 1 | I19: 49 | J19: 5 | K19: 5
C20: B岗培训 | D20: 6 | F20: 1 | G20: 18 | H20: 1 | I20: 0 | J20: 5 | K20: 5
C21: 销售经理培训 | D21: 1 | F21: 1 | G21: 4 | H21: 1 | I21: 0 | J21: 5 | K21: 5
A22: 1月 | B22: 辽宁 | C22: 销售提升训 | D22: 1 | E22: 2 | F22: 1 | G22: 1 | H22: 1 | I22: 80 | J22: 5 | K22: 5 | L22: 3 | M22: 15 | N22: 5 | O22: 122 | P22: 115 | Q22: =P22/O22 -> 0.94262295 | R22: 20 | S22: 20 | T22: =S22/R22 -> 1 | U22: 4 | V22: 4 | W22: =V22/U22 -> 1
C23: 销售经理培训 | D23: 1 | F23: 1 | G23: 2 | H23: 1 | I23: 0 | J23: 5 | K23: 5
A24: 1月 | B24: 内蒙古 | C24: 销售新人入职培训 | D24: 1 | E24: 1 | F24: 1 | G24: 3 | H24: 1 | I24: 76.75 | J24: 5 | K24: 5 | L24: 6 | M24: 21 | N24: 5 | O24: 213 | P24: 202 | Q24: =P24/O24 -> 0.94835681 | R24: 32 | S24: 31 | T24: =S24/R24 -> 0.96875 | U24: 8 | V24: 8 | W24: =V24/U24 -> 1
A25: 1月 | B25: 山东 | C25: 销售新人入职培训 | D25: 1 | E25: 9 | F25: 1 | G25: 2 | H25: 1 | I25: 93.75 | J25: 5 | K25: 5 | L25: 31 | M25: 119 | N25: 5 | O25: 1041 | P25: 1009 | Q25: =P25/O25 -> 0.96926033 | R25: 152 | S25: 151 | T25: =S25/R25 -> 0.99342105 | U25: 38 | V25: 37 | W25: =V25/U25 -> 0.97368421
C26: 销售提升训 | D26: 1 | F26: 1 | G26: 6 | H26: 1 | I26: 92.705882 | J26: 5 | K26: 5
C27: B岗培训 | D27: 6 | F27: 1 | G27: 18 | H27: 1 | I27: 0 | J27: 5 | K27: 5
C28: 销售经理培训 | D28: 1 | F28: 1 | G28: 3 | H28: 1 | I28: 0 | J28: 5 | K28: 5
A29: 1月 | B29: 山西 | C29: 销售提升训 | D29: 1 | E29: 8 | F29: 1 | G29: 6 | H29: 1 | I29: 83.166667 | J29: 5 | K29: 5 | L29: 23 | M29: 108 | N29: 5 | O29: 1004 | P29: 933 | Q29: =P29/O29 -> 0.92928287 | R29: 152 | S29: 148 | T29: =S29/R29 -> 0.97368421 | U29: 30 | V29: 29 | W29: =V29/U29 -> 0.96666667
C30: B岗培训 | D30: 6 | F30: 1 | G30: 6 | H30: 1 | I30: 0 | J30: 5 | K30: 5
C31: 销售经理培训 | D31: 1 | F31: 1 | G31: 3 | H31: 1 | I31: 0 | J31: 5 | K31: 5
A32: 1月 | B32: 陕西 | C32: 销售新人入职培训 | D32: 1 | E32: 9 | F32: 1 | G32: 4 | H32: 1 | I32: 89.375 | J32: 5 | K32: 5 | L32: 50 | M32: 214 | N32: 5 | O32: 2176 | P32: 2070 | Q32: =P32/O32 -> 0.95128676 | R32: 330 | S32: 319 | T32: =S32/R32 -> 0.96666667 | U32: 76 | V32: 75 | W32: =V32/U32 -> 0.98684211
C33: 销售提升训 | D33: 1 | F33: 1 | G33: 3 | H33: 0.75 | I33: 72.75 | J33: 5 | K33: 5
C34: B岗培训 | D34: 6 | F34: 1 | G34: 18 | H34: 1 | I34: 0 | J34: 5 | K34: 5
C35: 销售经理培训 | D35: 1 | F35: 1 | G35: 4 | H35: 1 | I35: 0 | J35: 5 | K35: 5
A36: 1月 | B36: 西南总部 | C36: 销售新人入职培训 | D36: 1 | E36: 9 | F36: 1 | G36: 17 | H36: 0.31481481 | I36: 26.912821 | J36: 5 | K36: 5 | L36: 169 | M36: 732 | N36: 5 | O36: 6601 | P36: 6347 | Q36: =P36/O36 -> 0.96152098 | R36: 990 | S36: 959 | T36: =S36/R36 -> 0.96868687 | U36: 215 | V36: 207 | W36: =V36/U36 -> 0.9627907
C37: 销售提升训 | D37: 1 | F37: 1 | G37: 18 | H37: 0.32727273 | I37: 34.04908 | J37: 5 | K37: 5
C38: B岗培训 | D38: 6 | F38: 1 | G38: 50 | H38: 1 | I38: 0 | J38: 5 | K38: 5
C39: 销售经理培训 | D39: 1 | F39: 1 | G39: 11 | H39: 1 | I39: 0 | J39: 5 | K39: 5
A40: 2月 | B40: 西南总部 | C40: 讲师TTT培训 | D40: 2 | E40: 2 | F40: 1 | G40: 26 | H40: 1 | I40: 0 | J40: 0 | K40: 0 | L40: 112 | M40: 471 | N40: 4.9 | O40: 5523 | P40: 5309 | Q40: 0.96125294 | R40: 1005 | S40: 975 | T40: =S40/R40 -> 0.97014925 | U40: 219 | V40: 211 | W40: =V40/U40 -> 0.96347032
A41: 2月 | B41: 湖南 | C41: 讲师TTT培训 | D41: 2 | E41: 2 | F41: 1 | G41: 3 | H41: 1 | I41: 0 | J41: 0 | K41: 0 | L41: 22 | M41: 70 | N41: 4.9 | O41: 881 | P41: 850 | Q41: 0.96481271 | R41: 155 | S41: 153 | T41: =S41/R41 -> 0.98709677 | U41: 48 | V41: 45 | W41: =V41/U41 -> 0.9375
A42: 2月 | B42: 陕西 | C42: 讲师TTT培训 | D42: 2 | E42: 2 | F42: 1 | G42: 3 | H42: 1 | I42: 0 | J42: 0 | K42: 0 | L42: 38 | M42: 161 | N42: 5.0 | O42: 1830 | P42: 1735 | Q42: 0.94808743 | R42: 331 | S42: 320 | T42: =S42/R42 -> 0.96676737 | U42: 76 | V42: 72 | W42: =V42/U42 -> 0.94736842
A43: 2月 | B43: 河南 | C43: 讲师TTT培训 | D43: 2 | E43: 2 | F43: 1 | G43: 3 | H43: 1 | I43: 0 | J43: 0 | K43: 0 | L43: 15 | M43: 66 | N43: 5.0 | O43: 636 | P43: 598 | Q43: 0.94025157 | R43: 117 | S43: 110 | T43: =S43/R43 -> 0.94017094 | U43: 24 | V43: 22 | W43: =V43/U43 -> 0.91666667
A44: 2月 | B44: 湖北 | C44: 讲师TTT培训 | D44: 2 | E44: 2 | F44: 1 | G44: 3 | H44: 1 | I44: 0 | J44: 0 | K44: 0 | L44: 24 | M44: 74 | N44: 5.0 | O44: 1058 | P44: 987 | Q44: 0.93289225 | R44: 192 | S44: 177 | T44: =S44/R44 -> 0.921875 | U44: 52 | V44: 50 | W44: =V44/U44 -> 0.96153846
A45: 2月 | B45: 山东 | C45: 讲师TTT培训 | D45: 2 | E45: 2 | F45: 1 | G45: 4 | H45: 1 | I45: 0 | J45: 0 | K45: 0 | L45: 19 | M45: 55 | N45: 5.0 | O45: 798 | P45: 770 | Q45: 0.96491228 | R45: 154 | S45: 148 | T45: =S45/R45 -> 0.96103896 | U45: 40 | V45: 40 | W45: =V45/U45 -> 1
A46: 2月 | B46: 河北 | C46: 讲师TTT培训 | D46: 2 | E46: 2 | F46: 1 | G46: 4 | H46: 1 | I46: 0 | J46: 0 | K46: 0 | L46: 6 | M46: 22 | N46: 4.9 | O46: 346 | P46: 329 | Q46: 0.95086705 | R46: 59 | S46: 53 | T46: =S46/R46 -> 0.89830508 | U46: 16 | V46: 14 | W46: =V46/U46 -> 0.875
A47: 2月 | B47: 安徽 | C47: 讲师TTT培训 | D47: 2 | E47: 2 | F47: 1 | G47: 1 | H47: 1 | I47: 0 | J47: 0 | K47: 0 | L47: 0 | M47: 0 | N47: 0 | O47: 0 | P47: 0 | Q47: 1 | R47: 0 | S47: 0 | T47: 1 | U47: 0 | V47: 0 | W47: 1
A48: 2月 | B48: 甘肃 | C48: 讲师TTT培训 | D48: 2 | E48: 2 | F48: 1 | G48: 1 | H48: 1 | I48: 0 | J48: 0 | K48: 0 | L48: 2 | M48: 8 | N48: 5.0 | O48: 88 | P48: 85 | Q48: 0.96590909 | R48: 16 | S48: 16 | T48: =S48/R48 -> 1 | U48: 4 | V48: 4 | W48: =V48/U48 -> 1
A49: 2月 | B49: 辽宁 | C49: 讲师TTT培训 | D49: 2 | E49: 2 | F49: 1 | G49: 2 | H49: 1 | I49: 0 | J49: 0 | K49: 0 | L49: 4 | M49: 14 | N49: 5.0 | O49: 154 | P49: 148 | Q49: 0.96103896 | R49: 27 | S49: 27 | T49: =S49/R49 -> 1 | U49: 8 | V49: 8 | W49: =V49/U49 -> 1
A50: 2月 | B50: 内蒙古 | C50: 讲师TTT培训 | D50: 2 | E50: 2 | F50: 1 | G50: 1 | H50: 1 | I50: 0 | J50: 0 | K50: 0 | L50: 2 | M50: 3 | N50: 5.0 | O50: 171 | P50: 163 | Q50: 0.95321637 | R50: 32 | S50: 30 | T50: =S50/R50 -> 0.9375 | U50: 8 | V50: 8 | W50: =V50/U50 -> 1
A51: 2月 | B51: 山西 | C51: 讲师TTT培训 | D51: 2 | E51: 2 | F51: 1 | G51: 3 | H51: 1 | I51: 0 | J51: 0 | K51: 0 | L51: 17 | M51: 80 | N51: 4.9 | O51: 850 | P51: 815 | Q51: 0.95882353 | R51: 153 | S51: 149 | T51: =S51/R51 -> 0.97385621 | U51: 32 | V51: 32 | W51: =V51/U51 -> 1
A52: 2月 | B52: 宁夏 | C52: 讲师TTT培训 | D52: 2 | E52: 2 | F52: 1 | G52: 1 | H52: 1 | I52: 0 | J52: 0 | K52: 0 | L52: 0 | M52: 0 | N52: 0 | O52: 0 | P52: 0 | Q52: 1 | R52: 0 | S52: 0 | T52: 1 | U52: 0 | V52: 0 | W52: 1
A53: 3月 | B53: 西南总部 | C53: 销售提升训 | D53: 1 | E53: =SUM(D53:D55) -> 7 | F53: 1 | G53: 62 | H53: =COUNTIFS('2026年度培训主表'!B:B,A53,'2026年度培训主表'!C:C,B53,'2026年度培训主表'!D:D,C53,'2026年度培训主表'!L:L,"已签到")/3/G53 -> 0.57526882 | I53: =AVERAGEIFS('2026年度培训主表'!S:S,'2026年度培训主表'!B:B,'2026年度培训主表'!B958,'2026年度培训主表'!C:C,'2026年度培训主表'!C958,'2026年度培训主表'!D:D,C53,'2026年度培训主表'!L:L,'2026年度培训主表'!L957) -> 93.130841 | J53: =AVERAGEIFS('2026年度培训主表'!R:R,'2026年度培训主表'!B:B,'2026年度培训主表'!B958,'2026年度培训主表'!C:C,'2026年度培训主表'!C958,'2026年度培训主表'!D:D,C53,'2026年度培训主表'!L:L,'2026年度培训主表'!L957) -> 4.7663551 | K53: =AVERAGEIFS('2026年度培训主表'!Q:Q,'2026年度培训主表'!B:B,'2026年度培训主表'!B958,'2026年度培训主表'!C:C,'2026年度培训主表'!C958,'2026年度培训主表'!D:D,C53,'2026年度培训主表'!L:L,'2026年度培训主表'!L957) -> 4.7663551 | O53: {=IF($B53="西南总部",SUM(SUMIFS([6]汇总表!D:D,[6]汇总表!$A:$A,{"营业一部","营业二部","营业三部","营业四部","营业五部","营业六部","营业七部"})),IF($B53="湖北",SUM(SUMIFS([6]汇总表!D:D,[6]汇总表!$A:$A,{"湖北1部","湖北2部"})),IF($B53="陕西",SUM(SUMIFS([6]汇总表!D:D,[6]汇总表!$A:$A,{"陕西1部","陕西2部"})),SUMIFS([6]汇总表!D:D,[6]汇总表!$A:$A,$B53&"销售部"))))} -> 6415 | P53: {=IF($B53="西南总部",SUM(SUMIFS([6]汇总表!E:E,[6]汇总表!$A:$A,{"营业一部","营业二部","营业三部","营业四部","营业五部","营业六部","营业七部"})),IF($B53="湖北",SUM(SUMIFS([6]汇总表!E:E,[6]汇总表!$A:$A,{"湖北1部","湖北2部"})),IF($B53="陕西",SUM(SUMIFS([6]汇总表!E:E,[6]汇总表!$A:$A,{"陕西1部","陕西2部"})),SUMIFS([6]汇总表!E:E,[6]汇总表!$A:$A,$B53&"销售部"))))} -> 6068 | Q53: =IFERROR(P53/O53,0) -> 0.94590803 | R53: {=IF($B53="西南总部",SUM(SUMIFS([6]汇总表!H:H,[6]汇总表!$A:$A,{"营业一部","营业二部","营业三部","营业四部","营业五部","营业六部","营业七部"})),IF($B53="湖北",SUM(SUMIFS([6]汇总表!H:H,[6]汇总表!$A:$A,{"湖北1部","湖北2部"})),IF($B53="陕西",SUM(SUMIFS([6]汇总表!H:H,[6]汇总表!$A:$A,{"陕西1部","陕西2部"})),SUMIFS([6]汇总表!H:H,[6]汇总表!$A:$A,$B53&"销售部"))))} -> 987 | S53: {=IF($B53="西南总部",SUM(SUMIFS([6]汇总表!I:I,[6]汇总表!$A:$A,{"营业一部","营业二部","营业三部","营业四部","营业五部","营业六部","营业七部"})),IF($B53="湖北",SUM(SUMIFS([6]汇总表!I:I,[6]汇总表!$A:$A,{"湖北1部","湖北2部"})),IF($B53="陕西",SUM(SUMIFS([6]汇总表!I:I,[6]汇总表!$A:$A,{"陕西1部","陕西2部"})),SUMIFS([6]汇总表!I:I,[6]汇总表!$A:$A,$B53&"销售部"))))} -> 959 | T53: =IFERROR(S53/R53,0) -> 0.97163121 | U53: {=IF($B53="西南总部",SUM(SUMIFS([6]汇总表!L:L,[6]汇总表!$A:$A,{"营业一部","营业二部","营业三部","营业四部","营业五部","营业六部","营业七部"})),IF($B53="湖北",SUM(SUMIFS([6]汇总表!L:L,[6]汇总表!$A:$A,{"湖北1部","湖北2部"})),IF($B53="陕西",SUM(SUMIFS([6]汇总表!L:L,[6]汇总表!$A:$A,{"陕西1部","陕西2部"})),SUMIFS([6]汇总表!L:L,[6]汇总表!$A:$A,$B53&"销售部"))))} -> 212 | V53: {=IF($B53="西南总部",SUM(SUMIFS([6]汇总表!M:M,[6]汇总表!$A:$A,{"营业一部","营业二部","营业三部","营业四部","营业五部","营业六部","营业七部"})),IF($B53="湖北",SUM(SUMIFS([6]汇总表!M:M,[6]汇总表!$A:$A,{"湖北1部","湖北2部"})),IF($B53="陕西",SUM(SUMIFS([6]汇总表!M:M,[6]汇总表!$A:$A,{"陕西1部","陕西2部"})),SUMIFS([6]汇总表!M:M,[6]汇总表!$A:$A,$B53&"销售部"))))} -> 206 | W53: =IFERROR(V53/U53,0) -> 0.97169811
C54: B岗培训 | D54: 5 | F54: 1 | G54: =COUNTIFS('2026年度培训主表'!B:B,A53,'2026年度培训主表'!C:C,B53,'2026年度培训主表'!D:D,C54)/6 -> 9 | H54: =COUNTIFS('2026年度培训主表'!B:B,'2026年度培训主表'!B873,'2026年度培训主表'!C:C,'2026年度培训主表'!C873,'2026年度培训主表'!D:D,'2026年度培训主表'!D873,'2026年度培训主表'!L:L,'2026年度培训主表'!L959)/6/G54 -> 1 | I54: =AVERAGEIFS('2026年度培训主表'!S:S,'2026年度培训主表'!B:B,'2026年度培训主表'!B959,'2026年度培训主表'!C:C,'2026年度培训主表'!C959,'2026年度培训主表'!D:D,C54,'2026年度培训主表'!L:L,'2026年度培训主表'!L958) -> 57.222222 | J54: =AVERAGEIFS('2026年度培训主表'!R:R,'2026年度培训主表'!B:B,'2026年度培训主表'!B959,'2026年度培训主表'!C:C,'2026年度培训主表'!C959,'2026年度培训主表'!D:D,C54,'2026年度培训主表'!L:L,'2026年度培训主表'!L958) -> 4.8074074 | K54: =AVERAGEIFS('2026年度培训主表'!Q:Q,'2026年度培训主表'!B:B,'2026年度培训主表'!B959,'2026年度培训主表'!C:C,'2026年度培训主表'!C959,'2026年度培训主表'!D:D,C54,'2026年度培训主表'!L:L,'2026年度培训主表'!L958) -> 4.8148148
C55: 销售新人入职培训 | D55: 1 | F55: 1 | G55: =COUNTIFS('2026年度培训主表'!B:B,A53,'2026年度培训主表'!C:C,B53,'2026年度培训主表'!D:D,C55)/4 -> 59.5 | H55: =COUNTIFS('2026年度培训主表'!B:B,A53,'2026年度培训主表'!C:C,B53,'2026年度培训主表'!D:D,C55,'2026年度培训主表'!L:L,"已签到")/4/G55 -> 0.36134454 | I55: =AVERAGEIFS('2026年度培训主表'!S:S,'2026年度培训主表'!B:B,A53,'2026年度培训主表'!C:C,B53,'2026年度培训主表'!D:D,C55,'2026年度培训主表'!L:L,"已签到") -> 85.186047 | J55: =AVERAGEIFS('2026年度培训主表'!R:R,'2026年度培训主表'!B:B,A53,'2026年度培训主表'!C:C,B53,'2026年度培训主表'!D:D,C55,'2026年度培训主表'!L:L,"已签到") -> 4.3604651 | K55: =AVERAGEIFS('2026年度培训主表'!Q:Q,'2026年度培训主表'!B:B,A53,'2026年度培训主表'!C:C,B53,'2026年度培训主表'!D:D,C55,'2026年度培训主表'!L:L,"已签到") -> 4.3575581
A56: 3月 | B56: 湖南 | C56: 销售提升训 | D56: 1 | E56: =SUM(D56:D58) -> 7 | F56: 1 | G56: =COUNTIFS('2026年度培训主表'!B:B,'2026年度培训主表'!B1007,'2026年度培训主表'!C:C,B56,'2026年度培训主表'!D:D,C56)/3 -> 1 | H56: =COUNTIFS('2026年度培训主表'!B:B,'2026年度培训主表'!B1007,'2026年度培训主表'!C:C,'2026年度培训主表'!C1007,'2026年度培训主表'!D:D,'2026年度培训主表'!D1007,'2026年度培训主表'!L:L,'2026年度培训主表'!L1007)/3/G56 -> 1 | I56: =AVERAGEIFS('2026年度培训主表'!S:S,'2026年度培训主表'!B:B,'2026年度培训主表'!B1007,'2026年度培训主表'!C:C,'2026年度培训主表'!C1007,'2026年度培训主表'!D:D,'2026年度培训主表'!D1007,'2026年度培训主表'!L:L,'2026年度培训主表'!L1007) -> 95.333333 | J56: =AVERAGEIFS('2026年度培训主表'!R:R,'2026年度培训主表'!B:B,'2026年度培训主表'!B1007,'2026年度培训主表'!C:C,'2026年度培训主表'!C1007,'2026年度培训主表'!D:D,C56,'2026年度培训主表'!L:L,'2026年度培训主表'!L1007) -> 5 | K56: =AVERAGEIFS('2026年度培训主表'!Q:Q,'2026年度培训主表'!B:B,'2026年度培训主表'!B1007,'2026年度培训主表'!C:C,'2026年度培训主表'!C1007,'2026年度培训主表'!D:D,C56,'2026年度培训主表'!L:L,'2026年度培训主表'!L1007) -> 4.9166667 | O56: {=IF($B56="西南总部",SUM(SUMIFS([6]汇总表!D:D,[6]汇总表!$A:$A,{"营业一部","营业二部","营业三部","营业四部","营业五部","营业六部","营业七部"})),IF($B56="湖北",SUM(SUMIFS([6]汇总表!D:D,[6]汇总表!$A:$A,{"湖北1部","湖北2部"})),IF($B56="陕西",SUM(SUMIFS([6]汇总表!D:D,[6]汇总表!$A:$A,{"陕西1部","陕西2部"})),SUMIFS([6]汇总表!D:D,[6]汇总表!$A:$A,$B56&"销售部"))))} -> 903 | P56: {=IF($B56="西南总部",SUM(SUMIFS([6]汇总表!E:E,[6]汇总表!$A:$A,{"营业一部","营业二部","营业三部","营业四部","营业五部","营业六部","营业七部"})),IF($B56="湖北",SUM(SUMIFS([6]汇总表!E:E,[6]汇总表!$A:$A,{"湖北1部","湖北2部"})),IF($B56="陕西",SUM(SUMIFS([6]汇总表!E:E,[6]汇总表!$A:$A,{"陕西1部","陕西2部"})),SUMIFS([6]汇总表!E:E,[6]汇总表!$A:$A,$B56&"销售部"))))} -> 873 | Q56: =IFERROR(P56/O56,0) -> 0.96677741 | R56: {=IF($B56="西南总部",SUM(SUMIFS([6]汇总表!H:H,[6]汇总表!$A:$A,{"营业一部","营业二部","营业三部","营业四部","营业五部","营业六部","营业七部"})),IF($B56="湖北",SUM(SUMIFS([6]汇总表!H:H,[6]汇总表!$A:$A,{"湖北1部","湖北2部"})),IF($B56="陕西",SUM(SUMIFS([6]汇总表!H:H,[6]汇总表!$A:$A,{"陕西1部","陕西2部"})),SUMIFS([6]汇总表!H:H,[6]汇总表!$A:$A,$B56&"销售部"))))} -> 136 | S56: {=IF($B56="西南总部",SUM(SUMIFS([6]汇总表!I:I,[6]汇总表!$A:$A,{"营业一部","营业二部","营业三部","营业四部","营业五部","营业六部","营业七部"})),IF($B56="湖北",SUM(SUMIFS([6]汇总表!I:I,[6]汇总表!$A:$A,{"湖北1部","湖北2部"})),IF($B56="陕西",SUM(SUMIFS([6]汇总表!I:I,[6]汇总表!$A:$A,{"陕西1部","陕西2部"})),SUMIFS([6]汇总表!I:I,[6]汇总表!$A:$A,$B56&"销售部"))))} -> 130 | T56: =IFERROR(S56/R56,0) -> 0.95588235 | U56: {=IF($B56="西南总部",SUM(SUMIFS([6]汇总表!L:L,[6]汇总表!$A:$A,{"营业一部","营业二部","营业三部","营业四部","营业五部","营业六部","营业七部"})),IF($B56="湖北",SUM(SUMIFS([6]汇总表!L:L,[6]汇总表!$A:$A,{"湖北1部","湖北2部"})),IF($B56="陕西",SUM(SUMIFS([6]汇总表!L:L,[6]汇总表!$A:$A,{"陕西1部","陕西2部"})),SUMIFS([6]汇总表!L:L,[6]汇总表!$A:$A,$B56&"销售部"))))} -> 47 | V56: {=IF($B56="西南总部",SUM(SUMIFS([6]汇总表!M:M,[6]汇总表!$A:$A,{"营业一部","营业二部","营业三部","营业四部","营业五部","营业六部","营业七部"})),IF($B56="湖北",SUM(SUMIFS([6]汇总表!M:M,[6]汇总表!$A:$A,{"湖北1部","湖北2部"})),IF($B56="陕西",SUM(SUMIFS([6]汇总表!M:M,[6]汇总表!$A:$A,{"陕西1部","陕西2部"})),SUMIFS([6]汇总表!M:M,[6]汇总表!$A:$A,$B56&"销售部"))))} -> 47 | W56: =IFERROR(V56/U56,0) -> 1
C57: B岗培训 | D57: 5 | F57: 1 | G57: =COUNTIFS('2026年度培训主表'!B:B,A56,'2026年度培训主表'!C:C,B56,'2026年度培训主表'!D:D,C57)/6 -> 1.6666667 | H57: =COUNTIFS('2026年度培训主表'!B:B,A56,'2026年度培训主表'!C:C,B56,'2026年度培训主表'!D:D,C57,'2026年度培训主表'!L:L,"已签到")/6/G57 -> 1 | I57: =AVERAGEIFS('2026年度培训主表'!S:S,'2026年度培训主表'!B:B,A56,'2026年度培训主表'!C:C,B56,'2026年度培训主表'!D:D,C57,'2026年度培训主表'!L:L,"已签到") -> 50 | J57: =AVERAGEIFS('2026年度培训主表'!R:R,'2026年度培训主表'!B:B,A56,'2026年度培训主表'!C:C,B56,'2026年度培训主表'!D:D,C57,'2026年度培训主表'!L:L,"已签到") -> 4.5 | K57: =AVERAGEIFS('2026年度培训主表'!Q:Q,'2026年度培训主表'!B:B,A56,'2026年度培训主表'!C:C,B56,'2026年度培训主表'!D:D,C57,'2026年度培训主表'!L:L,"已签到") -> 4.475
C58: 销售新人入职培训 | D58: 1 | F58: 1 | G58: =COUNTIFS('2026年度培训主表'!B:B,A56,'2026年度培训主表'!C:C,B56,'2026年度培训主表'!D:D,C58)/4 -> 5 | H58: =COUNTIFS('2026年度培训主表'!B:B,A56,'2026年度培训主表'!C:C,B56,'2026年度培训主表'!D:D,C58,'2026年度培训主表'!L:L,"已签到")/4/G58 -> 0.8 | I58: =AVERAGEIFS('2026年度培训主表'!S:S,'2026年度培训主表'!B:B,A56,'2026年度培训主表'!C:C,B56,'2026年度培训主表'!D:D,C58,'2026年度培训主表'!L:L,"已签到") -> 85.4375 | J58: =AVERAGEIFS('2026年度培训主表'!R:R,'2026年度培训主表'!B:B,A56,'2026年度培训主表'!C:C,B56,'2026年度培训主表'!D:D,C58,'2026年度培训主表'!L:L,"已签到") -> 4.6875 | K58: =AVERAGEIFS('2026年度培训主表'!Q:Q,'2026年度培训主表'!B:B,A56,'2026年度培训主表'!C:C,B56,'2026年度培训主表'!D:D,C58,'2026年度培训主表'!L:L,"已签到") -> 4.6875
A59: 3月 | B59: 陕西 | C59: 销售提升训 | D59: 1 | E59: =SUM(D59:D61) -> 7 | F59: 1 | G59: =COUNTIFS('2026年度培训主表'!B:B,A59,'2026年度培训主表'!C:C,B59,'2026年度培训主表'!D:D,C59)/3 -> 13 | H59: =COUNTIFS('2026年度培训主表'!B:B,A59,'2026年度培训主表'!C:C,B59,'2026年度培训主表'!D:D,C59,'2026年度培训主表'!L:L,"已签到")/3/G59 -> 0.53846154 | I59: =AVERAGEIFS('2026年度培训主表'!S:S,'2026年度培训主表'!B:B,A59,'2026年度培训主表'!C:C,B59,'2026年度培训主表'!D:D,C59,'2026年度培训主表'!L:L,"已签到") -> 94.238095 | J59: =AVERAGEIFS('2026年度培训主表'!R:R,'2026年度培训主表'!B:B,A59,'2026年度培训主表'!C:C,B59,'2026年度培训主表'!D:D,C59,'2026年度培训主表'!L:L,"已签到") -> 4.2857143 | K59: =AVERAGEIFS('2026年度培训主表'!Q:Q,'2026年度培训主表'!B:B,A59,'2026年度培训主表'!C:C,B59,'2026年度培训主表'!D:D,C59,'2026年度培训主表'!L:L,"已签到") -> 4.2738095 | O59: {=IF($B59="西南总部",SUM(SUMIFS([6]汇总表!D:D,[6]汇总表!$A:$A,{"营业一部","营业二部","营业三部","营业四部","营业五部","营业六部","营业七部"})),IF($B59="湖北",SUM(SUMIFS([6]汇总表!D:D,[6]汇总表!$A:$A,{"湖北1部","湖北2部"})),IF($B59="陕西",SUM(SUMIFS([6]汇总表!D:D,[6]汇总表!$A:$A,{"陕西1部","陕西2部"})),SUMIFS([6]汇总表!D:D,[6]汇总表!$A:$A,$B59&"销售部"))))} -> 1995 | P59: {=IF($B59="西南总部",SUM(SUMIFS([6]汇总表!E:E,[6]汇总表!$A:$A,{"营业一部","营业二部","营业三部","营业四部","营业五部","营业六部","营业七部"})),IF($B59="湖北",SUM(SUMIFS([6]汇总表!E:E,[6]汇总表!$A:$A,{"湖北1部","湖北2部"})),IF($B59="陕西",SUM(SUMIFS([6]汇总表!E:E,[6]汇总表!$A:$A,{"陕西1部","陕西2部"})),SUMIFS([6]汇总表!E:E,[6]汇总表!$A:$A,$B59&"销售部"))))} -> 1893 | Q59: =IFERROR(P59/O59,0) -> 0.94887218 | R59: {=IF($B59="西南总部",SUM(SUMIFS([6]汇总表!H:H,[6]汇总表!$A:$A,{"营业一部","营业二部","营业三部","营业四部","营业五部","营业六部","营业七部"})),IF($B59="湖北",SUM(SUMIFS([6]汇总表!H:H,[6]汇总表!$A:$A,{"湖北1部","湖北2部"})),IF($B59="陕西",SUM(SUMIFS([6]汇总表!H:H,[6]汇总表!$A:$A,{"陕西1部","陕西2部"})),SUMIFS([6]汇总表!H:H,[6]汇总表!$A:$A,$B59&"销售部"))))} -> 307 | S59: {=IF($B59="西南总部",SUM(SUMIFS([6]汇总表!I:I,[6]汇总表!$A:$A,{"营业一部","营业二部","营业三部","营业四部","营业五部","营业六部","营业七部"})),IF($B59="湖北",SUM(SUMIFS([6]汇总表!I:I,[6]汇总表!$A:$A,{"湖北1部","湖北2部"})),IF($B59="陕西",SUM(SUMIFS([6]汇总表!I:I,[6]汇总表!$A:$A,{"陕西1部","陕西2部"})),SUMIFS([6]汇总表!I:I,[6]汇总表!$A:$A,$B59&"销售部"))))} -> 298 | T59: =IFERROR(S59/R59,0) -> 0.97068404 | U59: {=IF($B59="西南总部",SUM(SUMIFS([6]汇总表!L:L,[6]汇总表!$A:$A,{"营业一部","营业二部","营业三部","营业四部","营业五部","营业六部","营业七部"})),IF($B59="湖北",SUM(SUMIFS([6]汇总表!L:L,[6]汇总表!$A:$A,{"湖北1部","湖北2部"})),IF($B59="陕西",SUM(SUMIFS([6]汇总表!L:L,[6]汇总表!$A:$A,{"陕西1部","陕西2部"})),SUMIFS([6]汇总表!L:L,[6]汇总表!$A:$A,$B59&"销售部"))))} -> 72 | V59: {=IF($B59="西南总部",SUM(SUMIFS([6]汇总表!M:M,[6]汇总表!$A:$A,{"营业一部","营业二部","营业三部","营业四部","营业五部","营业六部","营业七部"})),IF($B59="湖北",SUM(SUMIFS([6]汇总表!M:M,[6]汇总表!$A:$A,{"湖北1部","湖北2部"})),IF($B59="陕西",SUM(SUMIFS([6]汇总表!M:M,[6]汇总表!$A:$A,{"陕西1部","陕西2部"})),SUMIFS([6]汇总表!M:M,[6]汇总表!$A:$A,$B59&"销售部"))))} -> 70 | W59: =IFERROR(V59/U59,0) -> 0.97222222
C60: B岗培训 | D60: 5 | F60: 1 | G60: =COUNTIFS('2026年度培训主表'!B:B,A59,'2026年度培训主表'!C:C,B59,'2026年度培训主表'!D:D,C60)/6 -> 1 | H60: =COUNTIFS('2026年度培训主表'!B:B,A59,'2026年度培训主表'!C:C,B59,'2026年度培训主表'!D:D,C60,'2026年度培训主表'!L:L,"已签到")/6/G60 -> 1 | I60: =AVERAGEIFS('2026年度培训主表'!S:S,'2026年度培训主表'!B:B,A59,'2026年度培训主表'!C:C,B59,'2026年度培训主表'!D:D,C60,'2026年度培训主表'!L:L,"已签到") -> 70 | J60: =AVERAGEIFS('2026年度培训主表'!R:R,'2026年度培训主表'!B:B,A59,'2026年度培训主表'!C:C,B59,'2026年度培训主表'!D:D,C60,'2026年度培训主表'!L:L,"已签到") -> 5 | K60: =AVERAGEIFS('2026年度培训主表'!Q:Q,'2026年度培训主表'!B:B,A59,'2026年度培训主表'!C:C,B59,'2026年度培训主表'!D:D,C60,'2026年度培训主表'!L:L,"已签到") -> 5
C61: 销售新人入职培训 | D61: 1 | F61: 1 | G61: =COUNTIFS('2026年度培训主表'!B:B,A59,'2026年度培训主表'!C:C,B59,'2026年度培训主表'!D:D,C61)/4 -> 4 | H61: =COUNTIFS('2026年度培训主表'!B:B,A59,'2026年度培训主表'!C:C,B59,'2026年度培训主表'!D:D,C61,'2026年度培训主表'!L:L,"已签到")/4/G61 -> 1 | I61: =AVERAGEIFS('2026年度培训主表'!S:S,'2026年度培训主表'!B:B,A59,'2026年度培训主表'!C:C,B59,'2026年度培训主表'!D:D,C61,'2026年度培训主表'!L:L,"已签到") -> 64.6875 | J61: =AVERAGEIFS('2026年度培训主表'!R:R,'2026年度培训主表'!B:B,A59,'2026年度培训主表'!C:C,B59,'2026年度培训主表'!D:D,C61,'2026年度培训主表'!L:L,"已签到") -> 3.4375 | K61: =AVERAGEIFS('2026年度培训主表'!Q:Q,'2026年度培训主表'!B:B,A59,'2026年度培训主表'!C:C,B59,'2026年度培训主表'!D:D,C61,'2026年度培训主表'!L:L,"已签到") -> 3.4375
A62: 3月 | B62: 河南 | C62: 销售提升训 | D62: 1 | E62: =SUM(D62:D64) -> 7 | F62: 1 | G62: =COUNTIFS('2026年度培训主表'!B:B,A62,'2026年度培训主表'!C:C,B62,'2026年度培训主表'!D:D,C62)/3 -> 9 | H62: =COUNTIFS('2026年度培训主表'!B:B,A62,'2026年度培训主表'!C:C,B62,'2026年度培训主表'!D:D,C62,'2026年度培训主表'!L:L,"已签到")/3/G62 -> 0.88888889 | I62: =AVERAGEIFS('2026年度培训主表'!S:S,'2026年度培训主表'!B:B,A62,'2026年度培训主表'!C:C,B62,'2026年度培训主表'!D:D,C62,'2026年度培训主表'!L:L,"已签到") -> 84.375 | J62: =AVERAGEIFS('2026年度培训主表'!R:R,'2026年度培训主表'!B:B,A62,'2026年度培训主表'!C:C,B62,'2026年度培训主表'!D:D,C62,'2026年度培训主表'!L:L,"已签到") -> 4.5833333 | K62: =AVERAGEIFS('2026年度培训主表'!Q:Q,'2026年度培训主表'!B:B,A62,'2026年度培训主表'!C:C,B62,'2026年度培训主表'!D:D,C62,'2026年度培训主表'!L:L,"已签到") -> 4.5833333 | O62: {=IF($B62="西南总部",SUM(SUMIFS([6]汇总表!D:D,[6]汇总表!$A:$A,{"营业一部","营业二部","营业三部","营业四部","营业五部","营业六部","营业七部"})),IF($B62="湖北",SUM(SUMIFS([6]汇总表!D:D,[6]汇总表!$A:$A,{"湖北1部","湖北2部"})),IF($B62="陕西",SUM(SUMIFS([6]汇总表!D:D,[6]汇总表!$A:$A,{"陕西1部","陕西2部"})),SUMIFS([6]汇总表!D:D,[6]汇总表!$A:$A,$B62&"销售部"))))} -> 954 | P62: {=IF($B62="西南总部",SUM(SUMIFS([6]汇总表!E:E,[6]汇总表!$A:$A,{"营业一部","营业二部","营业三部","营业四部","营业五部","营业六部","营业七部"})),IF($B62="湖北",SUM(SUMIFS([6]汇总表!E:E,[6]汇总表!$A:$A,{"湖北1部","湖北2部"})),IF($B62="陕西",SUM(SUMIFS([6]汇总表!E:E,[6]汇总表!$A:$A,{"陕西1部","陕西2部"})),SUMIFS([6]汇总表!E:E,[6]汇总表!$A:$A,$B62&"销售部"))))} -> 912 | Q62: =IFERROR(P62/O62,0) -> 0.95597484 | R62: {=IF($B62="西南总部",SUM(SUMIFS([6]汇总表!H:H,[6]汇总表!$A:$A,{"营业一部","营业二部","营业三部","营业四部","营业五部","营业六部","营业七部"})),IF($B62="湖北",SUM(SUMIFS([6]汇总表!H:H,[6]汇总表!$A:$A,{"湖北1部","湖北2部"})),IF($B62="陕西",SUM(SUMIFS([6]汇总表!H:H,[6]汇总表!$A:$A,{"陕西1部","陕西2部"})),SUMIFS([6]汇总表!H:H,[6]汇总表!$A:$A,$B62&"销售部"))))} -> 149 | S62: {=IF($B62="西南总部",SUM(SUMIFS([6]汇总表!I:I,[6]汇总表!$A:$A,{"营业一部","营业二部","营业三部","营业四部","营业五部","营业六部","营业七部"})),IF($B62="湖北",SUM(SUMIFS([6]汇总表!I:I,[6]汇总表!$A:$A,{"湖北1部","湖北2部"})),IF($B62="陕西",SUM(SUMIFS([6]汇总表!I:I,[6]汇总表!$A:$A,{"陕西1部","陕西2部"})),SUMIFS([6]汇总表!I:I,[6]汇总表!$A:$A,$B62&"销售部"))))} -> 147 | T62: =IFERROR(S62/R62,0) -> 0.98657718 | U62: {=IF($B62="西南总部",SUM(SUMIFS([6]汇总表!L:L,[6]汇总表!$A:$A,{"营业一部","营业二部","营业三部","营业四部","营业五部","营业六部","营业七部"})),IF($B62="湖北",SUM(SUMIFS([6]汇总表!L:L,[6]汇总表!$A:$A,{"湖北1部","湖北2部"})),IF($B62="陕西",SUM(SUMIFS([6]汇总表!L:L,[6]汇总表!$A:$A,{"陕西1部","陕西2部"})),SUMIFS([6]汇总表!L:L,[6]汇总表!$A:$A,$B62&"销售部"))))} -> 32 | V62: {=IF($B62="西南总部",SUM(SUMIFS([6]汇总表!M:M,[6]汇总表!$A:$A,{"营业一部","营业二部","营业三部","营业四部","营业五部","营业六部","营业七部"})),IF($B62="湖北",SUM(SUMIFS([6]汇总表!M:M,[6]汇总表!$A:$A,{"湖北1部","湖北2部"})),IF($B62="陕西",SUM(SUMIFS([6]汇总表!M:M,[6]汇总表!$A:$A,{"陕西1部","陕西2部"})),SUMIFS([6]汇总表!M:M,[6]汇总表!$A:$A,$B62&"销售部"))))} -> 32 | W62: =IFERROR(V62/U62,0) -> 1
C63: B岗培训 | D63: 5 | F63: 1 | G63: =COUNTIFS('2026年度培训主表'!B:B,A62,'2026年度培训主表'!C:C,B62,'2026年度培训主表'!D:D,C63)/6 -> 1.6666667 | H63: =COUNTIFS('2026年度培训主表'!B:B,A62,'2026年度培训主表'!C:C,B62,'2026年度培训主表'!D:D,C63,'2026年度培训主表'!L:L,"已签到")/6/G63 -> 1 | I63: =AVERAGEIFS('2026年度培训主表'!S:S,'2026年度培训主表'!B:B,A62,'2026年度培训主表'!C:C,B62,'2026年度培训主表'!D:D,C63,'2026年度培训主表'!L:L,"已签到") -> 57 | J63: =AVERAGEIFS('2026年度培训主表'!R:R,'2026年度培训主表'!B:B,A62,'2026年度培训主表'!C:C,B62,'2026年度培训主表'!D:D,C63,'2026年度培训主表'!L:L,"已签到") -> 5 | K63: =AVERAGEIFS('2026年度培训主表'!Q:Q,'2026年度培训主表'!B:B,A62,'2026年度培训主表'!C:C,B62,'2026年度培训主表'!D:D,C63,'2026年度培训主表'!L:L,"已签到") -> 5
C64: 销售新人入职培训 | D64: 1 | F64: 1 | G64: =COUNTIFS('2026年度培训主表'!B:B,A62,'2026年度培训主表'!C:C,B62,'2026年度培训主表'!D:D,C64)/4 -> 3.5 | H64: =COUNTIFS('2026年度培训主表'!B:B,A62,'2026年度培训主表'!C:C,B62,'2026年度培训主表'!D:D,C64,'2026年度培训主表'!L:L,"已签到")/4/G64 -> 0.71428571 | I64: =AVERAGEIFS('2026年度培训主表'!S:S,'2026年度培训主表'!B:B,A62,'2026年度培训主表'!C:C,B62,'2026年度培训主表'!D:D,C64,'2026年度培训主表'!L:L,"已签到") -> 82.5 | J64: =AVERAGEIFS('2026年度培训主表'!R:R,'2026年度培训主表'!B:B,A62,'2026年度培训主表'!C:C,B62,'2026年度培训主表'!D:D,C64,'2026年度培训主表'!L:L,"已签到") -> 4.46 | K64: =AVERAGEIFS('2026年度培训主表'!Q:Q,'2026年度培训主表'!B:B,A62,'2026年度培训主表'!C:C,B62,'2026年度培训主表'!D:D,C64,'2026年度培训主表'!L:L,"已签到") -> 4.475
A65: 3月 | B65: 湖北 | C65: 销售提升训 | D65: 1 | E65: =SUM(D65:D67) -> 7 | F65: 1 | G65: =COUNTIFS('2026年度培训主表'!B:B,A65,'2026年度培训主表'!C:C,B65,'2026年度培训主表'!D:D,C65)/3 -> 9.6666667 | H65: =COUNTIFS('2026年度培训主表'!B:B,A65,'2026年度培训主表'!C:C,B65,'2026年度培训主表'!D:D,C65,'2026年度培训主表'!L:L,"已签到")/3/G65 -> 0.89655172 | I65: =AVERAGEIFS('2026年度培训主表'!S:S,'2026年度培训主表'!B:B,A65,'2026年度培训主表'!C:C,B65,'2026年度培训主表'!D:D,C65,'2026年度培训主表'!L:L,"已签到") -> 101.30769 | J65: =AVERAGEIFS('2026年度培训主表'!R:R,'2026年度培训主表'!B:B,A65,'2026年度培训主表'!C:C,B65,'2026年度培训主表'!D:D,C65,'2026年度培训主表'!L:L,"已签到") -> 4.8076923 | K65: =AVERAGEIFS('2026年度培训主表'!Q:Q,'2026年度培训主表'!B:B,A65,'2026年度培训主表'!C:C,B65,'2026年度培训主表'!D:D,C65,'2026年度培训主表'!L:L,"已签到") -> 4.8076923 | O65: {=IF($B65="西南总部",SUM(SUMIFS([6]汇总表!D:D,[6]汇总表!$A:$A,{"营业一部","营业二部","营业三部","营业四部","营业五部","营业六部","营业七部"})),IF($B65="湖北",SUM(SUMIFS([6]汇总表!D:D,[6]汇总表!$A:$A,{"湖北1部","湖北2部"})),IF($B65="陕西",SUM(SUMIFS([6]汇总表!D:D,[6]汇总表!$A:$A,{"陕西1部","陕西2部"})),SUMIFS([6]汇总表!D:D,[6]汇总表!$A:$A,$B65&"销售部"))))} -> 1335 | P65: {=IF($B65="西南总部",SUM(SUMIFS([6]汇总表!E:E,[6]汇总表!$A:$A,{"营业一部","营业二部","营业三部","营业四部","营业五部","营业六部","营业七部"})),IF($B65="湖北",SUM(SUMIFS([6]汇总表!E:E,[6]汇总表!$A:$A,{"湖北1部","湖北2部"})),IF($B65="陕西",SUM(SUMIFS([6]汇总表!E:E,[6]汇总表!$A:$A,{"陕西1部","陕西2部"})),SUMIFS([6]汇总表!E:E,[6]汇总表!$A:$A,$B65&"销售部"))))} -> 1263 | Q65: =IFERROR(P65/O65,0) -> 0.94606742 | R65: {=IF($B65="西南总部",SUM(SUMIFS([6]汇总表!H:H,[6]汇总表!$A:$A,{"营业一部","营业二部","营业三部","营业四部","营业五部","营业六部","营业七部"})),IF($B65="湖北",SUM(SUMIFS([6]汇总表!H:H,[6]汇总表!$A:$A,{"湖北1部","湖北2部"})),IF($B65="陕西",SUM(SUMIFS([6]汇总表!H:H,[6]汇总表!$A:$A,{"陕西1部","陕西2部"})),SUMIFS([6]汇总表!H:H,[6]汇总表!$A:$A,$B65&"销售部"))))} -> 204 | S65: {=IF($B65="西南总部",SUM(SUMIFS([6]汇总表!I:I,[6]汇总表!$A:$A,{"营业一部","营业二部","营业三部","营业四部","营业五部","营业六部","营业七部"})),IF($B65="湖北",SUM(SUMIFS([6]汇总表!I:I,[6]汇总表!$A:$A,{"湖北1部","湖北2部"})),IF($B65="陕西",SUM(SUMIFS([6]汇总表!I:I,[6]汇总表!$A:$A,{"陕西1部","陕西2部"})),SUMIFS([6]汇总表!I:I,[6]汇总表!$A:$A,$B65&"销售部"))))} -> 189 | T65: =IFERROR(S65/R65,0) -> 0.92647059 | U65: {=IF($B65="西南总部",SUM(SUMIFS([6]汇总表!L:L,[6]汇总表!$A:$A,{"营业一部","营业二部","营业三部","营业四部","营业五部","营业六部","营业七部"})),IF($B65="湖北",SUM(SUMIFS([6]汇总表!L:L,[6]汇总表!$A:$A,{"湖北1部","湖北2部"})),IF($B65="陕西",SUM(SUMIFS([6]汇总表!L:L,[6]汇总表!$A:$A,{"陕西1部","陕西2部"})),SUMIFS([6]汇总表!L:L,[6]汇总表!$A:$A,$B65&"销售部"))))} -> 56 | V65: {=IF($B65="西南总部",SUM(SUMIFS([6]汇总表!M:M,[6]汇总表!$A:$A,{"营业一部","营业二部","营业三部","营业四部","营业五部","营业六部","营业七部"})),IF($B65="湖北",SUM(SUMIFS([6]汇总表!M:M,[6]汇总表!$A:$A,{"湖北1部","湖北2部"})),IF($B65="陕西",SUM(SUMIFS([6]汇总表!M:M,[6]汇总表!$A:$A,{"陕西1部","陕西2部"})),SUMIFS([6]汇总表!M:M,[6]汇总表!$A:$A,$B65&"销售部"))))} -> 52 | W65: =IFERROR(V65/U65,0) -> 0.92857143
C66: B岗培训 | D66: 5 | F66: 1 | G66: =COUNTIFS('2026年度培训主表'!B:B,A65,'2026年度培训主表'!C:C,B65,'2026年度培训主表'!D:D,C66)/6 -> 1 | H66: =COUNTIFS('2026年度培训主表'!B:B,A65,'2026年度培训主表'!C:C,B65,'2026年度培训主表'!D:D,C66,'2026年度培训主表'!L:L,"已签到")/6/G66 -> 1 | I66: =AVERAGEIFS('2026年度培训主表'!S:S,'2026年度培训主表'!B:B,A65,'2026年度培训主表'!C:C,B65,'2026年度培训主表'!D:D,C66,'2026年度培训主表'!L:L,"已签到") -> 56.666667 | J66: =AVERAGEIFS('2026年度培训主表'!R:R,'2026年度培训主表'!B:B,A65,'2026年度培训主表'!C:C,B65,'2026年度培训主表'!D:D,C66,'2026年度培训主表'!L:L,"已签到") -> 4.1666667 | K66: =AVERAGEIFS('2026年度培训主表'!Q:Q,'2026年度培训主表'!B:B,A65,'2026年度培训主表'!C:C,B65,'2026年度培训主表'!D:D,C66,'2026年度培训主表'!L:L,"已签到") -> 4.1666667
C67: 销售新人入职培训 | D67: 1 | F67: 1 | G67: =COUNTIFS('2026年度培训主表'!B:B,A65,'2026年度培训主表'!C:C,B65,'2026年度培训主表'!D:D,C67)/4 -> 4 | H67: =COUNTIFS('2026年度培训主表'!B:B,A65,'2026年度培训主表'!C:C,B65,'2026年度培训主表'!D:D,C67,'2026年度培训主表'!L:L,"已签到")/4/G67 -> 0.75 | I67: =AVERAGEIFS('2026年度培训主表'!S:S,'2026年度培训主表'!B:B,A65,'2026年度培训主表'!C:C,B65,'2026年度培训主表'!D:D,C67,'2026年度培训主表'!L:L,"已签到") -> 74.333333 | J67: =AVERAGEIFS('2026年度培训主表'!R:R,'2026年度培训主表'!B:B,A65,'2026年度培训主表'!C:C,B65,'2026年度培训主表'!D:D,C67,'2026年度培训主表'!L:L,"已签到") -> 5 | K67: =AVERAGEIFS('2026年度培训主表'!Q:Q,'2026年度培训主表'!B:B,A65,'2026年度培训主表'!C:C,B65,'2026年度培训主表'!D:D,C67,'2026年度培训主表'!L:L,"已签到") -> 5
A68: 3月 | B68: 山东 | C68: 销售提升训 | D68: 1 | E68: =SUM(D68:D70) -> 7 | F68: 1 | G68: =COUNTIFS('2026年度培训主表'!B:B,A68,'2026年度培训主表'!C:C,B68,'2026年度培训主表'!D:D,C68)/3 -> 6 | H68: =COUNTIFS('2026年度培训主表'!B:B,A68,'2026年度培训主表'!C:C,B68,'2026年度培训主表'!D:D,C68,'2026年度培训主表'!L:L,"已签到")/3/G68 -> 0.5 | I68: =AVERAGEIFS('2026年度培训主表'!S:S,'2026年度培训主表'!B:B,A68,'2026年度培训主表'!C:C,B68,'2026年度培训主表'!D:D,C68,'2026年度培训主表'!L:L,"已签到") -> 86.333333 | J68: =AVERAGEIFS('2026年度培训主表'!R:R,'2026年度培训主表'!B:B,A68,'2026年度培训主表'!C:C,B68,'2026年度培训主表'!D:D,C68,'2026年度培训主表'!L:L,"已签到") -> 5 | K68: =AVERAGEIFS('2026年度培训主表'!Q:Q,'2026年度培训主表'!B:B,A68,'2026年度培训主表'!C:C,B68,'2026年度培训主表'!D:D,C68,'2026年度培训主表'!L:L,"已签到") -> 5 | O68: {=IF($B68="西南总部",SUM(SUMIFS([6]汇总表!D:D,[6]汇总表!$A:$A,{"营业一部","营业二部","营业三部","营业四部","营业五部","营业六部","营业七部"})),IF($B68="湖北",SUM(SUMIFS([6]汇总表!D:D,[6]汇总表!$A:$A,{"湖北1部","湖北2部"})),IF($B68="陕西",SUM(SUMIFS([6]汇总表!D:D,[6]汇总表!$A:$A,{"陕西1部","陕西2部"})),SUMIFS([6]汇总表!D:D,[6]汇总表!$A:$A,$B68&"销售部"))))} -> 1005 | P68: {=IF($B68="西南总部",SUM(SUMIFS([6]汇总表!E:E,[6]汇总表!$A:$A,{"营业一部","营业二部","营业三部","营业四部","营业五部","营业六部","营业七部"})),IF($B68="湖北",SUM(SUMIFS([6]汇总表!E:E,[6]汇总表!$A:$A,{"湖北1部","湖北2部"})),IF($B68="陕西",SUM(SUMIFS([6]汇总表!E:E,[6]汇总表!$A:$A,{"陕西1部","陕西2部"})),SUMIFS([6]汇总表!E:E,[6]汇总表!$A:$A,$B68&"销售部"))))} -> 965 | Q68: =IFERROR(P68/O68,0) -> 0.960199 | R68: {=IF($B68="西南总部",SUM(SUMIFS([6]汇总表!H:H,[6]汇总表!$A:$A,{"营业一部","营业二部","营业三部","营业四部","营业五部","营业六部","营业七部"})),IF($B68="湖北",SUM(SUMIFS([6]汇总表!H:H,[6]汇总表!$A:$A,{"湖北1部","湖北2部"})),IF($B68="陕西",SUM(SUMIFS([6]汇总表!H:H,[6]汇总表!$A:$A,{"陕西1部","陕西2部"})),SUMIFS([6]汇总表!H:H,[6]汇总表!$A:$A,$B68&"销售部"))))} -> 150 | S68: {=IF($B68="西南总部",SUM(SUMIFS([6]汇总表!I:I,[6]汇总表!$A:$A,{"营业一部","营业二部","营业三部","营业四部","营业五部","营业六部","营业七部"})),IF($B68="湖北",SUM(SUMIFS([6]汇总表!I:I,[6]汇总表!$A:$A,{"湖北1部","湖北2部"})),IF($B68="陕西",SUM(SUMIFS([6]汇总表!I:I,[6]汇总表!$A:$A,{"陕西1部","陕西2部"})),SUMIFS([6]汇总表!I:I,[6]汇总表!$A:$A,$B68&"销售部"))))} -> 149 | T68: =IFERROR(S68/R68,0) -> 0.99333333 | U68: {=IF($B68="西南总部",SUM(SUMIFS([6]汇总表!L:L,[6]汇总表!$A:$A,{"营业一部","营业二部","营业三部","营业四部","营业五部","营业六部","营业七部"})),IF($B68="湖北",SUM(SUMIFS([6]汇总表!L:L,[6]汇总表!$A:$A,{"湖北1部","湖北2部"})),IF($B68="陕西",SUM(SUMIFS([6]汇总表!L:L,[6]汇总表!$A:$A,{"陕西1部","陕西2部"})),SUMIFS([6]汇总表!L:L,[6]汇总表!$A:$A,$B68&"销售部"))))} -> 40 | V68: {=IF($B68="西南总部",SUM(SUMIFS([6]汇总表!M:M,[6]汇总表!$A:$A,{"营业一部","营业二部","营业三部","营业四部","营业五部","营业六部","营业七部"})),IF($B68="湖北",SUM(SUMIFS([6]汇总表!M:M,[6]汇总表!$A:$A,{"湖北1部","湖北2部"})),IF($B68="陕西",SUM(SUMIFS([6]汇总表!M:M,[6]汇总表!$A:$A,{"陕西1部","陕西2部"})),SUMIFS([6]汇总表!M:M,[6]汇总表!$A:$A,$B68&"销售部"))))} -> 40 | W68: =IFERROR(V68/U68,0) -> 1
C69: B岗培训 | D69: 5 | F69: 1 | G69: =COUNTIFS('2026年度培训主表'!B:B,A68,'2026年度培训主表'!C:C,B68,'2026年度培训主表'!D:D,C69)/6 -> 1 | H69: =COUNTIFS('2026年度培训主表'!B:B,A68,'2026年度培训主表'!C:C,B68,'2026年度培训主表'!D:D,C69,'2026年度培训主表'!L:L,"已签到")/6/G69 -> 1 | I69: =AVERAGEIFS('2026年度培训主表'!S:S,'2026年度培训主表'!B:B,A68,'2026年度培训主表'!C:C,B68,'2026年度培训主表'!D:D,C69,'2026年度培训主表'!L:L,"已签到") -> 55 | J69: =AVERAGEIFS('2026年度培训主表'!R:R,'2026年度培训主表'!B:B,A68,'2026年度培训主表'!C:C,B68,'2026年度培训主表'!D:D,C69,'2026年度培训主表'!L:L,"已签到") -> 4.1666667 | K69: =AVERAGEIFS('2026年度培训主表'!Q:Q,'2026年度培训主表'!B:B,A68,'2026年度培训主表'!C:C,B68,'2026年度培训主表'!D:D,C69,'2026年度培训主表'!L:L,"已签到") -> 4.1666667
C70: 销售新人入职培训 | D70: 1 | F70: 1 | G70: =COUNTIFS('2026年度培训主表'!B:B,A68,'2026年度培训主表'!C:C,B68,'2026年度培训主表'!D:D,C70)/4 -> 3 | H70: =COUNTIFS('2026年度培训主表'!B:B,A68,'2026年度培训主表'!C:C,B68,'2026年度培训主表'!D:D,C70,'2026年度培训主表'!L:L,"已签到")/4/G70 -> 1 | I70: =AVERAGEIFS('2026年度培训主表'!S:S,'2026年度培训主表'!B:B,A68,'2026年度培训主表'!C:C,B68,'2026年度培训主表'!D:D,C70,'2026年度培训主表'!L:L,"已签到") -> 80.666667 | J70: =AVERAGEIFS('2026年度培训主表'!R:R,'2026年度培训主表'!B:B,A68,'2026年度培训主表'!C:C,B68,'2026年度培训主表'!D:D,C70,'2026年度培训主表'!L:L,"已签到") -> 4.9666667 | K70: =AVERAGEIFS('2026年度培训主表'!Q:Q,'2026年度培训主表'!B:B,A68,'2026年度培训主表'!C:C,B68,'2026年度培训主表'!D:D,C70,'2026年度培训主表'!L:L,"已签到") -> 5
A71: 3月 | B71: 河北 | C71: 销售提升训 | D71: 1 | E71: =SUM(D71:D73) -> 7 | F71: 1 | G71: =COUNTIFS('2026年度培训主表'!B:B,A71,'2026年度培训主表'!C:C,B71,'2026年度培训主表'!D:D,C71)/3 -> 4 | H71: =COUNTIFS('2026年度培训主表'!B:B,A71,'2026年度培训主表'!C:C,B71,'2026年度培训主表'!D:D,C71,'2026年度培训主表'!L:L,"已签到")/3/G71 -> 0.5 | I71: =AVERAGEIFS('2026年度培训主表'!S:S,'2026年度培训主表'!B:B,A71,'2026年度培训主表'!C:C,B71,'2026年度培训主表'!D:D,C71,'2026年度培训主表'!L:L,"已签到") -> 97.333333 | J71: =AVERAGEIFS('2026年度培训主表'!R:R,'2026年度培训主表'!B:B,A71,'2026年度培训主表'!C:C,B71,'2026年度培训主表'!D:D,C71,'2026年度培训主表'!L:L,"已签到") -> 4.1666667 | K71: =AVERAGEIFS('2026年度培训主表'!Q:Q,'2026年度培训主表'!B:B,A71,'2026年度培训主表'!C:C,B71,'2026年度培训主表'!D:D,C71,'2026年度培训主表'!L:L,"已签到") -> 4.1666667 | O71: {=IF($B71="西南总部",SUM(SUMIFS([6]汇总表!D:D,[6]汇总表!$A:$A,{"营业一部","营业二部","营业三部","营业四部","营业五部","营业六部","营业七部"})),IF($B71="湖北",SUM(SUMIFS([6]汇总表!D:D,[6]汇总表!$A:$A,{"湖北1部","湖北2部"})),IF($B71="陕西",SUM(SUMIFS([6]汇总表!D:D,[6]汇总表!$A:$A,{"陕西1部","陕西2部"})),SUMIFS([6]汇总表!D:D,[6]汇总表!$A:$A,$B71&"销售部"))))} -> 425 | P71: {=IF($B71="西南总部",SUM(SUMIFS([6]汇总表!E:E,[6]汇总表!$A:$A,{"营业一部","营业二部","营业三部","营业四部","营业五部","营业六部","营业七部"})),IF($B71="湖北",SUM(SUMIFS([6]汇总表!E:E,[6]汇总表!$A:$A,{"湖北1部","湖北2部"})),IF($B71="陕西",SUM(SUMIFS([6]汇总表!E:E,[6]汇总表!$A:$A,{"陕西1部","陕西2部"})),SUMIFS([6]汇总表!E:E,[6]汇总表!$A:$A,$B71&"销售部"))))} -> 407 | Q71: =IFERROR(P71/O71,0) -> 0.95764706 | R71: {=IF($B71="西南总部",SUM(SUMIFS([6]汇总表!H:H,[6]汇总表!$A:$A,{"营业一部","营业二部","营业三部","营业四部","营业五部","营业六部","营业七部"})),IF($B71="湖北",SUM(SUMIFS([6]汇总表!H:H,[6]汇总表!$A:$A,{"湖北1部","湖北2部"})),IF($B71="陕西",SUM(SUMIFS([6]汇总表!H:H,[6]汇总表!$A:$A,{"陕西1部","陕西2部"})),SUMIFS([6]汇总表!H:H,[6]汇总表!$A:$A,$B71&"销售部"))))} -> 67 | S71: {=IF($B71="西南总部",SUM(SUMIFS([6]汇总表!I:I,[6]汇总表!$A:$A,{"营业一部","营业二部","营业三部","营业四部","营业五部","营业六部","营业七部"})),IF($B71="湖北",SUM(SUMIFS([6]汇总表!I:I,[6]汇总表!$A:$A,{"湖北1部","湖北2部"})),IF($B71="陕西",SUM(SUMIFS([6]汇总表!I:I,[6]汇总表!$A:$A,{"陕西1部","陕西2部"})),SUMIFS([6]汇总表!I:I,[6]汇总表!$A:$A,$B71&"销售部"))))} -> 67 | T71: =IFERROR(S71/R71,0) -> 1 | U71: {=IF($B71="西南总部",SUM(SUMIFS([6]汇总表!L:L,[6]汇总表!$A:$A,{"营业一部","营业二部","营业三部","营业四部","营业五部","营业六部","营业七部"})),IF($B71="湖北",SUM(SUMIFS([6]汇总表!L:L,[6]汇总表!$A:$A,{"湖北1部","湖北2部"})),IF($B71="陕西",SUM(SUMIFS([6]汇总表!L:L,[6]汇总表!$A:$A,{"陕西1部","陕西2部"})),SUMIFS([6]汇总表!L:L,[6]汇总表!$A:$A,$B71&"销售部"))))} -> 16 | V71: {=IF($B71="西南总部",SUM(SUMIFS([6]汇总表!M:M,[6]汇总表!$A:$A,{"营业一部","营业二部","营业三部","营业四部","营业五部","营业六部","营业七部"})),IF($B71="湖北",SUM(SUMIFS([6]汇总表!M:M,[6]汇总表!$A:$A,{"湖北1部","湖北2部"})),IF($B71="陕西",SUM(SUMIFS([6]汇总表!M:M,[6]汇总表!$A:$A,{"陕西1部","陕西2部"})),SUMIFS([6]汇总表!M:M,[6]汇总表!$A:$A,$B71&"销售部"))))} -> 16 | W71: =IFERROR(V71/U71,0) -> 1
C72: B岗培训 | D72: 5 | F72: 1 | G72: =COUNTIFS('2026年度培训主表'!B:B,A71,'2026年度培训主表'!C:C,B71,'2026年度培训主表'!D:D,C72)/6 -> 1 | H72: =COUNTIFS('2026年度培训主表'!B:B,A71,'2026年度培训主表'!C:C,B71,'2026年度培训主表'!D:D,C72,'2026年度培训主表'!L:L,"已签到")/6/G72 -> 1 | I72: =AVERAGEIFS('2026年度培训主表'!S:S,'2026年度培训主表'!B:B,A71,'2026年度培训主表'!C:C,B71,'2026年度培训主表'!D:D,C72,'2026年度培训主表'!L:L,"已签到") -> 56.666667 | J72: =AVERAGEIFS('2026年度培训主表'!R:R,'2026年度培训主表'!B:B,A71,'2026年度培训主表'!C:C,B71,'2026年度培训主表'!D:D,C72,'2026年度培训主表'!L:L,"已签到") -> 4.1666667 | K72: =AVERAGEIFS('2026年度培训主表'!Q:Q,'2026年度培训主表'!B:B,A71,'2026年度培训主表'!C:C,B71,'2026年度培训主表'!D:D,C72,'2026年度培训主表'!L:L,"已签到") -> 4.1666667
C73: 销售新人入职培训 | D73: 1 | F73: 1 | G73: =COUNTIFS('2026年度培训主表'!B:B,A71,'2026年度培训主表'!C:C,B71,'2026年度培训主表'!D:D,C73)/4 -> 4.5 | H73: =COUNTIFS('2026年度培训主表'!B:B,A71,'2026年度培训主表'!C:C,B71,'2026年度培训主表'!D:D,C73,'2026年度培训主表'!L:L,"已签到")/4/G73 -> 0.55555556 | I73: =AVERAGEIFS('2026年度培训主表'!S:S,'2026年度培训主表'!B:B,A71,'2026年度培训主表'!C:C,B71,'2026年度培训主表'!D:D,C73,'2026年度培训主表'!L:L,"已签到") -> 79.4 | J73: =AVERAGEIFS('2026年度培训主表'!R:R,'2026年度培训主表'!B:B,A71,'2026年度培训主表'!C:C,B71,'2026年度培训主表'!D:D,C73,'2026年度培训主表'!L:L,"已签到") -> 4.48 | K73: =AVERAGEIFS('2026年度培训主表'!Q:Q,'2026年度培训主表'!B:B,A71,'2026年度培训主表'!C:C,B71,'2026年度培训主表'!D:D,C73,'2026年度培训主表'!L:L,"已签到") -> 4.425
A74: 3月 | B74: 甘肃 | C74: 销售提升训 | D74: 0 | E74: =SUM(D74:D76) -> 6 | F74: 1 | G74: =COUNTIFS('2026年度培训主表'!B:B,A74,'2026年度培训主表'!C:C,B74,'2026年度培训主表'!D:D,C74)/3 -> 0 | H74: 1 | I74: 0 | J74: 0 | K74: 0 | O74: {=IF($B74="西南总部",SUM(SUMIFS([6]汇总表!D:D,[6]汇总表!$A:$A,{"营业一部","营业二部","营业三部","营业四部","营业五部","营业六部","营业七部"})),IF($B74="湖北",SUM(SUMIFS([6]汇总表!D:D,[6]汇总表!$A:$A,{"湖北1部","湖北2部"})),IF($B74="陕西",SUM(SUMIFS([6]汇总表!D:D,[6]汇总表!$A:$A,{"陕西1部","陕西2部"})),SUMIFS([6]汇总表!D:D,[6]汇总表!$A:$A,$B74&"销售部"))))} -> 104 | P74: {=IF($B74="西南总部",SUM(SUMIFS([6]汇总表!E:E,[6]汇总表!$A:$A,{"营业一部","营业二部","营业三部","营业四部","营业五部","营业六部","营业七部"})),IF($B74="湖北",SUM(SUMIFS([6]汇总表!E:E,[6]汇总表!$A:$A,{"湖北1部","湖北2部"})),IF($B74="陕西",SUM(SUMIFS([6]汇总表!E:E,[6]汇总表!$A:$A,{"陕西1部","陕西2部"})),SUMIFS([6]汇总表!E:E,[6]汇总表!$A:$A,$B74&"销售部"))))} -> 101 | Q74: =IFERROR(P74/O74,0) -> 0.97115385 | R74: {=IF($B74="西南总部",SUM(SUMIFS([6]汇总表!H:H,[6]汇总表!$A:$A,{"营业一部","营业二部","营业三部","营业四部","营业五部","营业六部","营业七部"})),IF($B74="湖北",SUM(SUMIFS([6]汇总表!H:H,[6]汇总表!$A:$A,{"湖北1部","湖北2部"})),IF($B74="陕西",SUM(SUMIFS([6]汇总表!H:H,[6]汇总表!$A:$A,{"陕西1部","陕西2部"})),SUMIFS([6]汇总表!H:H,[6]汇总表!$A:$A,$B74&"销售部"))))} -> 15 | S74: {=IF($B74="西南总部",SUM(SUMIFS([6]汇总表!I:I,[6]汇总表!$A:$A,{"营业一部","营业二部","营业三部","营业四部","营业五部","营业六部","营业七部"})),IF($B74="湖北",SUM(SUMIFS([6]汇总表!I:I,[6]汇总表!$A:$A,{"湖北1部","湖北2部"})),IF($B74="陕西",SUM(SUMIFS([6]汇总表!I:I,[6]汇总表!$A:$A,{"陕西1部","陕西2部"})),SUMIFS([6]汇总表!I:I,[6]汇总表!$A:$A,$B74&"销售部"))))} -> 15 | T74: =IFERROR(S74/R74,0) -> 1 | U74: {=IF($B74="西南总部",SUM(SUMIFS([6]汇总表!L:L,[6]汇总表!$A:$A,{"营业一部","营业二部","营业三部","营业四部","营业五部","营业六部","营业七部"})),IF($B74="湖北",SUM(SUMIFS([6]汇总表!L:L,[6]汇总表!$A:$A,{"湖北1部","湖北2部"})),IF($B74="陕西",SUM(SUMIFS([6]汇总表!L:L,[6]汇总表!$A:$A,{"陕西1部","陕西2部"})),SUMIFS([6]汇总表!L:L,[6]汇总表!$A:$A,$B74&"销售部"))))} -> 4 | V74: {=IF($B74="西南总部",SUM(SUMIFS([6]汇总表!M:M,[6]汇总表!$A:$A,{"营业一部","营业二部","营业三部","营业四部","营业五部","营业六部","营业七部"})),IF($B74="湖北",SUM(SUMIFS([6]汇总表!M:M,[6]汇总表!$A:$A,{"湖北1部","湖北2部"})),IF($B74="陕西",SUM(SUMIFS([6]汇总表!M:M,[6]汇总表!$A:$A,{"陕西1部","陕西2部"})),SUMIFS([6]汇总表!M:M,[6]汇总表!$A:$A,$B74&"销售部"))))} -> 4 | W74: =IFERROR(V74/U74,0) -> 1
C75: B岗培训 | D75: 5 | F75: 1 | G75: =COUNTIFS('2026年度培训主表'!B:B,A74,'2026年度培训主表'!C:C,B74,'2026年度培训主表'!D:D,C75)/6 -> 1.6666667 | H75: =COUNTIFS('2026年度培训主表'!B:B,A74,'2026年度培训主表'!C:C,B74,'2026年度培训主表'!D:D,C75,'2026年度培训主表'!L:L,"已签到")/6/G75 -> 1 | I75: =AVERAGEIFS('2026年度培训主表'!S:S,'2026年度培训主表'!B:B,A74,'2026年度培训主表'!C:C,B74,'2026年度培训主表'!D:D,C75,'2026年度培训主表'!L:L,"已签到") -> 52 | J75: =AVERAGEIFS('2026年度培训主表'!R:R,'2026年度培训主表'!B:B,A74,'2026年度培训主表'!C:C,B74,'2026年度培训主表'!D:D,C75,'2026年度培训主表'!L:L,"已签到") -> 3.5 | K75: =AVERAGEIFS('2026年度培训主表'!Q:Q,'2026年度培训主表'!B:B,A74,'2026年度培训主表'!C:C,B74,'2026年度培训主表'!D:D,C75,'2026年度培训主表'!L:L,"已签到") -> 3.475
C76: 销售新人入职培训 | D76: 1 | F76: 1 | G76: =COUNTIFS('2026年度培训主表'!B:B,A74,'2026年度培训主表'!C:C,B74,'2026年度培训主表'!D:D,C76)/4 -> 1 | H76: =COUNTIFS('2026年度培训主表'!B:B,A74,'2026年度培训主表'!C:C,B74,'2026年度培训主表'!D:D,C76,'2026年度培训主表'!L:L,"已签到")/4/G76 -> 1 | I76: =AVERAGEIFS('2026年度培训主表'!S:S,'2026年度培训主表'!B:B,A74,'2026年度培训主表'!C:C,B74,'2026年度培训主表'!D:D,C76,'2026年度培训主表'!L:L,"已签到") -> 71.5 | J76: =AVERAGEIFS('2026年度培训主表'!R:R,'2026年度培训主表'!B:B,A74,'2026年度培训主表'!C:C,B74,'2026年度培训主表'!D:D,C76,'2026年度培训主表'!L:L,"已签到") -> 0 | K76: =AVERAGEIFS('2026年度培训主表'!Q:Q,'2026年度培训主表'!B:B,A74,'2026年度培训主表'!C:C,B74,'2026年度培训主表'!D:D,C76,'2026年度培训主表'!L:L,"已签到") -> 0
A77: 3月 | B77: 辽宁 | C77: 销售提升训 | D77: 1 | E77: =SUM(D77:D79) -> 2 | F77: 1 | G77: =COUNTIFS('2026年度培训主表'!B:B,A77,'2026年度培训主表'!C:C,B77,'2026年度培训主表'!D:D,C77)/3 -> 2 | H77: =COUNTIFS('2026年度培训主表'!B:B,A77,'2026年度培训主表'!C:C,B77,'2026年度培训主表'!D:D,C77,'2026年度培训主表'!L:L,"已签到")/3/G77 -> 1 | I77: =AVERAGEIFS('2026年度培训主表'!S:S,'2026年度培训主表'!B:B,A77,'2026年度培训主表'!C:C,B77,'2026年度培训主表'!D:D,C77,'2026年度培训主表'!L:L,"已签到") -> 90 | J77: =AVERAGEIFS('2026年度培训主表'!R:R,'2026年度培训主表'!B:B,A77,'2026年度培训主表'!C:C,B77,'2026年度培训主表'!D:D,C77,'2026年度培训主表'!L:L,"已签到") -> 2.5 | K77: =AVERAGEIFS('2026年度培训主表'!Q:Q,'2026年度培训主表'!B:B,A77,'2026年度培训主表'!C:C,B77,'2026年度培训主表'!D:D,C77,'2026年度培训主表'!L:L,"已签到") -> 2.5 | O77: {=IF($B77="西南总部",SUM(SUMIFS([6]汇总表!D:D,[6]汇总表!$A:$A,{"营业一部","营业二部","营业三部","营业四部","营业五部","营业六部","营业七部"})),IF($B77="湖北",SUM(SUMIFS([6]汇总表!D:D,[6]汇总表!$A:$A,{"湖北1部","湖北2部"})),IF($B77="陕西",SUM(SUMIFS([6]汇总表!D:D,[6]汇总表!$A:$A,{"陕西1部","陕西2部"})),SUMIFS([6]汇总表!D:D,[6]汇总表!$A:$A,$B77&"销售部"))))} -> 311 | P77: {=IF($B77="西南总部",SUM(SUMIFS([6]汇总表!E:E,[6]汇总表!$A:$A,{"营业一部","营业二部","营业三部","营业四部","营业五部","营业六部","营业七部"})),IF($B77="湖北",SUM(SUMIFS([6]汇总表!E:E,[6]汇总表!$A:$A,{"湖北1部","湖北2部"})),IF($B77="陕西",SUM(SUMIFS([6]汇总表!E:E,[6]汇总表!$A:$A,{"陕西1部","陕西2部"})),SUMIFS([6]汇总表!E:E,[6]汇总表!$A:$A,$B77&"销售部"))))} -> 286 | Q77: =IFERROR(P77/O77,0) -> 0.91961415 | R77: {=IF($B77="西南总部",SUM(SUMIFS([6]汇总表!H:H,[6]汇总表!$A:$A,{"营业一部","营业二部","营业三部","营业四部","营业五部","营业六部","营业七部"})),IF($B77="湖北",SUM(SUMIFS([6]汇总表!H:H,[6]汇总表!$A:$A,{"湖北1部","湖北2部"})),IF($B77="陕西",SUM(SUMIFS([6]汇总表!H:H,[6]汇总表!$A:$A,{"陕西1部","陕西2部"})),SUMIFS([6]汇总表!H:H,[6]汇总表!$A:$A,$B77&"销售部"))))} -> 46 | S77: {=IF($B77="西南总部",SUM(SUMIFS([6]汇总表!I:I,[6]汇总表!$A:$A,{"营业一部","营业二部","营业三部","营业四部","营业五部","营业六部","营业七部"})),IF($B77="湖北",SUM(SUMIFS([6]汇总表!I:I,[6]汇总表!$A:$A,{"湖北1部","湖北2部"})),IF($B77="陕西",SUM(SUMIFS([6]汇总表!I:I,[6]汇总表!$A:$A,{"陕西1部","陕西2部"})),SUMIFS([6]汇总表!I:I,[6]汇总表!$A:$A,$B77&"销售部"))))} -> 46 | T77: =IFERROR(S77/R77,0) -> 1 | U77: {=IF($B77="西南总部",SUM(SUMIFS([6]汇总表!L:L,[6]汇总表!$A:$A,{"营业一部","营业二部","营业三部","营业四部","营业五部","营业六部","营业七部"})),IF($B77="湖北",SUM(SUMIFS([6]汇总表!L:L,[6]汇总表!$A:$A,{"湖北1部","湖北2部"})),IF($B77="陕西",SUM(SUMIFS([6]汇总表!L:L,[6]汇总表!$A:$A,{"陕西1部","陕西2部"})),SUMIFS([6]汇总表!L:L,[6]汇总表!$A:$A,$B77&"销售部"))))} -> 8 | V77: {=IF($B77="西南总部",SUM(SUMIFS([6]汇总表!M:M,[6]汇总表!$A:$A,{"营业一部","营业二部","营业三部","营业四部","营业五部","营业六部","营业七部"})),IF($B77="湖北",SUM(SUMIFS([6]汇总表!M:M,[6]汇总表!$A:$A,{"湖北1部","湖北2部"})),IF($B77="陕西",SUM(SUMIFS([6]汇总表!M:M,[6]汇总表!$A:$A,{"陕西1部","陕西2部"})),SUMIFS([6]汇总表!M:M,[6]汇总表!$A:$A,$B77&"销售部"))))} -> 8 | W77: =IFERROR(V77/U77,0) -> 1
C78: B岗培训 | D78: 0 | F78: 1 | G78: =COUNTIFS('2026年度培训主表'!B:B,A77,'2026年度培训主表'!C:C,B77,'2026年度培训主表'!D:D,C78)/6 -> 0 | H78: 1 | I78: 0 | J78: 0 | K78: 0
C79: 销售新人入职培训 | D79: 1 | F79: 1 | G79: =COUNTIFS('2026年度培训主表'!B:B,A77,'2026年度培训主表'!C:C,B77,'2026年度培训主表'!D:D,C79)/4 -> 2 | H79: =COUNTIFS('2026年度培训主表'!B:B,A77,'2026年度培训主表'!C:C,B77,'2026年度培训主表'!D:D,C79,'2026年度培训主表'!L:L,"已签到")/4/G79 -> 1 | I79: =AVERAGEIFS('2026年度培训主表'!S:S,'2026年度培训主表'!B:B,A77,'2026年度培训主表'!C:C,B77,'2026年度培训主表'!D:D,C79,'2026年度培训主表'!L:L,"已签到") -> 89.25 | J79: =AVERAGEIFS('2026年度培训主表'!R:R,'2026年度培训主表'!B:B,A77,'2026年度培训主表'!C:C,B77,'2026年度培训主表'!D:D,C79,'2026年度培训主表'!L:L,"已签到") -> 5 | K79: =AVERAGEIFS('2026年度培训主表'!Q:Q,'2026年度培训主表'!B:B,A77,'2026年度培训主表'!C:C,B77,'2026年度培训主表'!D:D,C79,'2026年度培训主表'!L:L,"已签到") -> 5
A80: 3月 | B80: 内蒙古 | C80: 销售提升训 | D80: 1 | E80: =SUM(D80:D82) -> 1 | F80: 1 | G80: =COUNTIFS('2026年度培训主表'!B:B,A80,'2026年度培训主表'!C:C,B80,'2026年度培训主表'!D:D,C80)/3 -> 3 | H80: =COUNTIFS('2026年度培训主表'!B:B,A80,'2026年度培训主表'!C:C,B80,'2026年度培训主表'!D:D,C80,'2026年度培训主表'!L:L,"已签到")/3/G80 -> 1 | I80: =AVERAGEIFS('2026年度培训主表'!S:S,'2026年度培训主表'!B:B,A80,'2026年度培训主表'!C:C,B80,'2026年度培训主表'!D:D,C80,'2026年度培训主表'!L:L,"已签到") -> 88.444444 | J80: =AVERAGEIFS('2026年度培训主表'!R:R,'2026年度培训主表'!B:B,A80,'2026年度培训主表'!C:C,B80,'2026年度培训主表'!D:D,C80,'2026年度培训主表'!L:L,"已签到") -> 5 | K80: =AVERAGEIFS('2026年度培训主表'!Q:Q,'2026年度培训主表'!B:B,A80,'2026年度培训主表'!C:C,B80,'2026年度培训主表'!D:D,C80,'2026年度培训主表'!L:L,"已签到") -> 5 | O80: {=IF($B80="西南总部",SUM(SUMIFS([6]汇总表!D:D,[6]汇总表!$A:$A,{"营业一部","营业二部","营业三部","营业四部","营业五部","营业六部","营业七部"})),IF($B80="湖北",SUM(SUMIFS([6]汇总表!D:D,[6]汇总表!$A:$A,{"湖北1部","湖北2部"})),IF($B80="陕西",SUM(SUMIFS([6]汇总表!D:D,[6]汇总表!$A:$A,{"陕西1部","陕西2部"})),SUMIFS([6]汇总表!D:D,[6]汇总表!$A:$A,$B80&"销售部"))))} -> 81 | P80: {=IF($B80="西南总部",SUM(SUMIFS([6]汇总表!E:E,[6]汇总表!$A:$A,{"营业一部","营业二部","营业三部","营业四部","营业五部","营业六部","营业七部"})),IF($B80="湖北",SUM(SUMIFS([6]汇总表!E:E,[6]汇总表!$A:$A,{"湖北1部","湖北2部"})),IF($B80="陕西",SUM(SUMIFS([6]汇总表!E:E,[6]汇总表!$A:$A,{"陕西1部","陕西2部"})),SUMIFS([6]汇总表!E:E,[6]汇总表!$A:$A,$B80&"销售部"))))} -> 72 | Q80: =IFERROR(P80/O80,0) -> 0.88888889 | R80: {=IF($B80="西南总部",SUM(SUMIFS([6]汇总表!H:H,[6]汇总表!$A:$A,{"营业一部","营业二部","营业三部","营业四部","营业五部","营业六部","营业七部"})),IF($B80="湖北",SUM(SUMIFS([6]汇总表!H:H,[6]汇总表!$A:$A,{"湖北1部","湖北2部"})),IF($B80="陕西",SUM(SUMIFS([6]汇总表!H:H,[6]汇总表!$A:$A,{"陕西1部","陕西2部"})),SUMIFS([6]汇总表!H:H,[6]汇总表!$A:$A,$B80&"销售部"))))} -> 12 | S80: {=IF($B80="西南总部",SUM(SUMIFS([6]汇总表!I:I,[6]汇总表!$A:$A,{"营业一部","营业二部","营业三部","营业四部","营业五部","营业六部","营业七部"})),IF($B80="湖北",SUM(SUMIFS([6]汇总表!I:I,[6]汇总表!$A:$A,{"湖北1部","湖北2部"})),IF($B80="陕西",SUM(SUMIFS([6]汇总表!I:I,[6]汇总表!$A:$A,{"陕西1部","陕西2部"})),SUMIFS([6]汇总表!I:I,[6]汇总表!$A:$A,$B80&"销售部"))))} -> 11 | T80: =IFERROR(S80/R80,0) -> 0.91666667 | U80: {=IF($B80="西南总部",SUM(SUMIFS([6]汇总表!L:L,[6]汇总表!$A:$A,{"营业一部","营业二部","营业三部","营业四部","营业五部","营业六部","营业七部"})),IF($B80="湖北",SUM(SUMIFS([6]汇总表!L:L,[6]汇总表!$A:$A,{"湖北1部","湖北2部"})),IF($B80="陕西",SUM(SUMIFS([6]汇总表!L:L,[6]汇总表!$A:$A,{"陕西1部","陕西2部"})),SUMIFS([6]汇总表!L:L,[6]汇总表!$A:$A,$B80&"销售部"))))} -> 4 | V80: {=IF($B80="西南总部",SUM(SUMIFS([6]汇总表!M:M,[6]汇总表!$A:$A,{"营业一部","营业二部","营业三部","营业四部","营业五部","营业六部","营业七部"})),IF($B80="湖北",SUM(SUMIFS([6]汇总表!M:M,[6]汇总表!$A:$A,{"湖北1部","湖北2部"})),IF($B80="陕西",SUM(SUMIFS([6]汇总表!M:M,[6]汇总表!$A:$A,{"陕西1部","陕西2部"})),SUMIFS([6]汇总表!M:M,[6]汇总表!$A:$A,$B80&"销售部"))))} -> 4 | W80: =IFERROR(V80/U80,0) -> 1
C81: B岗培训 | D81: 0 | F81: 1 | G81: =COUNTIFS('2026年度培训主表'!B:B,A80,'2026年度培训主表'!C:C,B80,'2026年度培训主表'!D:D,C81)/6 -> 0 | H81: 1 | I81: 0 | J81: 0 | K81: 0
C82: 销售新人入职培训 | D82: 0 | F82: 1 | G82: =COUNTIFS('2026年度培训主表'!B:B,A82,'2026年度培训主表'!C:C,B82,'2026年度培训主表'!D:D,C82)/3 -> 0 | H82: 1 | I82: 0 | J82: 0 | K82: 0
A83: 3月 | B83: 山西 | C83: 销售提升训 | D83: 1 | E83: =SUM(D83:D85) -> 6 | F83: 1 | G83: =COUNTIFS('2026年度培训主表'!B:B,A83,'2026年度培训主表'!C:C,B83,'2026年度培训主表'!D:D,C83)/3 -> 7 | H83: =COUNTIFS('2026年度培训主表'!B:B,A83,'2026年度培训主表'!C:C,B83,'2026年度培训主表'!D:D,C83,'2026年度培训主表'!L:L,"已签到")/3/G83 -> 1 | I83: =AVERAGEIFS('2026年度培训主表'!S:S,'2026年度培训主表'!B:B,A83,'2026年度培训主表'!C:C,B83,'2026年度培训主表'!D:D,C83,'2026年度培训主表'!L:L,"已签到") -> 93.190476 | J83: =AVERAGEIFS('2026年度培训主表'!R:R,'2026年度培训主表'!B:B,A83,'2026年度培训主表'!C:C,B83,'2026年度培训主表'!D:D,C83,'2026年度培训主表'!L:L,"已签到") -> 5 | K83: =AVERAGEIFS('2026年度培训主表'!Q:Q,'2026年度培训主表'!B:B,A83,'2026年度培训主表'!C:C,B83,'2026年度培训主表'!D:D,C83,'2026年度培训主表'!L:L,"已签到") -> 5 | O83: {=IF($B83="西南总部",SUM(SUMIFS([6]汇总表!D:D,[6]汇总表!$A:$A,{"营业一部","营业二部","营业三部","营业四部","营业五部","营业六部","营业七部"})),IF($B83="湖北",SUM(SUMIFS([6]汇总表!D:D,[6]汇总表!$A:$A,{"湖北1部","湖北2部"})),IF($B83="陕西",SUM(SUMIFS([6]汇总表!D:D,[6]汇总表!$A:$A,{"陕西1部","陕西2部"})),SUMIFS([6]汇总表!D:D,[6]汇总表!$A:$A,$B83&"销售部"))))} -> 968 | P83: {=IF($B83="西南总部",SUM(SUMIFS([6]汇总表!E:E,[6]汇总表!$A:$A,{"营业一部","营业二部","营业三部","营业四部","营业五部","营业六部","营业七部"})),IF($B83="湖北",SUM(SUMIFS([6]汇总表!E:E,[6]汇总表!$A:$A,{"湖北1部","湖北2部"})),IF($B83="陕西",SUM(SUMIFS([6]汇总表!E:E,[6]汇总表!$A:$A,{"陕西1部","陕西2部"})),SUMIFS([6]汇总表!E:E,[6]汇总表!$A:$A,$B83&"销售部"))))} -> 928 | Q83: =IFERROR(P83/O83,0) -> 0.95867769 | R83: {=IF($B83="西南总部",SUM(SUMIFS([6]汇总表!H:H,[6]汇总表!$A:$A,{"营业一部","营业二部","营业三部","营业四部","营业五部","营业六部","营业七部"})),IF($B83="湖北",SUM(SUMIFS([6]汇总表!H:H,[6]汇总表!$A:$A,{"湖北1部","湖北2部"})),IF($B83="陕西",SUM(SUMIFS([6]汇总表!H:H,[6]汇总表!$A:$A,{"陕西1部","陕西2部"})),SUMIFS([6]汇总表!H:H,[6]汇总表!$A:$A,$B83&"销售部"))))} -> 142 | S83: {=IF($B83="西南总部",SUM(SUMIFS([6]汇总表!I:I,[6]汇总表!$A:$A,{"营业一部","营业二部","营业三部","营业四部","营业五部","营业六部","营业七部"})),IF($B83="湖北",SUM(SUMIFS([6]汇总表!I:I,[6]汇总表!$A:$A,{"湖北1部","湖北2部"})),IF($B83="陕西",SUM(SUMIFS([6]汇总表!I:I,[6]汇总表!$A:$A,{"陕西1部","陕西2部"})),SUMIFS([6]汇总表!I:I,[6]汇总表!$A:$A,$B83&"销售部"))))} -> 136 | T83: =IFERROR(S83/R83,0) -> 0.95774648 | U83: {=IF($B83="西南总部",SUM(SUMIFS([6]汇总表!L:L,[6]汇总表!$A:$A,{"营业一部","营业二部","营业三部","营业四部","营业五部","营业六部","营业七部"})),IF($B83="湖北",SUM(SUMIFS([6]汇总表!L:L,[6]汇总表!$A:$A,{"湖北1部","湖北2部"})),IF($B83="陕西",SUM(SUMIFS([6]汇总表!L:L,[6]汇总表!$A:$A,{"陕西1部","陕西2部"})),SUMIFS([6]汇总表!L:L,[6]汇总表!$A:$A,$B83&"销售部"))))} -> 32 | V83: {=IF($B83="西南总部",SUM(SUMIFS([6]汇总表!M:M,[6]汇总表!$A:$A,{"营业一部","营业二部","营业三部","营业四部","营业五部","营业六部","营业七部"})),IF($B83="湖北",SUM(SUMIFS([6]汇总表!M:M,[6]汇总表!$A:$A,{"湖北1部","湖北2部"})),IF($B83="陕西",SUM(SUMIFS([6]汇总表!M:M,[6]汇总表!$A:$A,{"陕西1部","陕西2部"})),SUMIFS([6]汇总表!M:M,[6]汇总表!$A:$A,$B83&"销售部"))))} -> 31 | W83: =IFERROR(V83/U83,0) -> 0.96875
C84: B岗培训 | D84: 5 | F84: 1 | G84: =COUNTIFS('2026年度培训主表'!B:B,A83,'2026年度培训主表'!C:C,B83,'2026年度培训主表'!D:D,C84)/6 -> 1 | H84: =COUNTIFS('2026年度培训主表'!B:B,A83,'2026年度培训主表'!C:C,B83,'2026年度培训主表'!D:D,C84,'2026年度培训主表'!L:L,"已签到")/6/G84 -> 1 | I84: =AVERAGEIFS('2026年度培训主表'!S:S,'2026年度培训主表'!B:B,A83,'2026年度培训主表'!C:C,B83,'2026年度培训主表'!D:D,C84,'2026年度培训主表'!L:L,"已签到") -> 45 | J84: =AVERAGEIFS('2026年度培训主表'!R:R,'2026年度培训主表'!B:B,A83,'2026年度培训主表'!C:C,B83,'2026年度培训主表'!D:D,C84,'2026年度培训主表'!L:L,"已签到") -> 5 | K84: =AVERAGEIFS('2026年度培训主表'!Q:Q,'2026年度培训主表'!B:B,A83,'2026年度培训主表'!C:C,B83,'2026年度培训主表'!D:D,C84,'2026年度培训主表'!L:L,"已签到") -> 5
C85: 销售新人入职培训 | D85: 0 | F85: 1 | G85: =COUNTIFS('2026年度培训主表'!B:B,A85,'2026年度培训主表'!C:C,B85,'2026年度培训主表'!D:D,C85)/3 -> 0 | H85: 1 | I85: 0 | J85: 0 | K85: 0

Sheet 自主培训2026年度数据（累计）
A1: 自主培训(1-2月） | P1: 月份 | Q1: 城市 | R1: 自主培训
A2: 地区 | B2: 月份 | C2: 培训日期 | D2: 项目经理 | E2: 营业部 | F2: 项目名称 | G2: 培训课程 | H2: 讲师满意度 | I2: 已签到人数 | J2: 是否合格 | K2: APP签到 | L2: 笔记上传 | M2: 满意度反馈 | R2: 应培训场次（累计） 经理数*3 | S2: 培训场次（累计） | T2: 培训人数（累计） | U2: 合格场次数 | V2: 考核经理合格率 （合格场次/应培训场次）
A3: 西南总部 | B3: 1月 | C3: 46053 | D3: 杨威 | E3: 营业五部 | F3: 丽都国际 | G3: 项目各阶段朋友圈内容 | H3: 4.9333333 | I3: 3 | J3: 合格 | K3: √ | L3: √ | M3: √ | P3: 1月 | Q3: 西南总部 | R3: =VLOOKUP(Q3,'[2]自主培训2026年度数据（累计）'!$Q:$R,2,0) -> 162 | S3: 169 | T3: 732 | U3: 161 | V3: =U3/R3 -> 0.99382716
A4: 西南总部 | B4: 1月 | C4: 46053 | D4: 杨威 | E4: 营业五部 | F4: 丽都国际 | G4: 优秀的车位置业顾问的5要素 | H4: 4.8666667 | I4: 3 | J4: 合格 | K4: √ | L4: √ | M4: √ | P4: 1月 | Q4: 湖北 | R4: =VLOOKUP(Q4,'[2]自主培训2026年度数据（累计）'!$Q:$R,2,0) -> 42 | S4: 38 | T4: 125 | U4: 39 | V4: =U4/R4 -> 0.92857143
A5: 西南总部 | B5: 1月 | C5: 46053 | D5: 文鹏羽 | E5: 营业二部 | F5: 御府观澜阁 | G5: 加微信阶段注意事项 | H5: 5 | I5: 3 | J5: 合格 | K5: √ | L5: √ | M5: √ | P5: 1月 | Q5: 甘肃 | R5: =VLOOKUP(Q5,'[2]自主培训2026年度数据（累计）'!$Q:$R,2,0) -> 3 | S5: 9 | T5: 33 | U5: 3 | V5: 1
A6: 西南总部 | B6: 1月 | C6: 46053 | D6: 文鹏羽 | E6: 营业二部 | F6: 御府观澜阁 | G6: 回话的技术 | H6: 5 | I6: 3 | J6: 合格 | K6: √ | L6: √ | M6: √ | P6: 1月 | Q6: 湖南 | R6: =VLOOKUP(Q6,'[2]自主培训2026年度数据（累计）'!$Q:$R,2,0) -> 36 | S6: 37 | T6: 119 | U6: 36 | V6: 1
A7: 西南总部 | B7: 1月 | C7: 46053 | D7: 刘鹏 | E7: 营业七部 | F7: 海德花园 | G7: 带看流程 | H7: 5 | I7: 2 | J7: 合格 | K7: √ | L7: √ | M7: √ | P7: 1月 | Q7: 陕西 | R7: =VLOOKUP(Q7,'[2]自主培训2026年度数据（累计）'!$Q:$R,2,0) -> 57 | S7: 56 | T7: 214 | U7: 56 | V7: =U7/R7 -> 0.98245614
A8: 湖北 | B8: 1月 | C8: 46053 | D8: 阮阳 | E8: 湖北1部 | F8: 滨湖壹号 | G8: 逼定和放价技巧 | H8: 5 | I8: 2 | J8: 合格 | K8: √ | L8: √ | M8: √ | P8: 1月 | Q8: 河北 | R8: =VLOOKUP(Q8,'[2]自主培训2026年度数据（累计）'!$Q:$R,2,0) -> 12 | S8: 12 | T8: 32 | U8: 12 | V8: 1
A9: 西南总部 | B9: 1月 | C9: 46045 | D9: 柏刚 | E9: 营业二部 | F9: 山水福都北区 | G9: 成功销售之优势谈判 | H9: 5 | I9: 3 | J9: 合格 | K9: √ | L9: √ | M9: √ | P9: 1月 | Q9: 山东 | R9: =VLOOKUP(Q9,'[2]自主培训2026年度数据（累计）'!$Q:$R,2,0) -> 30 | S9: 31 | T9: 119 | U9: 30 | V9: 1
A10: 湖北 | B10: 1月 | C10: 46053 | D10: 阮阳 | E10: 湖北1部 | F10: 滨湖壹号 | G10: 顾问式销售技巧 | H10: 5 | I10: 2 | J10: 合格 | K10: √ | L10: √ | M10: √ | P10: 1月 | Q10: 河南 | R10: =VLOOKUP(Q10,'[2]自主培训2026年度数据（累计）'!$Q:$R,2,0) -> 21 | S10: 19 | T10: 95 | U10: 19 | V10: =U10/R10 -> 0.9047619
A11: 湖北 | B11: 1月 | C11: 46053 | D11: 李文 | E11: 湖北1部 | F11: 恒大翡翠华庭 | G11: 项目不得不买的理由培训 | H11: 5 | I11: 3 | J11: 合格 | K11: √ | L11: √ | M11: √ | P11: 1月 | Q11: 山西 | R11: =VLOOKUP(Q11,'[2]自主培训2026年度数据（累计）'!$Q:$R,2,0) -> 24 | S11: 23 | T11: 108 | U11: 23 | V11: =U11/R11 -> 0.95833333
A12: 湖北 | B12: 1月 | C12: 46053 | D12: 陈晓辉 | E12: 湖北2部 | F12: 澜桥公馆 | G12: 客户预期管理 | H12: 5 | I12: 3 | J12: 合格 | K12: √ | L12: √ | M12: √ | P12: 1月 | Q12: 内蒙古 | R12: =VLOOKUP(Q12,'[2]自主培训2026年度数据（累计）'!$Q:$R,2,0) -> 6 | S12: 6 | T12: 21 | U12: 6 | V12: 1
A13: 湖北 | B13: 1月 | C13: 46053 | D13: 陈晓辉 | E13: 湖北2部 | F13: 澜桥公馆 | G13: 成功销售之优势谈判 | H13: 5 | I13: 3 | J13: 合格 | K13: √ | L13: √ | M13: √ | P13: 1月 | Q13: 辽宁 | R13: 3 | S13: 3 | T13: 15 | U13: 3 | V13: 1
A14: 湖北 | B14: 1月 | C14: 46053 | D14: 陈晓辉 | E14: 湖北2部 | F14: 澜桥公馆 | G14: 带看流程的培训 | H14: 5 | I14: 3 | J14: 合格 | K14: √ | L14: √ | M14: √ | P14: 合计 | R14: 399 | S14: 399 | T14: 1613 | U14: 388 | V14: =U14/R14 -> 0.97243108
A15: 西南总部 | B15: 1月 | C15: 46053 | D15: 张萍2 | E15: 营业五部 | F15: 南充市香槟尚城 | G15: 业主关系维护技巧 | H15: 5 | I15: 5 | J15: 合格 | K15: √ | L15: √ | M15: √ | P15: 2月 | Q15: 西南总部 | R15: 110 | S15: 112 | T15: 467 | U15: 108 | V15: =U15/R15 -> 0.98181818
A16: 湖北 | B16: 1月 | C16: 46053 | D16: 李文 | E16: 湖北1部 | F16: 恒大翡翠华庭 | G16: 项目SWOT培训 | H16: 5 | I16: 3 | J16: 合格 | K16: √ | L16: √ | M16: √ | P16: 2月 | Q16: 湖北 | R16: 26 | S16: 24 | T16: 74 | U16: 24 | V16: =U16/R16 -> 0.92307692
A17: 湖北 | B17: 1月 | C17: 46053 | D17: 李文 | E17: 湖北1部 | F17: 恒大翡翠华庭 | G17: 带看流程标准培训 | H17: 5 | I17: 3 | J17: 合格 | K17: √ | L17: √ | M17: √ | P17: 2月 | Q17: 甘肃 | R17: 2 | S17: 2 | T17: 28 | U17: 2 | V17: =U17/R17 -> 1
A18: 甘肃 | B18: 1月 | C18: 46053 | D18: 王辉 | E18: 甘肃销售部 | F18: 金悦府 | G18: 客户成交技巧 | H18: 5 | I18: 4 | J18: 合格 | K18: √ | L18: √ | M18: √ | P18: 2月 | Q18: 湖南 | R18: 22 | S18: 22 | T18: 70 | U18: 22 | V18: =U18/R18 -> 1
A19: 湖南 | B19: 1月 | C19: 46053 | D19: 杨超群 | E19: 湖南销售部 | F19: 雅典名媛 | G19: 签约培训 | H19: 5 | I19: 3 | J19: 合格 | K19: √ | L19: √ | M19: √ | P19: 2月 | Q19: 陕西 | R19: 38 | S19: 38 | T19: 141 | U19: 38 | V19: =U19/R19 -> 1
A20: 陕西 | B20: 1月 | C20: 46053 | D20: 李耀 | E20: 陕西2部 | F20: 滨江花城营销中心 | G20: 销售就是一场心理战 | H20: 5 | I20: 9 | J20: 合格 | K20: √ | L20: √ | M20: √ | P20: 2月 | Q20: 河北 | R20: 8 | S20: 6 | T20: 22 | U20: 8 | V20: =U20/R20 -> 1
A21: 陕西 | B21: 1月 | C21: 46053 | D21: 蒙建 | E21: 陕西2部 | F21: 万科大都会物业办 | G21: 销售心理学实战应用 | H21: 5 | I21: 3 | J21: 合格 | K21: √ | L21: √ | M21: √ | P21: 2月 | Q21: 山东 | R21: 20 | S21: 19 | T21: 59 | U21: 20 | V21: =U21/R21 -> 1
A22: 湖南 | B22: 1月 | C22: 46053 | D22: 刘元发 | E22: 湖南销售部 | F22: 鸿大第六区 | G22: 项目合同签订POS机使用培训 | H22: 5 | I22: 4 | J22: 合格 | K22: √ | L22: √ | M22: √ | P22: 2月 | Q22: 河南 | R22: 14 | S22: 15 | T22: 66 | U22: 14 | V22: =U22/R22 -> 1
A23: 湖南 | B23: 1月 | C23: 46053 | D23: 杨超群 | E23: 湖南销售部 | F23: 雅典铭苑 | G23: 怎样应对业主说之前价格低现在价格高 | H23: 5 | I23: 3 | J23: 合格 | K23: √ | L23: √ | M23: √ | P23: 2月 | Q23: 山西 | R23: 16 | S23: 17 | T23: 80 | U23: 16 | V23: =U23/R23 -> 1
A24: 河北 | B24: 1月 | C24: 46053 | D24: 陈东2 | E24: 河北销售部 | F24: 河北金惠华苑小区 | G24: 项目撤场阶段后续处理事项 | H24: 5 | I24: 3 | J24: 合格 | K24: √ | L24: √ | M24: √ | P24: 2月 | Q24: 内蒙古 | R24: 2 | S24: 2 | T24: 3 | U24: 2 | V24: =U24/R24 -> 1
A25: 山东 | B25: 1月 | C25: 46053 | D25: 王杰 | E25: 山东销售部 | F25: 龙域天城 | G25: 项目基础知识培训 | H25: 5 | I25: 4 | J25: 合格 | K25: √ | L25: √ | M25: √ | P25: 2月 | Q25: 辽宁 | R25: 4 | S25: 4 | T25: 14 | U25: 4 | V25: =U25/R25 -> 1
A26: 陕西 | B26: 1月 | C26: 46053 | D26: 李耀 | E26: 陕西2部 | F26: 滨江花城营销中心 | G26: 为啥销冠一直有业绩 | H26: 5 | I26: 5 | J26: 合格 | K26: √ | L26: √ | M26: √ | P26: 合计 | R26: =SUM(R15:R25) -> 262 | S26: =SUM(S15:S25) -> 261 | T26: =SUM(T15:T25) -> 1024 | U26: =SUM(U15:U25) -> 258 | V26: =U26/R26 -> 0.98473282
A27: 河南 | B27: 1月 | C27: 46053 | D27: 叶鑫 | E27: 河南销售部 | F27: 世博领秀城 | G27: 如何加好微信 | H27: 5 | I27: 1 | J27: 合格 | K27: √ | L27: √ | M27: √
A28: 河南 | B28: 1月 | C28: 46053 | D28: 叶鑫 | E28: 河南销售部 | F28: 世博领秀城 | G28: 业主关系维护 | H28: 5 | I28: 1 | J28: 合格 | K28: √ | L28: √ | M28: √
A29: 湖北 | B29: 1月 | C29: 46053 | D29: 张宗铭 | E29: 湖北1部 | F29: 天纵.半岛蓝湾2期 | G29: 外呼邀约技巧培训 | H29: 5 | I29: 1 | J29: 合格 | K29: √ | L29: √ | M29: √
A30: 陕西 | B30: 1月 | C30: 46053 | D30: 冀敏 | E30: 陕西2部 | F30: 公园天下 | G30: 项目介绍视频培训 | H30: 5 | I30: 3 | J30: 合格 | K30: √ | L30: √ | M30: √
A31: 湖北 | B31: 1月 | C31: 46053 | D31: 张宗铭 | E31: 湖北1部 | F31: 天纵.半岛蓝湾2期 | G31: 外呼加微信技巧培训 | H31: 5 | I31: 1 | J31: 合格 | K31: √ | L31: √ | M31: √
A32: 陕西 | B32: 1月 | C32: 46053 | D32: 李耀 | E32: 陕西2部 | F32: 滨江花城营销中心 | G32: 销售必备的5种思维 | H32: 5 | I32: 5 | J32: 合格 | K32: √ | L32: √ | M32: √
A33: 湖北 | B33: 1月 | C33: 46053 | D33: 张宗铭 | E33: 湖北1部 | F33: 天纵.半岛蓝湾2期 | G33: app服务费录入 | H33: 5 | I33: 1 | J33: 合格 | K33: √ | L33: √ | M33: √
A34: 西南总部 | B34: 1月 | C34: 46053 | D34: 贾萍 | E34: 营业四部 | F34: 云尚花园 | G34: 签合同流程培 | H34: 5 | I34: 2 | J34: 合格 | K34: √ | L34: √ | M34: √
A35: 西南总部 | B35: 1月 | C35: 46053 | D35: 陶再阳 | E35: 营业三部 | F35: 荣城天街 | G35: 朋友圈运营 | H35: 5 | I35: 3 | J35: 合格 | K35: √ | L35: √ | M35: √
A36: 陕西 | B36: 1月 | C36: 46053 | D36: 张英 | E36: 陕西1部 | F36: 项目办公室 | G36: 签约流程培训 | H36: 5 | I36: 4 | J36: 合格 | K36: √ | L36: √ | M36: √
A37: 西南总部 | B37: 1月 | C37: 46053 | D37: 刘亮 | E37: 营业四部 | F37: 领地东原阅城 | G37: 探出客户的真实需求 | H37: 5 | I37: 4 | J37: 合格 | K37: √ | L37: √ | M37: √
A38: 甘肃 | B38: 1月 | C38: 46053 | D38: 王辉 | E38: 甘肃销售部 | F38: 金悦府项目 | G38: 如何做好微信营销 | H38: 5 | I38: 4 | J38: 合格 | K38: √ | L38: √ | M38: √
... A662: 河南 | B662: 2月 | C662: 46063 | D662: 张萍 | E662: 河南销售部 | F662: 兰台府 | G662: 成为卓越销售五大要素 | H662: 5 | I662: 4 | J662: 合格 | K662: √ | L662: √ | M662: √

Sheet 2026年度培训主表
A1: 2026年培训数据总表-明细（1-3月）
A2: 序号 | B2: 月份 | C2: 城市 | D2: 课程类型 | E2: 课程名称 | F2: 讲师 | G2: 培训方式 | H2: 培训地点 | I2: 考核方式 | J2: 培训时间 | K2: 应参训人姓名 | L2: 签到情况 | M2: 工号 | N2: 营业部 | O2: 职级 | P2: 入职时间 | Q2: 课程满意度 | R2: 讲师满意度 | S2: 考核成绩
A3: 1 | B3: 1月 | C3: 西南总部 | D3: 销售提升训 | E3: 《心态与成败》 | F3: 梁霞 | G3: 线下 | H3: 1212 | I3: app试卷考核 | J3: 46035 | K3: 蒋婷 | L3: 未签到 | M3: 01011 | N3: 营业五部 | O3: 一星销售顾问 | P3: 45970 | Q3: 0 | R3: 0 | S3: 0
A4: 2 | B4: 1月 | C4: 西南总部 | D4: 销售提升训 | E4: 《心态与成败》 | F4: 梁霞 | G4: 线下 | H4: 1212 | I4: app试卷考核 | J4: 46035 | K4: 孙智港 | L4: 未签到 | M4: 01423 | N4: 营业五部 | O4: 一星销售顾问 | P4: 45749 | Q4: 0 | R4: 0 | S4: 0
A5: 3 | B5: 1月 | C5: 西南总部 | D5: 销售提升训 | E5: 《心态与成败》 | F5: 梁霞 | G5: 线下 | H5: 1212 | I5: app试卷考核 | J5: 46035 | K5: 李裕楷 | L5: 未签到 | M5: 01412 | N5: 营业五部 | O5: 一星销售顾问 | P5: 45747 | Q5: 0 | R5: 0 | S5: 0
A6: 4 | B6: 1月 | C6: 西南总部 | D6: 销售提升训 | E6: 《心态与成败》 | F6: 梁霞 | G6: 线下 | H6: 1212 | I6: app试卷考核 | J6: 46035 | K6: 税小蓉 | L6: 已签到 | M6: 01684 | N6: 营业二部 | O6: 一星销售顾问 | P6: 45905 | Q6: 5 | R6: 5 | S6: 107
A7: 5 | B7: 1月 | C7: 陕西 | D7: 销售提升训 | E7: 《心态与成败》 | F7: 梁霞 | G7: 线下 | H7: 1212 | I7: app试卷考核 | J7: 46035 | K7: 李松 | L7: 已签到 | M7: 01689 | N7: 陕西2部 | O7: 一星销售顾问 | P7: 45910 | Q7: 5 | R7: 5 | S7: 94
A8: 6 | B8: 1月 | C8: 西南总部 | D8: 销售提升训 | E8: 《心态与成败》 | F8: 梁霞 | G8: 线下 | H8: 1212 | I8: app试卷考核 | J8: 46035 | K8: 先波 | L8: 未签到 | M8: 01512 | N8: 营业一部 | O8: 二星销售顾问 | P8: 45812 | Q8: 0 | R8: 0 | S8: 0
A9: 7 | B9: 1月 | C9: 西南总部 | D9: 销售提升训 | E9: 《心态与成败》 | F9: 梁霞 | G9: 线下 | H9: 1212 | I9: app试卷考核 | J9: 46035 | K9: 田丰 | L9: 未签到 | M9: 01500 | N9: 营业七部 | O9: 一星销售顾问 | P9: 45804 | Q9: 0 | R9: 0 | S9: 0
A10: 8 | B10: 1月 | C10: 西南总部 | D10: 销售提升训 | E10: 《心态与成败》 | F10: 梁霞 | G10: 线下 | H10: 1212 | I10: app试卷考核 | J10: 46035 | K10: 邓孝礼 | L10: 已签到 | M10: 01621 | N10: 营业四部 | O10: 一星销售顾问 | P10: 45864 | Q10: 5 | R10: 5 | S10: 87
A11: 9 | B11: 1月 | C11: 湖北 | D11: 销售提升训 | E11: 《心态与成败》 | F11: 梁霞 | G11: 线下 | H11: 1212 | I11: app试卷考核 | J11: 46035 | K11: 黄建 | L11: 未签到 | M11: 01657 | N11: 湖北1部 | O11: 一星销售顾问 | P11: 45883 | Q11: 0 | R11: 0 | S11: 0
A12: 10 | B12: 1月 | C12: 西南总部 | D12: 销售提升训 | E12: 《心态与成败》 | F12: 梁霞 | G12: 线下 | H12: 1212 | I12: app试卷考核 | J12: 46035 | K12: 向巡 | L12: 未签到 | M12: 01634 | N12: 营业四部 | O12: 一星销售顾问 | P12: 45872 | Q12: 0 | R12: 0 | S12: 0
A13: 11 | B13: 1月 | C13: 西南总部 | D13: 销售提升训 | E13: 《心态与成败》 | F13: 梁霞 | G13: 线下 | H13: 1212 | I13: app试卷考核 | J13: 46035 | K13: 陈帅2 | L13: 未签到 | M13: 01488 | N13: 营业四部 | O13: 二星销售顾问 | P13: 45794 | Q13: 0 | R13: 0 | S13: 0
A14: 12 | B14: 1月 | C14: 陕西 | D14: 销售提升训 | E14: 《心态与成败》 | F14: 梁霞 | G14: 线下 | H14: 1212 | I14: app试卷考核 | J14: 46035 | K14: 涂正丽 | L14: 未签到 | M14: 01654 | N14: 陕西2部 | O14: 一星销售顾问 | P14: 45881 | Q14: 0 | R14: 0 | S14: 0
... A248: 246 | B248: 1月 | C248: 西南总部 | D248: 销售提升训 | E248: 《如何剖析客户心理》 | F248: 欧松林 | G248: 线下 | H248: 1212 | I248: app试卷考核 | J248: 46035 | K248: 向明镜 | L248: 已签到 | M248: 01265 | N248: 营业一部 | O248: 二星销售顾问 | P248: 45666 | Q248: 5 | R248: 5 | S248: 89
A249: 247 | B249: 1月 | C249: 山西 | D249: B岗培训 | E249: 《采购＋广告＋财务》 | F249: 李旭 | G249: 线上 | H249: 项目上 | I249: 学习地图考核 | J249: 46031 | K249: 赵龙 | L249: 已签到 | M249: 00996 | N249: 山西销售部 | O249: 三星销售顾问 | P249: 45502 | Q249: 5 | R249: 5 | S249: 0
A250: 248 | B250: 1月 | C250: 西南总部 | D250: B岗培训 | E250: 《采购＋广告＋财务》 | F250: 李旭 | G250: 线上 | H250: 项目上 | I250: 学习地图考核 | J250: 46031 | K250: 扈岭楠 | L250: 已签到 | M250: 00798 | N250: 营业三部 | O250: 一星销售顾问 | P250: 45269 | Q250: 5 | R250: 5 | S250: 0
A251: 249 | B251: 1月 | C251: 山东 | D251: B岗培训 | E251: 《采购＋广告＋财务》 | F251: 李旭 | G251: 线上 | H251: 项目上 | I251: 学习地图考核 | J251: 46031 | K251: 周涛 | L251: 已签到 | M251: 00869 | N251: 山东销售部 | O251: B岗经理 | P251: 45400 | Q251: 5 | R251: 5 | S251: 0
A252: 250 | B252: 1月 | C252: 西南总部 | D252: B岗培训 | E252: 《采购＋广告＋财务》 | F252: 蒋明霞 | G252: 线上 | H252: 项目上 | I252: 学习地图考核 | J252: 46031 | K252: 李海艳 | L252: 已签到 | M252: 01344 | N252: 营业三部 | O252: 二星销售顾问 | P252: 45706 | Q252: 5 | R252: 5 | S252: 0
A253: 251 | B253: 1月 | C253: 湖南 | D253: B岗培训 | E253: 《采购＋广告＋财务》 | F253: 蒋明霞 | G253: 线上 | H253: 项目上 | I253: 学习地图考核 | J253: 46031 | K253: 罗敏 | L253: 已签到 | M253: 00134 | N253: 湖南销售部 | O253: B岗经理 | P253: 44351 | Q253: 0 | R253: 0 | S253: 0
A254: 252 | B254: 1月 | C254: 西南总部 | D254: B岗培训 | E254: 《采购＋广告＋财务》 | F254: 蒋明霞 | G254: 线上 | H254: 项目上 | I254: 学习地图考核 | J254: 46031 | K254: 张圣梁 | L254: 已签到 | M254: 01047 | N254: 营业一部 | O254: B岗经理 | P254: 45545 | Q254: 0 | R254: 0 | S254: 0
A255: 253 | B255: 1月 | C255: 西南总部 | D255: B岗培训 | E255: 《采购＋广告＋财务》 | F255: 蒋明霞 | G255: 线上 | H255: 项目上 | I255: 学习地图考核 | J255: 46031 | K255: 郑雄 | L255: 已签到 | M255: 01456 | N255: 营业六部 | O255: B岗经理 | P255: 45763 | Q255: 0 | R255: 0 | S255: 0
A256: 254 | B256: 1月 | C256: 湖南 | D256: B岗培训 | E256: 《采购＋广告＋财务》 | F256: 蒋明霞 | G256: 线上 | H256: 项目上 | I256: 学习地图考核 | J256: 46031 | K256: 夏富杨 | L256: 已签到 | M256: 01317 | N256: 湖南销售部 | O256: 二星销售顾问 | P256: 45699 | Q256: 5 | R256: 5 | S256: 0
A257: 255 | B257: 1月 | C257: 西南总部 | D257: B岗培训 | E257: 《采购＋广告＋财务》 | F257: 蒋明霞 | G257: 线上 | H257: 项目上 | I257: 学习地图考核 | J257: 46031 | K257: 张萍2 | L257: 已签到 | M257: 01257 | N257: 营业五部 | O257: B岗经理 | P257: 45661 | Q257: 0 | R257: 0 | S257: 0
A258: 256 | B258: 1月 | C258: 西南总部 | D258: B岗培训 | E258: 《采购＋广告＋财务》 | F258: 蒋明霞 | G258: 线上 | H258: 项目上 | I258: 学习地图考核 | J258: 46031 | K258: 张萍 | L258: 已签到 | M258: 01166 | N258: 营业五部 | O258: 三星销售顾问 | P258: 45604 | Q258: 5 | R258: 5 | S258: 0
A259: 257 | B259: 1月 | C259: 西南总部 | D259: B岗培训 | E259: 《采购＋广告＋财务》 | F259: 李芙蓉 | G259: 线上 | H259: 项目上 | I259: 学习地图考核 | J259: 46031 | K259: 周远芮 | L259: 已签到 | M259: 01284 | N259: 营业五部 | O259: B岗经理 | P259: 45698 | Q259: 5 | R259: 5 | S259: 0
A260: 258 | B260: 1月 | C260: 西南总部 | D260: B岗培训 | E260: 《采购＋广告＋财务》 | F260: 李芙蓉 | G260: 线上 | H260: 项目上 | I260: 学习地图考核 | J260: 46031 | K260: 陶再阳 | L260: 已签到 | M260: 01271 | N260: 营业三部 | O260: B岗经理 | P260: 45669 | Q260: 5 | R260: 5 | S260: 0
... A268: 266 | B268: 1月 | C268: 陕西 | D268: B岗培训 | E268: 《采购＋广告＋财务》 | F268: 李芙蓉 | G268: 线上 | H268: 项目上 | I268: 学习地图考核 | J268: 46031 | K268: 马少波 | L268: 已签到 | M268: 01148 | N268: 陕西2部 | O268: 三星销售顾问 | P268: 45599 | Q268: 5 | R268: 5 | S268: 0
A269: 267 | B269: 1月 | C269: 山东 | D269: B岗培训 | E269: 《项目带看管理》 | F269: 刘盼 | G269: 线下 | H269: 1212 | I269: 学习地图考核 | J269: 46037 | K269: 周涛 | L269: 已签到 | M269: 00869 | N269: 山东销售部 | O269: B岗经理 | P269: 45400 | Q269: 5 | R269: 5 | S269: 0
A270: 268 | B270: 1月 | C270: 西南总部 | D270: B岗培训 | E270: 《项目带看管理》 | F270: 刘盼 | G270: 线下 | H270: 1212 | I270: 学习地图考核 | J270: 46037 | K270: 郑雄 | L270: 已签到 | M270: 01456 | N270: 营业六部 | O270: B岗经理 | P270: 45763 | Q270: 5 | R270: 5 | S270: 0
A271: 269 | B271: 1月 | C271: 西南总部 | D271: B岗培训 | E271: 《项目带看管理》 | F271: 刘盼 | G271: 线下 | H271: 1212 | I271: 学习地图考核 | J271: 46037 | K271: 张圣梁 | L271: 已签到 | M271: 01047 | N271: 营业一部 | O271: B岗经理 | P271: 45545 | Q271: 5 | R271: 5 | S271: 0
A272: 270 | B272: 1月 | C272: 西南总部 | D272: B岗培训 | E272: 《项目带看管理》 | F272: 刘盼 | G272: 线下 | H272: 1212 | I272: 学习地图考核 | J272: 46037 | K272: 陶再阳 | L272: 已签到 | M272: 01271 | N272: 营业三部 | O272: B岗经理 | P272: 45669 | Q272: 5 | R272: 5 | S272: 0
A273: 271 | B273: 1月 | C273: 湖南 | D273: B岗培训 | E273: 《项目带看管理》 | F273: 刘盼 | G273: 线下 | H273: 1212 | I273: 学习地图考核 | J273: 46037 | K273: 罗敏 | L273: 已签到 | M273: 00134 | N273: 湖南销售部 | O273: B岗经理 | P273: 44351 | Q273: 0 | R273: 0 | S273: 0
A274: 272 | B274: 1月 | C274: 西南总部 | D274: B岗培训 | E274: 《项目带看管理》 | F274: 刘盼 | G274: 线下 | H274: 1212 | I274: 学习地图考核 | J274: 46037 | K274: 李海艳 | L274: 已签到 | M274: 01344 | N274: 营业三部 | O274: 二星销售顾问 | P274: 45706 | Q274: 5 | R274: 5 | S274: 0
A275: 273 | B275: 1月 | C275: 山西 | D275: B岗培训 | E275: 《项目带看管理》 | F275: 刘盼 | G275: 线下 | H275: 1212 | I275: 学习地图考核 | J275: 46037 | K275: 赵龙 | L275: 已签到 | M275: 00996 | N275: 山西销售部 | O275: 三星销售顾问 | P275: 45502 | Q275: 5 | R275: 5 | S275: 0
A276: 274 | B276: 1月 | C276: 西南总部 | D276: B岗培训 | E276: 《项目带看管理》 | F276: 刘盼 | G276: 线下 | H276: 1212 | I276: 学习地图考核 | J276: 46037 | K276: 谢敏 | L276: 已签到 | M276: 00349 | N276: 营业五部 | O276: 三星实习经理 | P276: 44725 | Q276: 0 | R276: 0 | S276: 0
A277: 275 | B277: 1月 | C277: 西南总部 | D277: B岗培训 | E277: 《项目带看管理》 | F277: 刘盼 | G277: 线下 | H277: 1212 | I277: 学习地图考核 | J277: 46037 | K277: 张萍2 | L277: 已签到 | M277: 01257 | N277: 营业五部 | O277: B岗经理 | P277: 45661 | Q277: 0 | R277: 0 | S277: 0
A278: 276 | B278: 1月 | C278: 西南总部 | D278: B岗培训 | E278: 《项目带看管理》 | F278: 刘盼 | G278: 线下 | H278: 1212 | I278: 学习地图考核 | J278: 46037 | K278: 周远芮 | L278: 已签到 | M278: 01284 | N278: 营业五部 | O278: B岗经理 | P278: 45698 | Q278: 5 | R278: 5 | S278: 0
A279: 277 | B279: 1月 | C279: 湖北 | D279: B岗培训 | E279: 《项目带看管理》 | F279: 刘盼 | G279: 线下 | H279: 1212 | I279: 学习地图考核 | J279: 46037 | K279: 阮阳 | L279: 已签到 | M279: 01239 | N279: 湖北1部 | O279: 三星销售顾问 | P279: 45649 | Q279: 5 | R279: 5 | S279: 0
A280: 278 | B280: 1月 | C280: 山东 | D280: B岗培训 | E280: 《项目带看管理》 | F280: 刘盼 | G280: 线下 | H280: 1212 | I280: 学习地图考核 | J280: 46037 | K280: 吴江平 | L280: 已签到 | M280: 00898 | N280: 山东销售部 | O280: B岗经理 | P280: 45427 | Q280: 5 | R280: 5 | S280: 0
... A761: 759 | B761: 1月 | C761: 西南总部 | D761: 销售新人入职培训 | E761: 《走进蜂族科技》 | F761: 黄芳 | G761: 线下 | H761: 1212 | I761: app试卷考核 | J761: 46051 | K761: 李青松 | L761: 未签到 | M761: 01821 | N761: 营业一部 | O761: 实习销售 | P761: 45992 | Q761: 0 | R761: 0 | S761: 0
A762: 760 | B762: 2月 | C762: 宁夏 | D762: 讲师《TTT》培训 | E762: 《讲师TTT培训》 | F762: 张振华 | G762: 线下 | H762: 1212 | I762: 无 | J762: 46077 | K762: 黄小东 | L762: 已签到 | M762: =VLOOKUP(K762,[4]在职!$A:$B,2,0) -> 00215 | N762: 宁夏拓展中心 | O762: =VLOOKUP(K762,[4]在职!$A:$I,9,0) -> 区域拓展总监 | P762: =VLOOKUP(K762,[4]在职!$A:$D,4,0) -> 44525 | Q762: 0 | R762: 0 | S762: 0
A763: 761 | B763: 2月 | C763: =VLOOKUP(K763,[4]在职!$A:$E,5,0) -> 西南总部 | D763: 讲师《TTT》培训 | E763: 《讲师TTT培训》 | F763: 张振华 | G763: 线下 | H763: 1212 | I763: 无 | J763: 46077 | K763: 蒋婉萍 | L763: 已签到 | M763: =VLOOKUP(K763,[4]在职!$A:$B,2,0) -> 00745 | N763: =VLOOKUP(K763,[4]在职!$A:$G,7,0) -> 川北 | O763: =VLOOKUP(K763,[4]在职!$A:$I,9,0) -> 区域拓展总监 | P763: =VLOOKUP(K763,[4]在职!$A:$D,4,0) -> 44522 | Q763: 0 | R763: 0 | S763: 0
A764: 762 | B764: 2月 | C764: =VLOOKUP(K764,[4]在职!$A:$E,5,0) -> 集团职能 | D764: 讲师《TTT》培训 | E764: 《讲师TTT培训》 | F764: 张振华 | G764: 线下 | H764: 1212 | I764: 无 | J764: 46077 | K764: 孔群慧 | L764: 已签到 | M764: =VLOOKUP(K764,[4]在职!$A:$B,2,0) -> 01918 | N764: 职能营销 | O764: =VLOOKUP(K764,[4]在职!$A:$I,9,0) -> 人资行政经理 | P764: =VLOOKUP(K764,[4]在职!$A:$D,4,0) -> 46048 | Q764: 0 | R764: 0 | S764: 0
A765: 763 | B765: 2月 | C765: =VLOOKUP(K765,[4]在职!$A:$E,5,0) -> 河北 | D765: 讲师《TTT》培训 | E765: 《讲师TTT培训》 | F765: 张振华 | G765: 线下 | H765: 1212 | I765: 无 | J765: 46077 | K765: 李港一 | L765: 已签到 | M765: =VLOOKUP(K765,[4]在职!$A:$B,2,0) -> 00008 | N765: =VLOOKUP(K765,[4]在职!$A:$G,7,0) -> 0 | O765: =VLOOKUP(K765,[4]在职!$A:$I,9,0) -> 分公司副总经理 | P765: =VLOOKUP(K765,[4]在职!$A:$D,4,0) -> 43598 | Q765: 0 | R765: 0 | S765: 0
A766: 764 | B766: 2月 | C766: =VLOOKUP(K766,[4]在职!$A:$E,5,0) -> 陕西 | D766: 讲师《TTT》培训 | E766: 《讲师TTT培训》 | F766: 张振华 | G766: 线下 | H766: 1212 | I766: 无 | J766: 46077 | K766: 李耀 | L766: 已签到 | M766: =VLOOKUP(K766,[4]在职!$A:$B,2,0) -> 00077 | N766: =VLOOKUP(K766,[4]在职!$A:$G,7,0) -> 陕西2部 | O766: =VLOOKUP(K766,[4]在职!$A:$I,9,0) -> 部长 | P766: =VLOOKUP(K766,[4]在职!$A:$D,4,0) -> 44088 | Q766: 0 | R766: 0 | S766: 0
A767: 765 | B767: 2月 | C767: =VLOOKUP(K767,[4]在职!$A:$E,5,0) -> 湖南 | D767: 讲师《TTT》培训 | E767: 《讲师TTT培训》 | F767: 张振华 | G767: 线下 | H767: 1212 | I767: 无 | J767: 46077 | K767: 刘进 | L767: 已签到 | M767: =VLOOKUP(K767,[4]在职!$A:$B,2,0) -> 00050 | N767: =VLOOKUP(K767,[4]在职!$A:$G,7,0) -> 湖南销售部 | O767: =VLOOKUP(K767,[4]在职!$A:$I,9,0) -> 分公司副总经理 | P767: =VLOOKUP(K767,[4]在职!$A:$D,4,0) -> 43997 | Q767: 0 | R767: 0 | S767: 0
A768: 766 | B768: 2月 | C768: =VLOOKUP(K768,[4]在职!$A:$E,5,0) -> 河南 | D768: 讲师《TTT》培训 | E768: 《讲师TTT培训》 | F768: 张振华 | G768: 线下 | H768: 1212 | I768: 无 | J768: 46077 | K768: 周吉双 | L768: 已签到 | M768: =VLOOKUP(K768,[4]在职!$A:$B,2,0) -> 00270 | N768: =VLOOKUP(K768,[4]在职!$A:$G,7,0) -> 河南销售部 | O768: =VLOOKUP(K768,[4]在职!$A:$I,9,0) -> 部长 | P768: =VLOOKUP(K768,[4]在职!$A:$D,4,0) -> 44555 | Q768: 0 | R768: 0 | S768: 0
A769: 767 | B769: 2月 | C769: =VLOOKUP(K769,[4]在职!$A:$E,5,0) -> 河北 | D769: 讲师《TTT》培训 | E769: 《讲师TTT培训》 | F769: 张振华 | G769: 线下 | H769: 1212 | I769: 无 | J769: 46077 | K769: 韩旭 | L769: 已签到 | M769: =VLOOKUP(K769,[4]在职!$A:$B,2,0) -> 00263 | N769: =VLOOKUP(K769,[4]在职!$A:$G,7,0) -> 河北销售部 | O769: =VLOOKUP(K769,[4]在职!$A:$I,9,0) -> 一星正式经理 | P769: =VLOOKUP(K769,[4]在职!$A:$D,4,0) -> 44552 | Q769: 0 | R769: 0 | S769: 0
A770: 768 | B770: 2月 | C770: 河北 | D770: 讲师《TTT》培训 | E770: 《讲师TTT培训》 | F770: 张振华 | G770: 线下 | H770: 1212 | I770: 无 | J770: 46077 | K770: 黄伟 | L770: 已签到 | M770: =VLOOKUP(K770,[4]在职!$A:$B,2,0) -> 00043 | N770: 河北拓展部 | O770: =VLOOKUP(K770,[4]在职!$A:$I,9,0) -> 分公司总经理 | P770: =VLOOKUP(K770,[4]在职!$A:$D,4,0) -> 43516 | Q770: 0 | R770: 0 | S770: 0
A771: 769 | B771: 2月 | C771: =VLOOKUP(K771,[4]在职!$A:$E,5,0) -> 辽宁 | D771: 讲师《TTT》培训 | E771: 《讲师TTT培训》 | F771: 张振华 | G771: 线下 | H771: 1212 | I771: 无 | J771: 46077 | K771: 赖慧 | L771: 已签到 | M771: =VLOOKUP(K771,[4]在职!$A:$B,2,0) -> 00016 | N771: =VLOOKUP(K771,[4]在职!$A:$G,7,0) -> 0 | O771: =VLOOKUP(K771,[4]在职!$A:$I,9,0) -> 分公司副总经理 | P771: =VLOOKUP(K771,[4]在职!$A:$D,4,0) -> 43904 | Q771: 0 | R771: 0 | S771: 0
A772: 770 | B772: 2月 | C772: =VLOOKUP(K772,[4]在职!$A:$E,5,0) -> 甘肃 | D772: 讲师《TTT》培训 | E772: 《讲师TTT培训》 | F772: 张振华 | G772: 线下 | H772: 1212 | I772: 无 | J772: 46077 | K772: 雷鸣 | L772: 已签到 | M772: =VLOOKUP(K772,[4]在职!$A:$B,2,0) -> 00248 | N772: 甘肃拓展部 | O772: =VLOOKUP(K772,[4]在职!$A:$I,9,0) -> 区域拓展总监 | P772: =VLOOKUP(K772,[4]在职!$A:$D,4,0) -> 44546 | Q772: 0 | R772: 0 | S772: 0
A773: 771 | B773: 2月 | C773: =VLOOKUP(K773,[4]在职!$A:$E,5,0) -> 陕西 | D773: 讲师《TTT》培训 | E773: 《讲师TTT培训》 | F773: 张振华 | G773: 线下 | H773: 1212 | I773: 无 | J773: 46077 | K773: 李丝丝 | L773: 已签到 | M773: =VLOOKUP(K773,[4]在职!$A:$B,2,0) -> 00090 | N773: =VLOOKUP(K773,[4]在职!$A:$G,7,0) -> 陕西1部 | O773: =VLOOKUP(K773,[4]在职!$A:$I,9,0) -> 部长 | P773: =VLOOKUP(K773,[4]在职!$A:$D,4,0) -> 44153 | Q773: 0 | R773: 0 | S773: 0
A774: 772 | B774: 2月 | C774: =VLOOKUP(K774,[4]在职!$A:$E,5,0) -> 陕西 | D774: 讲师《TTT》培训 | E774: 《讲师TTT培训》 | F774: 张振华 | G774: 线下 | H774: 1212 | I774: 无 | J774: 46077 | K774: 廖小朋 | L774: 已签到 | M774: =VLOOKUP(K774,[4]在职!$A:$B,2,0) -> 00009 | N774: 陕西1部 | O774: =VLOOKUP(K774,[4]在职!$A:$I,9,0) -> 分公司总经理 | P774: =VLOOKUP(K774,[4]在职!$A:$D,4,0) -> 43602 | Q774: 0 | R774: 0 | S774: 0
A775: 773 | B775: 2月 | C775: =VLOOKUP(K775,[4]在职!$A:$E,5,0) -> 集团职能 | D775: 讲师《TTT》培训 | E775: 《讲师TTT培训》 | F775: 张振华 | G775: 线下 | H775: 1212 | I775: 无 | J775: 46077 | K775: 杨薇 | L775: 已签到 | M775: =VLOOKUP(K775,[4]在职!$A:$B,2,0) -> 00456 | N775: 职能营销 | O775: =VLOOKUP(K775,[4]在职!$A:$I,9,0) -> 运营经理 | P775: =VLOOKUP(K775,[4]在职!$A:$D,4,0) -> 44865 | Q775: 0 | R775: 0 | S775: 0
A776: 774 | B776: 2月 | C776: =VLOOKUP(K776,[4]在职!$A:$E,5,0) -> 西南总部 | D776: 讲师《TTT》培训 | E776: 《讲师TTT培训》 | F776: 张振华 | G776: 线下 | H776: 1212 | I776: 无 | J776: 46077 | K776: 刘超 | L776: 已签到 | M776: =VLOOKUP(K776,[4]在职!$A:$B,2,0) -> 00029 | N776: =VLOOKUP(K776,[4]在职!$A:$G,7,0) -> 川东 | O776: =VLOOKUP(K776,[4]在职!$A:$I,9,0) -> 区域拓展总监 | P776: =VLOOKUP(K776,[4]在职!$A:$D,4,0) -> 43833 | Q776: 0 | R776: 0 | S776: 0
A777: 775 | B777: 2月 | C777: =VLOOKUP(K777,[4]在职!$A:$E,5,0) -> 集团职能 | D777: 讲师《TTT》培训 | E777: 《讲师TTT培训》 | F777: 张振华 | G777: 线下 | H777: 1212 | I777: 无 | J777: 46077 | K777: 张亚东 | L777: 已签到 | M777: =VLOOKUP(K777,[4]在职!$A:$B,2,0) -> 00120 | N777: 职能营销 | O777: =VLOOKUP(K777,[4]在职!$A:$I,9,0) -> 技术总监 | P777: =VLOOKUP(K777,[4]在职!$A:$D,4,0) -> 44298 | Q777: 0 | R777: 0 | S777: 0
A778: 776 | B778: 2月 | C778: =VLOOKUP(K778,[4]在职!$A:$E,5,0) -> 西南总部 | D778: 讲师《TTT》培训 | E778: 《讲师TTT培训》 | F778: 张振华 | G778: 线下 | H778: 1212 | I778: 无 | J778: 46077 | K778: 肖秀丽 | L778: 已签到 | M778: =VLOOKUP(K778,[4]在职!$A:$B,2,0) -> 00204 | N778: =VLOOKUP(K778,[4]在职!$A:$G,7,0) -> 营业三部 | O778: =VLOOKUP(K778,[4]在职!$A:$I,9,0) -> 二星正式经理 | P778: =VLOOKUP(K778,[4]在职!$A:$D,4,0) -> 44504 | Q778: 0 | R778: 0 | S778: 0
A779: 777 | B779: 2月 | C779: =VLOOKUP(K779,[4]在职!$A:$E,5,0) -> 湖北 | D779: 讲师《TTT》培训 | E779: 《讲师TTT培训》 | F779: 张振华 | G779: 线下 | H779: 1212 | I779: 无 | J779: 46077 | K779: 范庚 | L779: 已签到 | M779: =VLOOKUP(K779,[4]在职!$A:$B,2,0) -> 00004 | N779: 湖北1部 | O779: =VLOOKUP(K779,[4]在职!$A:$I,9,0) -> 分公司总经理 | P779: =VLOOKUP(K779,[4]在职!$A:$D,4,0) -> 43519 | Q779: 0 | R779: 0 | S779: 0
A780: 778 | B780: 2月 | C780: =VLOOKUP(K780,[4]在职!$A:$E,5,0) -> 西南总部 | D780: 讲师《TTT》培训 | E780: 《讲师TTT培训》 | F780: 张振华 | G780: 线下 | H780: 1212 | I780: 无 | J780: 46077 | K780: 雷小金 | L780: 已签到 | M780: =VLOOKUP(K780,[4]在职!$A:$B,2,0) -> 00011 | N780: =VLOOKUP(K780,[4]在职!$A:$G,7,0) -> 营业一部 | O780: =VLOOKUP(K780,[4]在职!$A:$I,9,0) -> 部长 | P780: =VLOOKUP(K780,[4]在职!$A:$D,4,0) -> 43743 | Q780: 0 | R780: 0 | S780: 0
A781: 779 | B781: 2月 | C781: =VLOOKUP(K781,[4]在职!$A:$E,5,0) -> 集团职能 | D781: 讲师《TTT》培训 | E781: 《讲师TTT培训》 | F781: 张振华 | G781: 线下 | H781: 1212 | I781: 无 | J781: 46077 | K781: 刘文宇 | L781: 已签到 | M781: =VLOOKUP(K781,[4]在职!$A:$B,2,0) -> 00003 | N781: 职能营销 | O781: =VLOOKUP(K781,[4]在职!$A:$I,9,0) -> 风控总监 | P781: =VLOOKUP(K781,[4]在职!$A:$D,4,0) -> 43466 | Q781: 0 | R781: 0 | S781: 0
A782: 780 | B782: 2月 | C782: =VLOOKUP(K782,[4]在职!$A:$E,5,0) -> 内蒙古 | D782: 讲师《TTT》培训 | E782: 《讲师TTT培训》 | F782: 张振华 | G782: 线下 | H782: 1212 | I782: 无 | J782: 46077 | K782: 刘宇 | L782: 已签到 | M782: =VLOOKUP(K782,[4]在职!$A:$B,2,0) -> 00154 | N782: 内蒙古拓展中心 | O782: =VLOOKUP(K782,[4]在职!$A:$I,9,0) -> 分公司总经理 | P782: =VLOOKUP(K782,[4]在职!$A:$D,4,0) -> 44415 | Q782: 0 | R782: 0 | S782: 0
A783: 781 | B783: 2月 | C783: =VLOOKUP(K783,[4]在职!$A:$E,5,0) -> 山西 | D783: 讲师《TTT》培训 | E783: 《讲师TTT培训》 | F783: 张振华 | G783: 线下 | H783: 1212 | I783: 无 | J783: 46077 | K783: 吴志虎 | L783: 已签到 | M783: =VLOOKUP(K783,[4]在职!$A:$B,2,0) -> 00160 | N783: =VLOOKUP(K783,[4]在职!$A:$G,7,0) -> 山西销售部 | O783: =VLOOKUP(K783,[4]在职!$A:$I,9,0) -> 部长 | P783: =VLOOKUP(K783,[4]在职!$A:$D,4,0) -> 44420 | Q783: 0 | R783: 0 | S783: 0
A784: 782 | B784: 2月 | C784: =VLOOKUP(K784,[4]在职!$A:$E,5,0) -> 西南总部 | D784: 讲师《TTT》培训 | E784: 《讲师TTT培训》 | F784: 张振华 | G784: 线下 | H784: 1212 | I784: 无 | J784: 46077 | K784: 杨科 | L784: 已签到 | M784: =VLOOKUP(K784,[4]在职!$A:$B,2,0) -> 00012 | N784: =VLOOKUP(K784,[4]在职!$A:$G,7,0) -> 营业五部 | O784: =VLOOKUP(K784,[4]在职!$A:$I,9,0) -> 二星正式经理 | P784: =VLOOKUP(K784,[4]在职!$A:$D,4,0) -> 43757 | Q784: 0 | R784: 0 | S784: 0
A785: 783 | B785: 2月 | C785: =VLOOKUP(K785,[4]在职!$A:$E,5,0) -> 西南总部 | D785: 讲师《TTT》培训 | E785: 《讲师TTT培训》 | F785: 张振华 | G785: 线下 | H785: 1212 | I785: 无 | J785: 46077 | K785: 杨蓉 | L785: 已签到 | M785: =VLOOKUP(K785,[4]在职!$A:$B,2,0) -> 00770 | N785: =VLOOKUP(K785,[4]在职!$A:$G,7,0) -> 川西 | O785: =VLOOKUP(K785,[4]在职!$A:$I,9,0) -> 区域拓展总监 | P785: =VLOOKUP(K785,[4]在职!$A:$D,4,0) -> 45244 | Q785: 0 | R785: 0 | S785: 0
A786: 784 | B786: 2月 | C786: =VLOOKUP(K786,[4]在职!$A:$E,5,0) -> 西南总部 | D786: 讲师《TTT》培训 | E786: 《讲师TTT培训》 | F786: 张振华 | G786: 线下 | H786: 1212 | I786: 无 | J786: 46077 | K786: 于强 | L786: 已签到 | M786: =VLOOKUP(K786,[4]在职!$A:$B,2,0) -> 00416 | N786: =VLOOKUP(K786,[4]在职!$A:$G,7,0) -> 川南 | O786: =VLOOKUP(K786,[4]在职!$A:$I,9,0) -> 区域拓展总监 | P786: =VLOOKUP(K786,[4]在职!$A:$D,4,0) -> 44805 | Q786: 0 | R786: 0 | S786: 0
A787: 785 | B787: 2月 | C787: =VLOOKUP(K787,[4]在职!$A:$E,5,0) -> 西南总部 | D787: 讲师《TTT》培训 | E787: 《讲师TTT培训》 | F787: 张振华 | G787: 线下 | H787: 1212 | I787: 无 | J787: 46077 | K787: 向高涵 | L787: 已签到 | M787: =VLOOKUP(K787,[4]在职!$A:$B,2,0) -> 00590 | N787: =VLOOKUP(K787,[4]在职!$A:$G,7,0) -> 川东 | O787: =VLOOKUP(K787,[4]在职!$A:$I,9,0) -> 二星拓展专员 | P787: =VLOOKUP(K787,[4]在职!$A:$D,4,0) -> 44982 | Q787: 0 | R787: 0 | S787: 0
A788: 786 | B788: 2月 | C788: =VLOOKUP(K788,[4]在职!$A:$E,5,0) -> 湖南 | D788: 讲师《TTT》培训 | E788: 《讲师TTT培训》 | F788: 张振华 | G788: 线下 | H788: 1212 | I788: 无 | J788: 46077 | K788: 刘岷 | L788: 已签到 | M788: =VLOOKUP(K788,[4]在职!$A:$B,2,0) -> 00235 | N788: 湖南拓展部 | O788: =VLOOKUP(K788,[4]在职!$A:$I,9,0) -> 二星拓展专员 | P788: =VLOOKUP(K788,[4]在职!$A:$D,4,0) -> 44543 | Q788: 0 | R788: 0 | S788: 0
A789: 787 | B789: 2月 | C789: =VLOOKUP(K789,[4]在职!$A:$E,5,0) -> 西南总部 | D789: 讲师《TTT》培训 | E789: 《讲师TTT培训》 | F789: 张振华 | G789: 线下 | H789: 1212 | I789: 无 | J789: 46077 | K789: 程新浩 | L789: 已签到 | M789: =VLOOKUP(K789,[4]在职!$A:$B,2,0) -> 00345 | N789: =VLOOKUP(K789,[4]在职!$A:$G,7,0) -> 营业七部 | O789: =VLOOKUP(K789,[4]在职!$A:$I,9,0) -> 部长 | P789: =VLOOKUP(K789,[4]在职!$A:$D,4,0) -> 44721 | Q789: 0 | R789: 0 | S789: 0
A790: 788 | B790: 2月 | C790: =VLOOKUP(K790,[4]在职!$A:$E,5,0) -> 集团职能 | D790: 讲师《TTT》培训 | E790: 《讲师TTT培训》 | F790: 张振华 | G790: 线下 | H790: 1212 | I790: 无 | J790: 46077 | K790: 梁霞 | L790: 已签到 | M790: =VLOOKUP(K790,[4]在职!$A:$B,2,0) -> 00585 | N790: 职能营销 | O790: =VLOOKUP(K790,[4]在职!$A:$I,9,0) -> 业绩增长部经理 | P790: =VLOOKUP(K790,[4]在职!$A:$D,4,0) -> 44978 | Q790: 0 | R790: 0 | S790: 0
A791: 789 | B791: 2月 | C791: =VLOOKUP(K791,[4]在职!$A:$E,5,0) -> 集团职能 | D791: 讲师《TTT》培训 | E791: 《讲师TTT培训》 | F791: 张振华 | G791: 线下 | H791: 1212 | I791: 无 | J791: 46077 | K791: 黄洁 | L791: 已签到 | M791: =VLOOKUP(K791,[4]在职!$A:$B,2,0) -> 00828 | N791: 职能营销 | O791: =VLOOKUP(K791,[4]在职!$A:$I,9,0) -> 教培主管 | P791: =VLOOKUP(K791,[4]在职!$A:$D,4,0) -> 45345 | Q791: 0 | R791: 0 | S791: 0
A792: 790 | B792: 2月 | C792: =VLOOKUP(K792,[4]在职!$A:$E,5,0) -> 西南总部 | D792: 讲师《TTT》培训 | E792: 《讲师TTT培训》 | F792: 张振华 | G792: 线下 | H792: 1212 | I792: 无 | J792: 46077 | K792: 毛富林 | L792: 已签到 | M792: =VLOOKUP(K792,[4]在职!$A:$B,2,0) -> 00087 | N792: =VLOOKUP(K792,[4]在职!$A:$G,7,0) -> 营业六部 | O792: =VLOOKUP(K792,[4]在职!$A:$I,9,0) -> 部长 | P792: =VLOOKUP(K792,[4]在职!$A:$D,4,0) -> 44139 | Q792: 0 | R792: 0 | S792: 0
A793: 791 | B793: 2月 | C793: =VLOOKUP(K793,[4]在职!$A:$E,5,0) -> 河南 | D793: 讲师《TTT》培训 | E793: 《讲师TTT培训》 | F793: 张振华 | G793: 线下 | H793: 1212 | I793: 无 | J793: 46077 | K793: 毛孝树 | L793: 已签到 | M793: =VLOOKUP(K793,[4]在职!$A:$B,2,0) -> 00010 | N793: =VLOOKUP(K793,[4]在职!$A:$G,7,0) -> 0 | O793: =VLOOKUP(K793,[4]在职!$A:$I,9,0) -> 分公司副总经理 | P793: =VLOOKUP(K793,[4]在职!$A:$D,4,0) -> 43743 | Q793: 0 | R793: 0 | S793: 0
A794: 792 | B794: 2月 | C794: =VLOOKUP(K794,[4]在职!$A:$E,5,0) -> 山东 | D794: 讲师《TTT》培训 | E794: 《讲师TTT培训》 | F794: 张振华 | G794: 线下 | H794: 1212 | I794: 无 | J794: 46077 | K794: 苏晓青 | L794: 已签到 | M794: =VLOOKUP(K794,[4]在职!$A:$B,2,0) -> 00166 | N794: =VLOOKUP(K794,[4]在职!$A:$G,7,0) -> 山东销售部 | O794: =VLOOKUP(K794,[4]在职!$A:$I,9,0) -> 二星正式经理 | P794: =VLOOKUP(K794,[4]在职!$A:$D,4,0) -> 44426 | Q794: 0 | R794: 0 | S794: 0
A795: 793 | B795: 2月 | C795: =VLOOKUP(K795,[4]在职!$A:$E,5,0) -> 山东 | D795: 讲师《TTT》培训 | E795: 《讲师TTT培训》 | F795: 张振华 | G795: 线下 | H795: 1212 | I795: 无 | J795: 46077 | K795: 向润 | L795: 已签到 | M795: =VLOOKUP(K795,[4]在职!$A:$B,2,0) -> 00315 | N795: 山东拓展部 | O795: =VLOOKUP(K795,[4]在职!$A:$I,9,0) -> 区域拓展总监 | P795: =VLOOKUP(K795,[4]在职!$A:$D,4,0) -> 43974 | Q795: 0 | R795: 0 | S795: 0
A796: 794 | B796: 2月 | C796: =VLOOKUP(K796,[4]在职!$A:$E,5,0) -> 河北 | D796: 讲师《TTT》培训 | E796: 《讲师TTT培训》 | F796: 张振华 | G796: 线下 | H796: 1212 | I796: 无 | J796: 46077 | K796: 张冀 | L796: 已签到 | M796: =VLOOKUP(K796,[4]在职!$A:$B,2,0) -> 00039 | N796: 河北拓展部 | O796: =VLOOKUP(K796,[4]在职!$A:$I,9,0) -> 分公司总经理 | P796: =VLOOKUP(K796,[4]在职!$A:$D,4,0) -> 43721 | Q796: 0 | R796: 0 | S796: 0
A797: 795 | B797: 2月 | C797: =VLOOKUP(K797,[4]在职!$A:$E,5,0) -> 湖南 | D797: 讲师《TTT》培训 | E797: 《讲师TTT培训》 | F797: 张振华 | G797: 线下 | H797: 1212 | I797: 无 | J797: 46077 | K797: 孙小龙 | L797: 已签到 | M797: =VLOOKUP(K797,[4]在职!$A:$B,2,0) -> 00288 | N797: =VLOOKUP(K797,[4]在职!$A:$G,7,0) -> 湖南销售部 | O797: =VLOOKUP(K797,[4]在职!$A:$I,9,0) -> 二星正式经理 | P797: =VLOOKUP(K797,[4]在职!$A:$D,4,0) -> 44578 | Q797: 0 | R797: 0 | S797: 0
A798: 796 | B798: 2月 | C798: =VLOOKUP(K798,[4]在职!$A:$E,5,0) -> 湖北 | D798: 讲师《TTT》培训 | E798: 《讲师TTT培训》 | F798: 张振华 | G798: 线下 | H798: 1212 | I798: 无 | J798: 46077 | K798: 陈晓辉 | L798: 已签到 | M798: =VLOOKUP(K798,[4]在职!$A:$B,2,0) -> 00549 | N798: =VLOOKUP(K798,[4]在职!$A:$G,7,0) -> 湖北2部 | O798: =VLOOKUP(K798,[4]在职!$A:$I,9,0) -> 部长 | P798: =VLOOKUP(K798,[4]在职!$A:$D,4,0) -> 44933 | Q798: 0 | R798: 0 | S798: 0
A799: 797 | B799: 2月 | C799: =VLOOKUP(K799,[4]在职!$A:$E,5,0) -> 集团职能 | D799: 讲师《TTT》培训 | E799: 《讲师TTT培训》 | F799: 张振华 | G799: 线下 | H799: 1212 | I799: 无 | J799: 46077 | K799: 郭秉娜 | L799: 已签到 | M799: =VLOOKUP(K799,[4]在职!$A:$B,2,0) -> 00380 | N799: 职能营销 | O799: =VLOOKUP(K799,[4]在职!$A:$I,9,0) -> 拓展BP组长 | P799: =VLOOKUP(K799,[4]在职!$A:$D,4,0) -> 44753 | Q799: 0 | R799: 0 | S799: 0
A800: 798 | B800: 2月 | C800: =VLOOKUP(K800,[4]在职!$A:$E,5,0) -> 河南 | D800: 讲师《TTT》培训 | E800: 《讲师TTT培训》 | F800: 张振华 | G800: 线下 | H800: 1212 | I800: 无 | J800: 46077 | K800: 廖静 | L800: 已签到 | M800: =VLOOKUP(K800,[4]在职!$A:$B,2,0) -> 00040 | N800: 河南拓展部 | O800: =VLOOKUP(K800,[4]在职!$A:$I,9,0) -> 分公司总经理 | P800: =VLOOKUP(K800,[4]在职!$A:$D,4,0) -> 43692 | Q800: 0 | R800: 0 | S800: 0
A801: 799 | B801: 2月 | C801: =VLOOKUP(K801,[4]在职!$A:$E,5,0) -> 西南总部 | D801: 讲师《TTT》培训 | E801: 《讲师TTT培训》 | F801: 张振华 | G801: 线下 | H801: 1212 | I801: 无 | J801: 46077 | K801: 叶鑫 | L801: 已签到 | M801: =VLOOKUP(K801,[4]在职!$A:$B,2,0) -> 00472 | N801: =VLOOKUP(K801,[4]在职!$A:$G,7,0) -> 营业五部 | O801: =VLOOKUP(K801,[4]在职!$A:$I,9,0) -> 部长 | P801: =VLOOKUP(K801,[4]在职!$A:$D,4,0) -> 44878 | Q801: 0 | R801: 0 | S801: 0
A802: 800 | B802: 2月 | C802: =VLOOKUP(K802,[4]在职!$A:$E,5,0) -> 西南总部 | D802: 讲师《TTT》培训 | E802: 《讲师TTT培训》 | F802: 张振华 | G802: 线下 | H802: 1212 | I802: 无 | J802: 46077 | K802: 刘亮 | L802: 已签到 | M802: =VLOOKUP(K802,[4]在职!$A:$B,2,0) -> 00117 | N802: =VLOOKUP(K802,[4]在职!$A:$G,7,0) -> 营业四部 | O802: =VLOOKUP(K802,[4]在职!$A:$I,9,0) -> 部长 | P802: =VLOOKUP(K802,[4]在职!$A:$D,4,0) -> 44272 | Q802: 0 | R802: 0 | S802: 0
A803: 801 | B803: 2月 | C803: =VLOOKUP(K803,[4]在职!$A:$E,5,0) -> 西南总部 | D803: 讲师《TTT》培训 | E803: 《讲师TTT培训》 | F803: 张振华 | G803: 线下 | H803: 1212 | I803: 无 | J803: 46077 | K803: 刘盼 | L803: 已签到 | M803: =VLOOKUP(K803,[4]在职!$A:$B,2,0) -> 00036 | N803: =VLOOKUP(K803,[4]在职!$A:$G,7,0) -> 营业三部 | O803: =VLOOKUP(K803,[4]在职!$A:$I,9,0) -> 督导 | P803: =VLOOKUP(K803,[4]在职!$A:$D,4,0) -> 43800 | Q803: 0 | R803: 0 | S803: 0
A804: 802 | B804: 2月 | C804: =VLOOKUP(K804,[4]在职!$A:$E,5,0) -> 湖南 | D804: 讲师《TTT》培训 | E804: 《讲师TTT培训》 | F804: 张振华 | G804: 线下 | H804: 1212 | I804: 无 | J804: 46077 | K804: 王超飞 | L804: 已签到 | M804: =VLOOKUP(K804,[4]在职!$A:$B,2,0) -> 00094 | N804: 湖南销售部 | O804: =VLOOKUP(K804,[4]在职!$A:$I,9,0) -> 分公司总经理 | P804: =VLOOKUP(K804,[4]在职!$A:$D,4,0) -> 44175 | Q804: 0 | R804: 0 | S804: 0
A805: 803 | B805: 2月 | C805: =VLOOKUP(K805,[4]在职!$A:$E,5,0) -> 安徽 | D805: 讲师《TTT》培训 | E805: 《讲师TTT培训》 | F805: 张振华 | G805: 线下 | H805: 1212 | I805: 无 | J805: 46077 | K805: 许钊 | L805: 已签到 | M805: =VLOOKUP(K805,[4]在职!$A:$B,2,0) -> 00032 | N805: 安徽拓展部 | O805: =VLOOKUP(K805,[4]在职!$A:$I,9,0) -> 分公司总经理 | P805: =VLOOKUP(K805,[4]在职!$A:$D,4,0) -> 43910 | Q805: 0 | R805: 0 | S805: 0
A806: 804 | B806: 2月 | C806: =VLOOKUP(K806,[4]在职!$A:$E,5,0) -> 西南总部 | D806: 讲师《TTT》培训 | E806: 《讲师TTT培训》 | F806: 张振华 | G806: 线下 | H806: 1212 | I806: 无 | J806: 46077 | K806: 魏飞翔 | L806: 已签到 | M806: =VLOOKUP(K806,[4]在职!$A:$B,2,0) -> 00522 | N806: =VLOOKUP(K806,[4]在职!$A:$G,7,0) -> 营业二部 | O806: =VLOOKUP(K806,[4]在职!$A:$I,9,0) -> 一星正式经理 | P806: =VLOOKUP(K806,[4]在职!$A:$D,4,0) -> 44919 | Q806: 0 | R806: 0 | S806: 0
A807: 805 | B807: 2月 | C807: =VLOOKUP(K807,[4]在职!$A:$E,5,0) -> 西南总部 | D807: 讲师《TTT》培训 | E807: 《讲师TTT培训》 | F807: 张振华 | G807: 线下 | H807: 1212 | I807: 无 | J807: 46077 | K807: 柏刚 | L807: 已签到 | M807: =VLOOKUP(K807,[4]在职!$A:$B,2,0) -> 00060 | N807: =VLOOKUP(K807,[4]在职!$A:$G,7,0) -> 营业二部 | O807: =VLOOKUP(K807,[4]在职!$A:$I,9,0) -> 部长 | P807: =VLOOKUP(K807,[4]在职!$A:$D,4,0) -> 44033 | Q807: 0 | R807: 0 | S807: 0
A808: 806 | B808: 2月 | C808: =VLOOKUP(K808,[4]在职!$A:$E,5,0) -> 集团职能 | D808: 讲师《TTT》培训 | E808: 《讲师TTT培训》 | F808: 张振华 | G808: 线下 | H808: 1212 | I808: 无 | J808: 46077 | K808: 查丹 | L808: 已签到 | M808: =VLOOKUP(K808,[4]在职!$A:$B,2,0) -> 00068 | N808: 职能营销 | O808: =VLOOKUP(K808,[4]在职!$A:$I,9,0) -> 拓展BP | P808: =VLOOKUP(K808,[4]在职!$A:$D,4,0) -> 44062 | Q808: 0 | R808: 0 | S808: 0
A809: 807 | B809: 2月 | C809: =VLOOKUP(K809,[4]在职!$A:$E,5,0) -> 集团职能 | D809: 讲师《TTT》培训 | E809: 《讲师TTT培训》 | F809: 张振华 | G809: 线下 | H809: 1212 | I809: 无 | J809: 46077 | K809: 陈萍 | L809: 已签到 | M809: =VLOOKUP(K809,[4]在职!$A:$B,2,0) -> 00037 | N809: 职能营销 | O809: =VLOOKUP(K809,[4]在职!$A:$I,9,0) -> 财务经理 | P809: =VLOOKUP(K809,[4]在职!$A:$D,4,0) -> 43525 | Q809: 0 | R809: 0 | S809: 0
A810: 808 | B810: 2月 | C810: =VLOOKUP(K810,[4]在职!$A:$E,5,0) -> 山东 | D810: 讲师《TTT》培训 | E810: 《讲师TTT培训》 | F810: 张振华 | G810: 线下 | H810: 1212 | I810: 无 | J810: 46077 | K810: 李丹 | L810: 已签到 | M810: =VLOOKUP(K810,[4]在职!$A:$B,2,0) -> 00067 | N810: 山东销售部 | O810: =VLOOKUP(K810,[4]在职!$A:$I,9,0) -> 分公司总经理 | P810: =VLOOKUP(K810,[4]在职!$A:$D,4,0) -> 44054 | Q810: 0 | R810: 0 | S810: 0
A811: 809 | B811: 2月 | C811: =VLOOKUP(K811,[4]在职!$A:$E,5,0) -> 湖北 | D811: 讲师《TTT》培训 | E811: 《讲师TTT培训》 | F811: 张振华 | G811: 线下 | H811: 1212 | I811: 无 | J811: 46077 | K811: 林浩 | L811: 已签到 | M811: =VLOOKUP(K811,[4]在职!$A:$B,2,0) -> 00333 | N811: =VLOOKUP(K811,[4]在职!$A:$G,7,0) -> 湖北1部 | O811: =VLOOKUP(K811,[4]在职!$A:$I,9,0) -> 部长 | P811: =VLOOKUP(K811,[4]在职!$A:$D,4,0) -> 44698 | Q811: 0 | R811: 0 | S811: 0
A812: 810 | B812: 2月 | C812: =VLOOKUP(K812,[4]在职!$A:$E,5,0) -> 山西 | D812: 讲师《TTT》培训 | E812: 《讲师TTT培训》 | F812: 张振华 | G812: 线下 | H812: 1212 | I812: 无 | J812: 46077 | K812: 刘辉 | L812: 已签到 | M812: =VLOOKUP(K812,[4]在职!$A:$B,2,0) -> 00015 | N812: =VLOOKUP(K812,[4]在职!$A:$G,7,0) -> 0 | O812: =VLOOKUP(K812,[4]在职!$A:$I,9,0) -> 分公司副总经理 | P812: =VLOOKUP(K812,[4]在职!$A:$D,4,0) -> 43904 | Q812: 0 | R812: 0 | S812: 0
A813: 811 | B813: 2月 | C813: =VLOOKUP(K813,[4]在职!$A:$E,5,0) -> 辽宁 | D813: 讲师《TTT》培训 | E813: 《讲师TTT培训》 | F813: 张振华 | G813: 线下 | H813: 1212 | I813: 无 | J813: 46077 | K813: 聂仕平 | L813: 已签到 | M813: =VLOOKUP(K813,[4]在职!$A:$B,2,0) -> 00057 | N813: 辽宁拓展部 | O813: =VLOOKUP(K813,[4]在职!$A:$I,9,0) -> 分公司总经理 | P813: =VLOOKUP(K813,[4]在职!$A:$D,4,0) -> 44019 | Q813: 0 | R813: 0 | S813: 0
A814: 812 | B814: 2月 | C814: =VLOOKUP(K814,[4]在职!$A:$E,5,0) -> 山西 | D814: 讲师《TTT》培训 | E814: 《讲师TTT培训》 | F814: 张振华 | G814: 线下 | H814: 1212 | I814: 无 | J814: 46077 | K814: 吴川江 | L814: 已签到 | M814: =VLOOKUP(K814,[4]在职!$A:$B,2,0) -> 00695 | N814: 山西拓展部 | O814: =VLOOKUP(K814,[4]在职!$A:$I,9,0) -> 分公司总经理 | P814: =VLOOKUP(K814,[4]在职!$A:$D,4,0) -> 44849 | Q814: 0 | R814: 0 | S814: 0
A815: 813 | B815: 2月 | C815: =VLOOKUP(K815,[4]在职!$A:$E,5,0) -> 山东 | D815: 讲师《TTT》培训 | E815: 《讲师TTT培训》 | F815: 张振华 | G815: 线下 | H815: 1212 | I815: 无 | J815: 46077 | K815: 肖佳 | L815: 已签到 | M815: =VLOOKUP(K815,[4]在职!$A:$B,2,0) -> 00521 | N815: =VLOOKUP(K815,[4]在职!$A:$G,7,0) -> 山东销售部 | O815: =VLOOKUP(K815,[4]在职!$A:$I,9,0) -> 一星正式经理 | P815: =VLOOKUP(K815,[4]在职!$A:$D,4,0) -> 44919 | Q815: 0 | R815: 0 | S815: 0
A816: 814 | B816: 2月 | C816: =VLOOKUP(K816,[4]在职!$A:$E,5,0) -> 集团职能 | D816: 讲师《TTT》培训 | E816: 《讲师TTT培训》 | F816: 张振华 | G816: 线下 | H816: 1212 | I816: 无 | J816: 46077 | K816: 黄芳 | L816: 已签到 | M816: =VLOOKUP(K816,[4]在职!$A:$B,2,0) -> 00001 | N816: 职能营销 | O816: =VLOOKUP(K816,[4]在职!$A:$I,9,0) -> 总经理 | P816: =VLOOKUP(K816,[4]在职!$A:$D,4,0) -> 43466 | Q816: 0 | R816: 0 | S816: 0
A817: 815 | B817: 2月 | C817: =VLOOKUP(K817,[4]在职!$A:$E,5,0) -> 集团职能 | D817: 讲师《TTT》培训 | E817: 《讲师TTT培训》 | F817: 张振华 | G817: 线下 | H817: 1212 | I817: 无 | J817: 46078 | K817: 黄芳 | L817: 已签到 | M817: =VLOOKUP(K817,[4]在职!$A:$B,2,0) -> 00001 | N817: 职能营销 | O817: =VLOOKUP(K817,[4]在职!$A:$I,9,0) -> 总经理 | P817: =VLOOKUP(K817,[4]在职!$A:$D,4,0) -> 43466 | Q817: 0 | R817: 0 | S817: 0
A818: 816 | B818: 2月 | C818: 宁夏 | D818: 讲师《TTT》培训 | E818: 《讲师TTT培训》 | F818: 张振华 | G818: 线下 | H818: 1212 | I818: 无 | J818: 46078 | K818: 黄小东 | L818: 已签到 | M818: =VLOOKUP(K818,[4]在职!$A:$B,2,0) -> 00215 | N818: 宁夏拓展中心 | O818: =VLOOKUP(K818,[4]在职!$A:$I,9,0) -> 区域拓展总监 | P818: =VLOOKUP(K818,[4]在职!$A:$D,4,0) -> 44525 | Q818: 0 | R818: 0 | S818: 0
A819: 817 | B819: 2月 | C819: =VLOOKUP(K819,[4]在职!$A:$E,5,0) -> 西南总部 | D819: 讲师《TTT》培训 | E819: 《讲师TTT培训》 | F819: 张振华 | G819: 线下 | H819: 1212 | I819: 无 | J819: 46078 | K819: 蒋婉萍 | L819: 已签到 | M819: =VLOOKUP(K819,[4]在职!$A:$B,2,0) -> 00745 | N819: =VLOOKUP(K819,[4]在职!$A:$G,7,0) -> 川北 | O819: =VLOOKUP(K819,[4]在职!$A:$I,9,0) -> 区域拓展总监 | P819: =VLOOKUP(K819,[4]在职!$A:$D,4,0) -> 44522 | Q819: 0 | R819: 0 | S819: 0
A820: 818 | B820: 2月 | C820: =VLOOKUP(K820,[4]在职!$A:$E,5,0) -> 集团职能 | D820: 讲师《TTT》培训 | E820: 《讲师TTT培训》 | F820: 张振华 | G820: 线下 | H820: 1212 | I820: 无 | J820: 46078 | K820: 孔群慧 | L820: 已签到 | M820: =VLOOKUP(K820,[4]在职!$A:$B,2,0) -> 01918 | N820: 职能营销 | O820: =VLOOKUP(K820,[4]在职!$A:$I,9,0) -> 人资行政经理 | P820: =VLOOKUP(K820,[4]在职!$A:$D,4,0) -> 46048 | Q820: 0 | R820: 0 | S820: 0
...

Sheet 《营业部》维度的参训率
A1: 《营业部》维度的参训率（1-3月）
A2: 序号 | B2: 月份 | C2: 城市 | D2: 营业部 | E2: 部长姓名 | F2: 课程类型 | G2: 应参训人次 | H2: 实际参训人次 | I2: 参训率
A3: 1 | B3: 1月 | C3: 西南总部 | D3: 营业五部 | E3: 叶鑫 | F3: 销售新人入职培训 | G3: =COUNTIFS('2026年度培训主表'!B:B,B3,'2026年度培训主表'!C:C,C3,'2026年度培训主表'!N:N,D3,'2026年度培训主表'!D:D,F3) -> 32 | H3: =COUNTIFS('2026年度培训主表'!B:B,B3,'2026年度培训主表'!C:C,C3,'2026年度培训主表'!N:N,D3,'2026年度培训主表'!D:D,F3,'2026年度培训主表'!L:L,"已签到") -> 0 | I3: =H3/G3 -> 0
A4: 2 | B4: 1月 | C4: 湖南 | D4: 湖南销售部 | E4: 刘进 | F4: 销售新人入职培训 | G4: =COUNTIFS('2026年度培训主表'!B:B,B4,'2026年度培训主表'!C:C,C4,'2026年度培训主表'!N:N,D4,'2026年度培训主表'!D:D,F4) -> 24 | H4: =COUNTIFS('2026年度培训主表'!B:B,B4,'2026年度培训主表'!C:C,C4,'2026年度培训主表'!N:N,D4,'2026年度培训主表'!D:D,F4,'2026年度培训主表'!L:L,"已签到") -> 12 | I4: =H4/G4 -> 0.5
A5: 3 | B5: 1月 | C5: 陕西 | D5: 陕西2部 | E5: 李耀 | F5: 销售新人入职培训 | G5: =COUNTIFS('2026年度培训主表'!B:B,B5,'2026年度培训主表'!C:C,C5,'2026年度培训主表'!N:N,D5,'2026年度培训主表'!D:D,F5) -> 16 | H5: =COUNTIFS('2026年度培训主表'!B:B,B5,'2026年度培训主表'!C:C,C5,'2026年度培训主表'!N:N,D5,'2026年度培训主表'!D:D,F5,'2026年度培训主表'!L:L,"已签到") -> 16 | I5: =H5/G5 -> 1
A6: 4 | B6: 1月 | C6: 西南总部 | D6: 营业六部 | E6: 毛富林 | F6: 销售新人入职培训 | G6: =COUNTIFS('2026年度培训主表'!B:B,B6,'2026年度培训主表'!C:C,C6,'2026年度培训主表'!N:N,D6,'2026年度培训主表'!D:D,F6) -> 29 | H6: =COUNTIFS('2026年度培训主表'!B:B,B6,'2026年度培训主表'!C:C,C6,'2026年度培训主表'!N:N,D6,'2026年度培训主表'!D:D,F6,'2026年度培训主表'!L:L,"已签到") -> 0 | I6: =H6/G6 -> 0
A7: 5 | B7: 1月 | C7: 西南总部 | D7: 营业三部 | E7: 周吉双 | F7: 销售新人入职培训 | G7: =COUNTIFS('2026年度培训主表'!B:B,B7,'2026年度培训主表'!C:C,C7,'2026年度培训主表'!N:N,D7,'2026年度培训主表'!D:D,F7) -> 28 | H7: =COUNTIFS('2026年度培训主表'!B:B,B7,'2026年度培训主表'!C:C,C7,'2026年度培训主表'!N:N,D7,'2026年度培训主表'!D:D,F7,'2026年度培训主表'!L:L,"已签到") -> 8 | I7: =H7/G7 -> 0.28571429
A8: 6 | B8: 1月 | C8: 西南总部 | D8: 营业一部 | E8: 雷小金 | F8: 销售新人入职培训 | G8: =COUNTIFS('2026年度培训主表'!B:B,B8,'2026年度培训主表'!C:C,C8,'2026年度培训主表'!N:N,D8,'2026年度培训主表'!D:D,F8) -> 28 | H8: =COUNTIFS('2026年度培训主表'!B:B,B8,'2026年度培训主表'!C:C,C8,'2026年度培训主表'!N:N,D8,'2026年度培训主表'!D:D,F8,'2026年度培训主表'!L:L,"已签到") -> 16 | I8: =H8/G8 -> 0.57142857
A9: 7 | B9: 1月 | C9: 河南 | D9: 河南销售部 | E9: 毛孝树 | F9: 销售新人入职培训 | G9: =COUNTIFS('2026年度培训主表'!B:B,B9,'2026年度培训主表'!C:C,C9,'2026年度培训主表'!N:N,D9,'2026年度培训主表'!D:D,F9) -> 24 | H9: =COUNTIFS('2026年度培训主表'!B:B,B9,'2026年度培训主表'!C:C,C9,'2026年度培训主表'!N:N,D9,'2026年度培训主表'!D:D,F9,'2026年度培训主表'!L:L,"已签到") -> 20 | I9: =H9/G9 -> 0.83333333
A10: 8 | B10: 1月 | C10: 西南总部 | D10: 营业二部 | E10: 柏刚 | F10: 销售新人入职培训 | G10: =COUNTIFS('2026年度培训主表'!B:B,B10,'2026年度培训主表'!C:C,C10,'2026年度培训主表'!N:N,D10,'2026年度培训主表'!D:D,F10) -> 24 | H10: =COUNTIFS('2026年度培训主表'!B:B,B10,'2026年度培训主表'!C:C,C10,'2026年度培训主表'!N:N,D10,'2026年度培训主表'!D:D,F10,'2026年度培训主表'!L:L,"已签到") -> 8 | I10: =H10/G10 -> 0.33333333
A11: 9 | B11: 1月 | C11: 西南总部 | D11: 营业七部 | E11: 程新浩 | F11: 销售新人入职培训 | G11: =COUNTIFS('2026年度培训主表'!B:B,B11,'2026年度培训主表'!C:C,C11,'2026年度培训主表'!N:N,D11,'2026年度培训主表'!D:D,F11) -> 28 | H11: =COUNTIFS('2026年度培训主表'!B:B,B11,'2026年度培训主表'!C:C,C11,'2026年度培训主表'!N:N,D11,'2026年度培训主表'!D:D,F11,'2026年度培训主表'!L:L,"已签到") -> 12 | I11: =H11/G11 -> 0.42857143
A12: 10 | B12: 1月 | C12: 湖北 | D12: 湖北2部 | E12: 陈晓辉 | F12: 销售新人入职培训 | G12: =COUNTIFS('2026年度培训主表'!B:B,B12,'2026年度培训主表'!C:C,C12,'2026年度培训主表'!N:N,D12,'2026年度培训主表'!D:D,F12) -> 4 | H12: =COUNTIFS('2026年度培训主表'!B:B,B12,'2026年度培训主表'!C:C,C12,'2026年度培训主表'!N:N,D12,'2026年度培训主表'!D:D,F12,'2026年度培训主表'!L:L,"已签到") -> 4 | I12: =H12/G12 -> 1
A13: 11 | B13: 1月 | C13: 甘肃 | D13: 甘肃销售部 | E13: 李耀 | F13: 销售新人入职培训 | G13: =COUNTIFS('2026年度培训主表'!B:B,B13,'2026年度培训主表'!C:C,C13,'2026年度培训主表'!N:N,D13,'2026年度培训主表'!D:D,F13) -> 4 | H13: =COUNTIFS('2026年度培训主表'!B:B,B13,'2026年度培训主表'!C:C,C13,'2026年度培训主表'!N:N,D13,'2026年度培训主表'!D:D,F13,'2026年度培训主表'!L:L,"已签到") -> 4 | I13: =H13/G13 -> 1
A14: 12 | B14: 1月 | C14: 山东 | D14: 山东销售部 | E14: 李丹 | F14: 销售新人入职培训 | G14: =COUNTIFS('2026年度培训主表'!B:B,B14,'2026年度培训主表'!C:C,C14,'2026年度培训主表'!N:N,D14,'2026年度培训主表'!D:D,F14) -> 8 | H14: =COUNTIFS('2026年度培训主表'!B:B,B14,'2026年度培训主表'!C:C,C14,'2026年度培训主表'!N:N,D14,'2026年度培训主表'!D:D,F14,'2026年度培训主表'!L:L,"已签到") -> 8 | I14: =H14/G14 -> 1
... A64: 62 | B64: 1月 | C64: 河北 | D64: 河北销售部 | E64: 李港一 | F64: 销售经理培训 | G64: =COUNTIFS('2026年度培训主表'!B:B,B64,'2026年度培训主表'!C:C,C64,'2026年度培训主表'!N:N,D64,'2026年度培训主表'!D:D,F64) -> 2 | H64: =COUNTIFS('2026年度培训主表'!B:B,B64,'2026年度培训主表'!C:C,C64,'2026年度培训主表'!N:N,D64,'2026年度培训主表'!D:D,F64,'2026年度培训主表'!L:L,"已签到") -> 2 | I64: =H64/G64 -> 1
A65: 63 | B65: 2月 | C65: 西南总部 | D65: 营业五部 | E65: 叶鑫 | F65: 讲师《TTT》培训 | G65: =COUNTIFS('2026年度培训主表'!B:B,B65,'2026年度培训主表'!C:C,C65,'2026年度培训主表'!N:N,D65,'2026年度培训主表'!D:D,F65) -> 4 | H65: =COUNTIFS('2026年度培训主表'!B:B,B65,'2026年度培训主表'!N:N,D65,'2026年度培训主表'!L:L,"已签到") -> 4 | I65: =H65/G65 -> 1
A66: 64 | B66: 2月 | C66: 湖南 | D66: 湖南销售部 | E66: 刘进 | F66: 讲师《TTT》培训 | G66: =COUNTIFS('2026年度培训主表'!B:B,B66,'2026年度培训主表'!C:C,C66,'2026年度培训主表'!N:N,D66,'2026年度培训主表'!D:D,F66) -> 6 | H66: =COUNTIFS('2026年度培训主表'!B:B,B66,'2026年度培训主表'!N:N,D66,'2026年度培训主表'!L:L,"已签到") -> 6 | I66: =H66/G66 -> 1
A67: 65 | B67: 2月 | C67: 陕西 | D67: 陕西2部 | E67: 李耀 | F67: 讲师《TTT》培训 | G67: =COUNTIFS('2026年度培训主表'!B:B,B67,'2026年度培训主表'!C:C,C67,'2026年度培训主表'!N:N,D67,'2026年度培训主表'!D:D,F67) -> 2 | H67: =COUNTIFS('2026年度培训主表'!B:B,B67,'2026年度培训主表'!N:N,D67,'2026年度培训主表'!L:L,"已签到") -> 2 | I67: =H67/G67 -> 1
A68: 66 | B68: 2月 | C68: 西南总部 | D68: 营业六部 | E68: 毛富林 | F68: 讲师《TTT》培训 | G68: =COUNTIFS('2026年度培训主表'!B:B,B68,'2026年度培训主表'!C:C,C68,'2026年度培训主表'!N:N,D68,'2026年度培训主表'!D:D,F68) -> 2 | H68: =COUNTIFS('2026年度培训主表'!B:B,B68,'2026年度培训主表'!N:N,D68,'2026年度培训主表'!L:L,"已签到") -> 2 | I68: =H68/G68 -> 1
A69: 67 | B69: 2月 | C69: 西南总部 | D69: 营业三部 | E69: 周吉双 | F69: 讲师《TTT》培训 | G69: =COUNTIFS('2026年度培训主表'!B:B,B69,'2026年度培训主表'!C:C,C69,'2026年度培训主表'!N:N,D69,'2026年度培训主表'!D:D,F69) -> 4 | H69: =COUNTIFS('2026年度培训主表'!B:B,B69,'2026年度培训主表'!N:N,D69,'2026年度培训主表'!L:L,"已签到") -> 4 | I69: =H69/G69 -> 1
A70: 68 | B70: 2月 | C70: 西南总部 | D70: 营业一部 | E70: 雷小金 | F70: 讲师《TTT》培训 | G70: =COUNTIFS('2026年度培训主表'!B:B,B70,'2026年度培训主表'!C:C,C70,'2026年度培训主表'!N:N,D70,'2026年度培训主表'!D:D,F70) -> 2 | H70: =COUNTIFS('2026年度培训主表'!B:B,B70,'2026年度培训主表'!N:N,D70,'2026年度培训主表'!L:L,"已签到") -> 2 | I70: =H70/G70 -> 1
A71: 69 | B71: 2月 | C71: 河南 | D71: 河南销售部 | E71: 毛孝树 | F71: 讲师《TTT》培训 | G71: =COUNTIFS('2026年度培训主表'!B:B,B71,'2026年度培训主表'!C:C,C71,'2026年度培训主表'!N:N,D71,'2026年度培训主表'!D:D,F71) -> 2 | H71: =COUNTIFS('2026年度培训主表'!B:B,B71,'2026年度培训主表'!N:N,D71,'2026年度培训主表'!L:L,"已签到") -> 2 | I71: =H71/G71 -> 1
A72: 70 | B72: 2月 | C72: 西南总部 | D72: 营业二部 | E72: 柏刚 | F72: 讲师《TTT》培训 | G72: =COUNTIFS('2026年度培训主表'!B:B,B72,'2026年度培训主表'!C:C,C72,'2026年度培训主表'!N:N,D72,'2026年度培训主表'!D:D,F72) -> 4 | H72: =COUNTIFS('2026年度培训主表'!B:B,B72,'2026年度培训主表'!N:N,D72,'2026年度培训主表'!L:L,"已签到") -> 4 | I72: =H72/G72 -> 1
A73: 71 | B73: 2月 | C73: 西南总部 | D73: 营业七部 | E73: 程新浩 | F73: 讲师《TTT》培训 | G73: =COUNTIFS('2026年度培训主表'!B:B,B73,'2026年度培训主表'!C:C,C73,'2026年度培训主表'!N:N,D73,'2026年度培训主表'!D:D,F73) -> 2 | H73: =COUNTIFS('2026年度培训主表'!B:B,B73,'2026年度培训主表'!N:N,D73,'2026年度培训主表'!L:L,"已签到") -> 2 | I73: =H73/G73 -> 1
A74: 72 | B74: 2月 | C74: 湖北 | D74: 湖北2部 | E74: 陈晓辉 | F74: 讲师《TTT》培训 | G74: =COUNTIFS('2026年度培训主表'!B:B,B74,'2026年度培训主表'!C:C,C74,'2026年度培训主表'!N:N,D74,'2026年度培训主表'!D:D,F74) -> 2 | H74: =COUNTIFS('2026年度培训主表'!B:B,B74,'2026年度培训主表'!N:N,D74,'2026年度培训主表'!L:L,"已签到") -> 2 | I74: =H74/G74 -> 1
A75: 74 | B75: 2月 | C75: 山东 | D75: 山东销售部 | E75: 李丹 | F75: 讲师《TTT》培训 | G75: =COUNTIFS('2026年度培训主表'!B:B,B75,'2026年度培训主表'!C:C,C75,'2026年度培训主表'!N:N,D75,'2026年度培训主表'!D:D,F75) -> 6 | H75: =COUNTIFS('2026年度培训主表'!B:B,B75,'2026年度培训主表'!N:N,D75,'2026年度培训主表'!L:L,"已签到") -> 6 | I75: =H75/G75 -> 1
A76: 76 | B76: 2月 | C76: 湖北 | D76: 湖北1部 | E76: 林浩 | F76: 讲师《TTT》培训 | G76: =COUNTIFS('2026年度培训主表'!B:B,B76,'2026年度培训主表'!C:C,C76,'2026年度培训主表'!N:N,D76,'2026年度培训主表'!D:D,F76) -> 4 | H76: =COUNTIFS('2026年度培训主表'!B:B,B76,'2026年度培训主表'!N:N,D76,'2026年度培训主表'!L:L,"已签到") -> 4 | I76: =H76/G76 -> 1
... A95: 96 | B95: 2月 | C95: 河北 | D95: 河北拓展部 | E95: 张冀 | F95: 讲师《TTT》培训 | G95: =COUNTIFS('2026年度培训主表'!B:B,B95,'2026年度培训主表'!C:C,C95,'2026年度培训主表'!N:N,D95,'2026年度培训主表'!D:D,F95) -> 4 | H95: =COUNTIFS('2026年度培训主表'!B:B,B95,'2026年度培训主表'!N:N,D95,'2026年度培训主表'!L:L,"已签到") -> 4 | I95: =H95/G95 -> 1
A96: 97 | B96: 3月 | C96: 西南总部 | D96: 营业一部 | E96: 雷小金 | F96: 销售新人入职培训 | G96: =COUNTIFS('2026年度培训主表'!B:B,B96,'2026年度培训主表'!D:D,F96,'2026年度培训主表'!N:N,D96) -> 52 | H96: =COUNTIFS('2026年度培训主表'!B:B,B96,'2026年度培训主表'!D:D,F96,'2026年度培训主表'!N:N,D96,'2026年度培训主表'!L:L,"已签到") -> 36 | I96: =H96/G96 -> 0.69230769
A97: 98 | B97: 3月 | C97: 西南总部 | D97: 营业二部 | E97: 柏刚 | F97: 销售新人入职培训 | G97: =COUNTIFS('2026年度培训主表'!B:B,B97,'2026年度培训主表'!D:D,F97,'2026年度培训主表'!N:N,D97) -> 20 | H97: =COUNTIFS('2026年度培训主表'!B:B,B97,'2026年度培训主表'!D:D,F97,'2026年度培训主表'!N:N,D97,'2026年度培训主表'!L:L,"已签到") -> 0 | I97: =H97/G97 -> 0
A98: 99 | B98: 3月 | C98: 西南总部 | D98: 营业三部 | E98: 周吉双 | F98: 销售新人入职培训 | G98: =COUNTIFS('2026年度培训主表'!B:B,B98,'2026年度培训主表'!D:D,F98,'2026年度培训主表'!N:N,D98) -> 12 | H98: =COUNTIFS('2026年度培训主表'!B:B,B98,'2026年度培训主表'!D:D,F98,'2026年度培训主表'!N:N,D98,'2026年度培训主表'!L:L,"已签到") -> 8 | I98: =H98/G98 -> 0.66666667
A99: 100 | B99: 3月 | C99: 西南总部 | D99: 营业四部 | E99: 刘亮 | F99: 销售新人入职培训 | G99: =COUNTIFS('2026年度培训主表'!B:B,B99,'2026年度培训主表'!D:D,F99,'2026年度培训主表'!N:N,D99) -> 16 | H99: =COUNTIFS('2026年度培训主表'!B:B,B99,'2026年度培训主表'!D:D,F99,'2026年度培训主表'!N:N,D99,'2026年度培训主表'!L:L,"已签到") -> 0 | I99: =H99/G99 -> 0
A100: 101 | B100: 3月 | C100: 西南总部 | D100: 营业五部 | E100: 叶鑫 | F100: 销售新人入职培训 | G100: =COUNTIFS('2026年度培训主表'!B:B,B100,'2026年度培训主表'!D:D,F100,'2026年度培训主表'!N:N,D100) -> 44 | H100: =COUNTIFS('2026年度培训主表'!B:B,B100,'2026年度培训主表'!D:D,F100,'2026年度培训主表'!N:N,D100,'2026年度培训主表'!L:L,"已签到") -> 4 | I100: =H100/G100 -> 0.090909091
A101: 102 | B101: 3月 | C101: 西南总部 | D101: 营业六部 | E101: 毛富林 | F101: 销售新人入职培训 | G101: =COUNTIFS('2026年度培训主表'!B:B,B101,'2026年度培训主表'!D:D,F101,'2026年度培训主表'!N:N,D101) -> 40 | H101: =COUNTIFS('2026年度培训主表'!B:B,B101,'2026年度培训主表'!D:D,F101,'2026年度培训主表'!N:N,D101,'2026年度培训主表'!L:L,"已签到") -> 12 | I101: =H101/G101 -> 0.3
A102: 103 | B102: 3月 | C102: 西南总部 | D102: 营业七部 | E102: 程新浩 | F102: 销售新人入职培训 | G102: =COUNTIFS('2026年度培训主表'!B:B,B102,'2026年度培训主表'!D:D,F102,'2026年度培训主表'!N:N,D102) -> 36 | H102: =COUNTIFS('2026年度培训主表'!B:B,B102,'2026年度培训主表'!D:D,F102,'2026年度培训主表'!N:N,D102,'2026年度培训主表'!L:L,"已签到") -> 8 | I102: =H102/G102 -> 0.22222222
A103: 105 | B103: 3月 | C103: 河北 | D103: 河北销售部 | E103: 李港一 | F103: 销售新人入职培训 | G103: =COUNTIFS('2026年度培训主表'!B:B,B103,'2026年度培训主表'!D:D,F103,'2026年度培训主表'!N:N,D103) -> 16 | H103: =COUNTIFS('2026年度培训主表'!B:B,B103,'2026年度培训主表'!D:D,F103,'2026年度培训主表'!N:N,D103,'2026年度培训主表'!L:L,"已签到") -> 8 | I103: =H103/G103 -> 0.5
A104: 106 | B104: 3月 | C104: 河南 | D104: 河南销售部 | E104: 毛孝树 | F104: 销售新人入职培训 | G104: =COUNTIFS('2026年度培训主表'!B:B,B104,'2026年度培训主表'!D:D,F104,'2026年度培训主表'!N:N,D104) -> 12 | H104: =COUNTIFS('2026年度培训主表'!B:B,B104,'2026年度培训主表'!D:D,F104,'2026年度培训主表'!N:N,D104,'2026年度培训主表'!L:L,"已签到") -> 8 | I104: =H104/G104 -> 0.66666667
A105: 107 | B105: 3月 | C105: 湖北 | D105: 湖北1部 | E105: 林浩 | F105: 销售新人入职培训 | G105: =COUNTIFS('2026年度培训主表'!B:B,B105,'2026年度培训主表'!D:D,F105,'2026年度培训主表'!N:N,D105) -> 12 | H105: =COUNTIFS('2026年度培训主表'!B:B,B105,'2026年度培训主表'!D:D,F105,'2026年度培训主表'!N:N,D105,'2026年度培训主表'!L:L,"已签到") -> 8 | I105: =H105/G105 -> 0.66666667
A106: 108 | B106: 3月 | C106: 湖北 | D106: 湖北2部 | E106: 陈晓辉 | F106: 销售新人入职培训 | G106: =COUNTIFS('2026年度培训主表'!B:B,B106,'2026年度培训主表'!D:D,F106,'2026年度培训主表'!N:N,D106) -> 4 | H106: =COUNTIFS('2026年度培训主表'!B:B,B106,'2026年度培训主表'!D:D,F106,'2026年度培训主表'!N:N,D106,'2026年度培训主表'!L:L,"已签到") -> 4 | I106: =H106/G106 -> 1
A107: 109 | B107: 3月 | C107: 湖南 | D107: 湖南销售部 | E107: 刘进 | F107: 销售新人入职培训 | G107: =COUNTIFS('2026年度培训主表'!B:B,B107,'2026年度培训主表'!D:D,F107,'2026年度培训主表'!N:N,D107) -> 20 | H107: =COUNTIFS('2026年度培训主表'!B:B,B107,'2026年度培训主表'!D:D,F107,'2026年度培训主表'!N:N,D107,'2026年度培训主表'!L:L,"已签到") -> 16 | I107: =H107/G107 -> 0.8
... A111: 113 | B111: 3月 | C111: 陕西 | D111: 陕西2部 | E111: 李耀 | F111: 销售新人入职培训 | G111: =COUNTIFS('2026年度培训主表'!B:B,B111,'2026年度培训主表'!D:D,F111,'2026年度培训主表'!N:N,D111) -> 12 | H111: =COUNTIFS('2026年度培训主表'!B:B,B111,'2026年度培训主表'!D:D,F111,'2026年度培训主表'!N:N,D111,'2026年度培训主表'!L:L,"已签到") -> 12 | I111: =H111/G111 -> 1
A112: 114 | B112: 3月 | C112: 西南总部 | D112: 职能营销 | E112: 总经办 | F112: 销售新人入职培训 | G112: 18 | H112: 16 | I112: =H112/G112 -> 0.88888889
A113: 115 | B113: 3月 | C113: 西南总部 | D113: 营业一部 | E113: 雷小金 | F113: 销售提升训 | G113: =COUNTIFS('2026年度培训主表'!B:B,B113,'2026年度培训主表'!D:D,F113,'2026年度培训主表'!N:N,D113) -> 24 | H113: =COUNTIFS('2026年度培训主表'!B:B,B113,'2026年度培训主表'!D:D,F113,'2026年度培训主表'!N:N,D113,'2026年度培训主表'!L:L,"已签到") -> 15 | I113: =H113/G113 -> 0.625
A114: 116 | B114: 3月 | C114: 西南总部 | D114: 营业二部 | E114: 柏刚 | F114: 销售提升训 | G114: =COUNTIFS('2026年度培训主表'!B:B,B114,'2026年度培训主表'!D:D,F114,'2026年度培训主表'!N:N,D114) -> 12 | H114: =COUNTIFS('2026年度培训主表'!B:B,B114,'2026年度培训主表'!D:D,F114,'2026年度培训主表'!N:N,D114,'2026年度培训主表'!L:L,"已签到") -> 6 | I114: =H114/G114 -> 0.5
A115: 117 | B115: 3月 | C115: 西南总部 | D115: 营业三部 | E115: 周吉双 | F115: 销售提升训 | G115: =COUNTIFS('2026年度培训主表'!B:B,B115,'2026年度培训主表'!D:D,F115,'2026年度培训主表'!N:N,D115) -> 35 | H115: =COUNTIFS('2026年度培训主表'!B:B,B115,'2026年度培训主表'!D:D,F115,'2026年度培训主表'!N:N,D115,'2026年度培训主表'!L:L,"已签到") -> 15 | I115: =H115/G115 -> 0.42857143
A116: 118 | B116: 3月 | C116: 西南总部 | D116: 营业四部 | E116: 刘亮 | F116: 销售提升训 | G116: =COUNTIFS('2026年度培训主表'!B:B,B116,'2026年度培训主表'!D:D,F116,'2026年度培训主表'!N:N,D116) -> 18 | H116: =COUNTIFS('2026年度培训主表'!B:B,B116,'2026年度培训主表'!D:D,F116,'2026年度培训主表'!N:N,D116,'2026年度培训主表'!L:L,"已签到") -> 18 | I116: =H116/G116 -> 1
A117: 119 | B117: 3月 | C117: 西南总部 | D117: 营业五部 | E117: 叶鑫 | F117: 销售提升训 | G117: =COUNTIFS('2026年度培训主表'!B:B,B117,'2026年度培训主表'!D:D,F117,'2026年度培训主表'!N:N,D117) -> 32 | H117: =COUNTIFS('2026年度培训主表'!B:B,B117,'2026年度培训主表'!D:D,F117,'2026年度培训主表'!N:N,D117,'2026年度培训主表'!L:L,"已签到") -> 18 | I117: =H117/G117 -> 0.5625
A118: 120 | B118: 3月 | C118: 西南总部 | D118: 营业六部 | E118: 毛富林 | F118: 销售提升训 | G118: =COUNTIFS('2026年度培训主表'!B:B,B118,'2026年度培训主表'!D:D,F118,'2026年度培训主表'!N:N,D118) -> 30 | H118: =COUNTIFS('2026年度培训主表'!B:B,B118,'2026年度培训主表'!D:D,F118,'2026年度培训主表'!N:N,D118,'2026年度培训主表'!L:L,"已签到") -> 9 | I118: =H118/G118 -> 0.3
A119: 121 | B119: 3月 | C119: 西南总部 | D119: 营业七部 | E119: 程新浩 | F119: 销售提升训 | G119: =COUNTIFS('2026年度培训主表'!B:B,B119,'2026年度培训主表'!D:D,F119,'2026年度培训主表'!N:N,D119) -> 29 | H119: =COUNTIFS('2026年度培训主表'!B:B,B119,'2026年度培训主表'!D:D,F119,'2026年度培训主表'!N:N,D119,'2026年度培训主表'!L:L,"已签到") -> 26 | I119: =H119/G119 -> 0.89655172
A120: 122 | B120: 3月 | C120: 河北 | D120: 河北销售部 | E120: 李港一 | F120: 销售提升训 | G120: =COUNTIFS('2026年度培训主表'!B:B,B120,'2026年度培训主表'!D:D,F120,'2026年度培训主表'!N:N,D120) -> 12 | H120: =COUNTIFS('2026年度培训主表'!B:B,B120,'2026年度培训主表'!D:D,F120,'2026年度培训主表'!N:N,D120,'2026年度培训主表'!L:L,"已签到") -> 6 | I120: =H120/G120 -> 0.5
A121: 123 | B121: 3月 | C121: 河南 | D121: 河南销售部 | E121: 毛孝树 | F121: 销售提升训 | G121: =COUNTIFS('2026年度培训主表'!B:B,B121,'2026年度培训主表'!D:D,F121,'2026年度培训主表'!N:N,D121) -> 24 | H121: =COUNTIFS('2026年度培训主表'!B:B,B121,'2026年度培训主表'!D:D,F121,'2026年度培训主表'!N:N,D121,'2026年度培训主表'!L:L,"已签到") -> 21 | I121: =H121/G121 -> 0.875
A122: 124 | B122: 3月 | C122: 湖北 | D122: 湖北1部 | E122: 林浩 | F122: 销售提升训 | G122: =COUNTIFS('2026年度培训主表'!B:B,B122,'2026年度培训主表'!D:D,F122,'2026年度培训主表'!N:N,D122) -> 26 | H122: =COUNTIFS('2026年度培训主表'!B:B,B122,'2026年度培训主表'!D:D,F122,'2026年度培训主表'!N:N,D122,'2026年度培训主表'!L:L,"已签到") -> 26 | I122: =H122/G122 -> 1
A123: 125 | B123: 3月 | C123: 湖北 | D123: 湖北2部 | E123: 陈晓辉 | F123: 销售提升训 | G123: =COUNTIFS('2026年度培训主表'!B:B,B123,'2026年度培训主表'!D:D,F123,'2026年度培训主表'!N:N,D123) -> 3 | H123: =COUNTIFS('2026年度培训主表'!B:B,B123,'2026年度培训主表'!D:D,F123,'2026年度培训主表'!N:N,D123,'2026年度培训主表'!L:L,"已签到") -> 0 | I123: =H123/G123 -> 0
A124: 126 | B124: 3月 | C124: 湖南 | D124: 湖南销售部 | E124: 刘进 | F124: 销售提升训 | G124: =COUNTIFS('2026年度培训主表'!B:B,B124,'2026年度培训主表'!D:D,F124,'2026年度培训主表'!N:N,D124) -> 9 | H124: =COUNTIFS('2026年度培训主表'!B:B,B124,'2026年度培训主表'!D:D,F124,'2026年度培训主表'!N:N,D124,'2026年度培训主表'!L:L,"已签到") -> 6 | I124: =H124/G124 -> 0.66666667
... A143: 145 | B143: 3月 | C143: 陕西 | D143: 陕西2部 | E143: 李耀 | F143: B岗培训 | G143: =COUNTIFS('2026年度培训主表'!B:B,B143,'2026年度培训主表'!D:D,F143,'2026年度培训主表'!N:N,D143) -> 4 | H143: =COUNTIFS('2026年度培训主表'!B:B,B143,'2026年度培训主表'!D:D,F143,'2026年度培训主表'!N:N,D143,'2026年度培训主表'!L:L,"已签到") -> 4 | I143: =H143/G143 -> 1

Sheet 《分公司》维度的参训率
A1: 《分公司》维度的参训率（1-3月）
A2: 序号 | B2: 月份 | C2: 城市 | D2: 课程类型 | E2: 应参训人次 | F2: 实际参训人次 | G2: 参训率
A3: 1 | B3: 1月 | C3: 西南总部 | D3: 销售新人入职培训 | E3: =COUNTIFS('2026年度培训主表'!B:B,B3,'2026年度培训主表'!C:C,C3,'2026年度培训主表'!D:D,D3) -> 195 | F3: =COUNTIFS('2026年度培训主表'!B:B,B3,'2026年度培训主表'!C:C,C3,'2026年度培训主表'!D:D,D3,'2026年度培训主表'!L:L,"已签到") -> 53 | G3: =F3/E3 -> 0.27179487
A4: 2 | B4: 1月 | C4: 湖南 | D4: 销售新人入职培训 | E4: =COUNTIFS('2026年度培训主表'!B:B,B4,'2026年度培训主表'!C:C,C4,'2026年度培训主表'!D:D,D4) -> 24 | F4: =COUNTIFS('2026年度培训主表'!B:B,B4,'2026年度培训主表'!C:C,C4,'2026年度培训主表'!D:D,D4,'2026年度培训主表'!L:L,"已签到") -> 12 | G4: =F4/E4 -> 0.5
A5: 3 | B5: 1月 | C5: 陕西 | D5: 销售新人入职培训 | E5: =COUNTIFS('2026年度培训主表'!B:B,B5,'2026年度培训主表'!C:C,C5,'2026年度培训主表'!D:D,D5) -> 16 | F5: =COUNTIFS('2026年度培训主表'!B:B,B5,'2026年度培训主表'!C:C,C5,'2026年度培训主表'!D:D,D5,'2026年度培训主表'!L:L,"已签到") -> 16 | G5: =F5/E5 -> 1
A6: 4 | B6: 1月 | C6: 河南 | D6: 销售新人入职培训 | E6: =COUNTIFS('2026年度培训主表'!B:B,B6,'2026年度培训主表'!C:C,C6,'2026年度培训主表'!D:D,D6) -> 24 | F6: =COUNTIFS('2026年度培训主表'!B:B,B6,'2026年度培训主表'!C:C,C6,'2026年度培训主表'!D:D,D6,'2026年度培训主表'!L:L,"已签到") -> 20 | G6: =F6/E6 -> 0.83333333
A7: 5 | B7: 1月 | C7: 湖北 | D7: 销售新人入职培训 | E7: =COUNTIFS('2026年度培训主表'!B:B,B7,'2026年度培训主表'!C:C,C7,'2026年度培训主表'!D:D,D7) -> 12 | F7: =COUNTIFS('2026年度培训主表'!B:B,B7,'2026年度培训主表'!C:C,C7,'2026年度培训主表'!D:D,D7,'2026年度培训主表'!L:L,"已签到") -> 12 | G7: =F7/E7 -> 1
A8: 6 | B8: 1月 | C8: 甘肃 | D8: 销售新人入职培训 | E8: =COUNTIFS('2026年度培训主表'!B:B,B8,'2026年度培训主表'!C:C,C8,'2026年度培训主表'!D:D,D8) -> 4 | F8: =COUNTIFS('2026年度培训主表'!B:B,B8,'2026年度培训主表'!C:C,C8,'2026年度培训主表'!D:D,D8,'2026年度培训主表'!L:L,"已签到") -> 4 | G8: =F8/E8 -> 1
A9: 7 | B9: 1月 | C9: 山东 | D9: 销售新人入职培训 | E9: =COUNTIFS('2026年度培训主表'!B:B,B9,'2026年度培训主表'!C:C,C9,'2026年度培训主表'!D:D,D9) -> 8 | F9: =COUNTIFS('2026年度培训主表'!B:B,B9,'2026年度培训主表'!C:C,C9,'2026年度培训主表'!D:D,D9,'2026年度培训主表'!L:L,"已签到") -> 8 | G9: =F9/E9 -> 1
A10: 8 | B10: 1月 | C10: 内蒙古 | D10: 销售新人入职培训 | E10: =COUNTIFS('2026年度培训主表'!B:B,B10,'2026年度培训主表'!C:C,C10,'2026年度培训主表'!D:D,D10) -> 12 | F10: =COUNTIFS('2026年度培训主表'!B:B,B10,'2026年度培训主表'!C:C,C10,'2026年度培训主表'!D:D,D10,'2026年度培训主表'!L:L,"已签到") -> 12 | G10: =F10/E10 -> 1
A11: 9 | B11: 1月 | C11: 河北 | D11: 销售新人入职培训 | E11: =COUNTIFS('2026年度培训主表'!B:B,B11,'2026年度培训主表'!C:C,C11,'2026年度培训主表'!D:D,D11) -> 16 | F11: =COUNTIFS('2026年度培训主表'!B:B,B11,'2026年度培训主表'!C:C,C11,'2026年度培训主表'!D:D,D11,'2026年度培训主表'!L:L,"已签到") -> 12 | G11: =F11/E11 -> 0.75
A12: 10 | B12: 1月 | C12: 西南总部 | D12: 销售提升训 | E12: =COUNTIFS('2026年度培训主表'!B:B,B12,'2026年度培训主表'!C:C,C12,'2026年度培训主表'!D:D,D12) -> 163 | F12: =COUNTIFS('2026年度培训主表'!B:B,B12,'2026年度培训主表'!C:C,C12,'2026年度培训主表'!D:D,D12,'2026年度培训主表'!L:L,"已签到") -> 55 | G12: =F12/E12 -> 0.33742331
A13: 11 | B13: 1月 | C13: 陕西 | D13: 销售提升训 | E13: =COUNTIFS('2026年度培训主表'!B:B,B13,'2026年度培训主表'!C:C,C13,'2026年度培训主表'!D:D,D13) -> 12 | F13: =COUNTIFS('2026年度培训主表'!B:B,B13,'2026年度培训主表'!C:C,C13,'2026年度培训主表'!D:D,D13,'2026年度培训主表'!L:L,"已签到") -> 9 | G13: =F13/E13 -> 0.75
A14: 12 | B14: 1月 | C14: 湖北 | D14: 销售提升训 | E14: =COUNTIFS('2026年度培训主表'!B:B,B14,'2026年度培训主表'!C:C,C14,'2026年度培训主表'!D:D,D14) -> 14 | F14: =COUNTIFS('2026年度培训主表'!B:B,B14,'2026年度培训主表'!C:C,C14,'2026年度培训主表'!D:D,D14,'2026年度培训主表'!L:L,"已签到") -> 0 | G14: =F14/E14 -> 0
... A77: 85 | B77: 3月 | C77: 辽宁 | D77: 销售新人入职培训 | E77: =COUNTIFS('2026年度培训主表'!B:B,B77,'2026年度培训主表'!C:C,C77,'2026年度培训主表'!D:D,D77) -> 8 | F77: =COUNTIFS('2026年度培训主表'!B:B,B77,'2026年度培训主表'!C:C,C77,'2026年度培训主表'!D:D,D77,'2026年度培训主表'!L:L,"已签到") -> 8 | G77: =F77/E77 -> 1

Sheet 《课程名称》维度的参训明细（主表）
A1: 《课程名称》维度的参训明细（主表）1-3月
A2: 序号 | B2: 月份 | C2: 城市 | D2: 营业部 | E2: 直系上级 | F2: 应参训人姓名 | G2: 工号 | H2: 职级 | I2: 签到情况 | J2: 培训时间 | K2: 课程名称 | L2: 授课类型
A3: 1 | B3: 1月 | C3: 西南总部 | D3: 营业五部 | E3: 安芮内蒙古 | F3: 蒋婷 | G3: 01011 | H3: 一星销售顾问 | I3: 未签到 | J3: 46035 | K3: 《心态与成败》 | L3: 销售提升训
A4: 2 | B4: 1月 | C4: 西南总部 | D4: 营业五部 | E4: 安芮内蒙古 | F4: 孙智港 | G4: 01423 | H4: 一星销售顾问 | I4: 未签到 | J4: 46035 | K4: 《心态与成败》 | L4: 销售提升训
A5: 3 | B5: 1月 | C5: 西南总部 | D5: 营业五部 | E5: 安芮内蒙古 | F5: 李裕楷 | G5: 01412 | H5: 一星销售顾问 | I5: 未签到 | J5: 46035 | K5: 《心态与成败》 | L5: 销售提升训
A6: 4 | B6: 1月 | C6: 西南总部 | D6: 营业二部 | E6: 柏刚 | F6: 税小蓉 | G6: 01684 | H6: 一星销售顾问 | I6: 已签到 | J6: 46035 | K6: 《心态与成败》 | L6: 销售提升训
A7: 5 | B7: 1月 | C7: 陕西 | D7: 陕西2部 | E7: 李丝丝 | F7: 李松 | G7: 01689 | H7: 一星销售顾问 | I7: 已签到 | J7: 46035 | K7: 《心态与成败》 | L7: 销售提升训
A8: 6 | B8: 1月 | C8: 西南总部 | D8: 营业一部 | E8: 白世根 | F8: 先波 | G8: 01512 | H8: 二星销售顾问 | I8: 未签到 | J8: 46035 | K8: 《心态与成败》 | L8: 销售提升训
A9: 7 | B9: 1月 | C9: 西南总部 | D9: 营业七部 | E9: 陈彪 | F9: 田丰 | G9: 01500 | H9: 一星销售顾问 | I9: 未签到 | J9: 46035 | K9: 《心态与成败》 | L9: 销售提升训
A10: 8 | B10: 1月 | C10: 西南总部 | D10: 营业四部 | E10: 陈帅 | F10: 邓孝礼 | G10: 01621 | H10: 一星销售顾问 | I10: 已签到 | J10: 46035 | K10: 《心态与成败》 | L10: 销售提升训
A11: 9 | B11: 1月 | C11: 湖北 | D11: 湖北1部 | E11: 张宗铭湖北 | F11: 黄建 | G11: 01657 | H11: 一星销售顾问 | I11: 未签到 | J11: 46035 | K11: 《心态与成败》 | L11: 销售提升训
A12: 10 | B12: 1月 | C12: 西南总部 | D12: 营业四部 | E12: 陈嘉文 | F12: 向巡 | G12: 01634 | H12: 一星销售顾问 | I12: 未签到 | J12: 46035 | K12: 《心态与成败》 | L12: 销售提升训
A13: 11 | B13: 1月 | C13: 西南总部 | D13: 营业四部 | E13: 陈嘉文 | F13: 陈帅2 | G13: 01488 | H13: 二星销售顾问 | I13: 未签到 | J13: 46035 | K13: 《心态与成败》 | L13: 销售提升训
A14: 12 | B14: 1月 | C14: 陕西 | D14: 陕西2部 | E14: 冀敏 | F14: 涂正丽 | G14: 01654 | H14: 一星销售顾问 | I14: 未签到 | J14: 46035 | K14: 《心态与成败》 | L14: 销售提升训
... A761: 759 | B761: 1月 | C761: 西南总部 | D761: 营业一部 | E761: 白世根 | F761: 李青松 | G761: 01821 | H761: 实习销售 | I761: 未签到 | J761: 46051 | K761: 《走进蜂族科技》 | L761: 销售新人入职培训
A762: 760 | B762: 2月 | C762: =VLOOKUP(F762,[4]在职!$A:$E,5,0) -> 安徽 | D762: 安徽拓展部 | E762: =VLOOKUP(F762,[4]在职!$A:$M,13,0) -> 黄芳 | F762: 许钊 | G762: =VLOOKUP(F762,[4]在职!$A:$B,2,0) -> 00032 | H762: =VLOOKUP(F762,[4]在职!$A:$I,9,0) -> 分公司总经理 | I762: 已签到 | J762: 46077 | K762: 《讲师TTT培训》 | L762: 《讲师TTT培训》
A763: 761 | B763: 2月 | C763: =VLOOKUP(F763,[4]在职!$A:$E,5,0) -> 安徽 | D763: 安徽拓展部 | E763: =VLOOKUP(F763,[4]在职!$A:$M,13,0) -> 黄芳 | F763: 许钊 | G763: =VLOOKUP(F763,[4]在职!$A:$B,2,0) -> 00032 | H763: =VLOOKUP(F763,[4]在职!$A:$I,9,0) -> 分公司总经理 | I763: 已签到 | J763: 46078 | K763: 《讲师TTT培训》 | L763: 《讲师TTT培训》
A764: 762 | B764: 2月 | C764: =VLOOKUP(F764,[4]在职!$A:$E,5,0) -> 西南总部 | D764: =VLOOKUP(F764,[4]在职!$A:$G,7,0) -> 川北 | E764: =VLOOKUP(F764,[4]在职!$A:$M,13,0) -> 刘文宇 | F764: 蒋婉萍 | G764: =VLOOKUP(F764,[4]在职!$A:$B,2,0) -> 00745 | H764: =VLOOKUP(F764,[4]在职!$A:$I,9,0) -> 区域拓展总监 | I764: 已签到 | J764: 46077 | K764: 《讲师TTT培训》 | L764: 《讲师TTT培训》
A765: 763 | B765: 2月 | C765: =VLOOKUP(F765,[4]在职!$A:$E,5,0) -> 西南总部 | D765: =VLOOKUP(F765,[4]在职!$A:$G,7,0) -> 川北 | E765: =VLOOKUP(F765,[4]在职!$A:$M,13,0) -> 刘文宇 | F765: 蒋婉萍 | G765: =VLOOKUP(F765,[4]在职!$A:$B,2,0) -> 00745 | H765: =VLOOKUP(F765,[4]在职!$A:$I,9,0) -> 区域拓展总监 | I765: 已签到 | J765: 46078 | K765: 《讲师TTT培训》 | L765: 《讲师TTT培训》
A766: 764 | B766: 2月 | C766: =VLOOKUP(F766,[4]在职!$A:$E,5,0) -> 西南总部 | D766: =VLOOKUP(F766,[4]在职!$A:$G,7,0) -> 川东 | E766: =VLOOKUP(F766,[4]在职!$A:$M,13,0) -> 刘文宇 | F766: 刘超 | G766: =VLOOKUP(F766,[4]在职!$A:$B,2,0) -> 00029 | H766: =VLOOKUP(F766,[4]在职!$A:$I,9,0) -> 区域拓展总监 | I766: 已签到 | J766: 46077 | K766: 《讲师TTT培训》 | L766: 《讲师TTT培训》
A767: 765 | B767: 2月 | C767: =VLOOKUP(F767,[4]在职!$A:$E,5,0) -> 西南总部 | D767: =VLOOKUP(F767,[4]在职!$A:$G,7,0) -> 川东 | E767: =VLOOKUP(F767,[4]在职!$A:$M,13,0) -> 刘超 | F767: 向高涵 | G767: =VLOOKUP(F767,[4]在职!$A:$B,2,0) -> 00590 | H767: =VLOOKUP(F767,[4]在职!$A:$I,9,0) -> 二星拓展专员 | I767: 已签到 | J767: 46077 | K767: 《讲师TTT培训》 | L767: 《讲师TTT培训》
A768: 766 | B768: 2月 | C768: =VLOOKUP(F768,[4]在职!$A:$E,5,0) -> 西南总部 | D768: =VLOOKUP(F768,[4]在职!$A:$G,7,0) -> 川东 | E768: =VLOOKUP(F768,[4]在职!$A:$M,13,0) -> 刘文宇 | F768: 刘超 | G768: =VLOOKUP(F768,[4]在职!$A:$B,2,0) -> 00029 | H768: =VLOOKUP(F768,[4]在职!$A:$I,9,0) -> 区域拓展总监 | I768: 已签到 | J768: 46078 | K768: 《讲师TTT培训》 | L768: 《讲师TTT培训》
A769: 767 | B769: 2月 | C769: =VLOOKUP(F769,[4]在职!$A:$E,5,0) -> 西南总部 | D769: =VLOOKUP(F769,[4]在职!$A:$G,7,0) -> 川东 | E769: =VLOOKUP(F769,[4]在职!$A:$M,13,0) -> 刘超 | F769: 向高涵 | G769: =VLOOKUP(F769,[4]在职!$A:$B,2,0) -> 00590 | H769: =VLOOKUP(F769,[4]在职!$A:$I,9,0) -> 二星拓展专员 | I769: 已签到 | J769: 46078 | K769: 《讲师TTT培训》 | L769: 《讲师TTT培训》
A770: 768 | B770: 2月 | C770: =VLOOKUP(F770,[4]在职!$A:$E,5,0) -> 西南总部 | D770: =VLOOKUP(F770,[4]在职!$A:$G,7,0) -> 川南 | E770: =VLOOKUP(F770,[4]在职!$A:$M,13,0) -> 刘文宇 | F770: 于强 | G770: =VLOOKUP(F770,[4]在职!$A:$B,2,0) -> 00416 | H770: =VLOOKUP(F770,[4]在职!$A:$I,9,0) -> 区域拓展总监 | I770: 已签到 | J770: 46077 | K770: 《讲师TTT培训》 | L770: 《讲师TTT培训》
A771: 769 | B771: 2月 | C771: =VLOOKUP(F771,[4]在职!$A:$E,5,0) -> 西南总部 | D771: =VLOOKUP(F771,[4]在职!$A:$G,7,0) -> 川南 | E771: =VLOOKUP(F771,[4]在职!$A:$M,13,0) -> 刘文宇 | F771: 于强 | G771: =VLOOKUP(F771,[4]在职!$A:$B,2,0) -> 00416 | H771: =VLOOKUP(F771,[4]在职!$A:$I,9,0) -> 区域拓展总监 | I771: 已签到 | J771: 46078 | K771: 《讲师TTT培训》 | L771: 《讲师TTT培训》
A772: 770 | B772: 2月 | C772: =VLOOKUP(F772,[4]在职!$A:$E,5,0) -> 西南总部 | D772: =VLOOKUP(F772,[4]在职!$A:$G,7,0) -> 川西 | E772: =VLOOKUP(F772,[4]在职!$A:$M,13,0) -> 刘文宇 | F772: 杨蓉 | G772: =VLOOKUP(F772,[4]在职!$A:$B,2,0) -> 00770 | H772: =VLOOKUP(F772,[4]在职!$A:$I,9,0) -> 区域拓展总监 | I772: 已签到 | J772: 46077 | K772: 《讲师TTT培训》 | L772: 《讲师TTT培训》
A773: 771 | B773: 2月 | C773: =VLOOKUP(F773,[4]在职!$A:$E,5,0) -> 西南总部 | D773: =VLOOKUP(F773,[4]在职!$A:$G,7,0) -> 川西 | E773: =VLOOKUP(F773,[4]在职!$A:$M,13,0) -> 刘文宇 | F773: 杨蓉 | G773: =VLOOKUP(F773,[4]在职!$A:$B,2,0) -> 00770 | H773: =VLOOKUP(F773,[4]在职!$A:$I,9,0) -> 区域拓展总监 | I773: 已签到 | J773: 46078 | K773: 《讲师TTT培训》 | L773: 《讲师TTT培训》
A774: 772 | B774: 2月 | C774: =VLOOKUP(F774,[4]在职!$A:$E,5,0) -> 甘肃 | D774: 甘肃拓展部 | E774: =VLOOKUP(F774,[4]在职!$A:$M,13,0) -> 黄芳 | F774: 雷鸣 | G774: =VLOOKUP(F774,[4]在职!$A:$B,2,0) -> 00248 | H774: =VLOOKUP(F774,[4]在职!$A:$I,9,0) -> 区域拓展总监 | I774: 已签到 | J774: 46077 | K774: 《讲师TTT培训》 | L774: 《讲师TTT培训》
A775: 773 | B775: 2月 | C775: =VLOOKUP(F775,[4]在职!$A:$E,5,0) -> 甘肃 | D775: 甘肃拓展部 | E775: =VLOOKUP(F775,[4]在职!$A:$M,13,0) -> 黄芳 | F775: 雷鸣 | G775: =VLOOKUP(F775,[4]在职!$A:$B,2,0) -> 00248 | H775: =VLOOKUP(F775,[4]在职!$A:$I,9,0) -> 区域拓展总监 | I775: 已签到 | J775: 46078 | K775: 《讲师TTT培训》 | L775: 《讲师TTT培训》
A776: 774 | B776: 2月 | C776: =VLOOKUP(F776,[4]在职!$A:$E,5,0) -> 河北 | D776: 河北拓展部 | E776: 黄芳 | F776: 张冀 | G776: =VLOOKUP(F776,[4]在职!$A:$B,2,0) -> 00039 | H776: =VLOOKUP(F776,[4]在职!$A:$I,9,0) -> 分公司总经理 | I776: 已签到 | J776: 46077 | K776: 《讲师TTT培训》 | L776: 《讲师TTT培训》
A777: 775 | B777: 2月 | C777: =VLOOKUP(F777,[4]在职!$A:$E,5,0) -> 河北 | D777: 河北拓展部 | E777: 黄芳 | F777: 张冀 | G777: =VLOOKUP(F777,[4]在职!$A:$B,2,0) -> 00039 | H777: =VLOOKUP(F777,[4]在职!$A:$I,9,0) -> 分公司总经理 | I777: 已签到 | J777: 46078 | K777: 《讲师TTT培训》 | L777: 《讲师TTT培训》
A778: 776 | B778: 2月 | C778: =VLOOKUP(F778,[4]在职!$A:$E,5,0) -> 河北 | D778: =VLOOKUP(F778,[4]在职!$A:$G,7,0) -> 0 | E778: =VLOOKUP(F778,[4]在职!$A:$M,13,0) -> 张冀 | F778: 李港一 | G778: =VLOOKUP(F778,[4]在职!$A:$B,2,0) -> 00008 | H778: =VLOOKUP(F778,[4]在职!$A:$I,9,0) -> 分公司副总经理 | I778: 已签到 | J778: 46077 | K778: 《讲师TTT培训》 | L778: 《讲师TTT培训》
A779: 777 | B779: 2月 | C779: =VLOOKUP(F779,[4]在职!$A:$E,5,0) -> 河北 | D779: =VLOOKUP(F779,[4]在职!$A:$G,7,0) -> 河北销售部 | E779: =VLOOKUP(F779,[4]在职!$A:$M,13,0) -> 李港一 | F779: 韩旭 | G779: =VLOOKUP(F779,[4]在职!$A:$B,2,0) -> 00263 | H779: =VLOOKUP(F779,[4]在职!$A:$I,9,0) -> 一星正式经理 | I779: 已签到 | J779: 46077 | K779: 《讲师TTT培训》 | L779: 《讲师TTT培训》
A780: 778 | B780: 2月 | C780: =VLOOKUP(F780,[4]在职!$A:$E,5,0) -> 河北 | D780: =VLOOKUP(F780,[4]在职!$A:$G,7,0) -> 0 | E780: =VLOOKUP(F780,[4]在职!$A:$M,13,0) -> 张冀 | F780: 李港一 | G780: =VLOOKUP(F780,[4]在职!$A:$B,2,0) -> 00008 | H780: =VLOOKUP(F780,[4]在职!$A:$I,9,0) -> 分公司副总经理 | I780: 已签到 | J780: 46078 | K780: 《讲师TTT培训》 | L780: 《讲师TTT培训》
A781: 779 | B781: 2月 | C781: =VLOOKUP(F781,[4]在职!$A:$E,5,0) -> 河北 | D781: =VLOOKUP(F781,[4]在职!$A:$G,7,0) -> 河北销售部 | E781: =VLOOKUP(F781,[4]在职!$A:$M,13,0) -> 李港一 | F781: 韩旭 | G781: =VLOOKUP(F781,[4]在职!$A:$B,2,0) -> 00263 | H781: =VLOOKUP(F781,[4]在职!$A:$I,9,0) -> 一星正式经理 | I781: 已签到 | J781: 46078 | K781: 《讲师TTT培训》 | L781: 《讲师TTT培训》
A782: 780 | B782: 2月 | C782: =VLOOKUP(F782,[4]在职!$A:$E,5,0) -> 河南 | D782: 河南拓展部 | E782: =VLOOKUP(F782,[4]在职!$A:$M,13,0) -> 黄芳 | F782: 廖静 | G782: =VLOOKUP(F782,[4]在职!$A:$B,2,0) -> 00040 | H782: =VLOOKUP(F782,[4]在职!$A:$I,9,0) -> 分公司总经理 | I782: 已签到 | J782: 46077 | K782: 《讲师TTT培训》 | L782: 《讲师TTT培训》
A783: 781 | B783: 2月 | C783: =VLOOKUP(F783,[4]在职!$A:$E,5,0) -> 河南 | D783: 河南拓展部 | E783: =VLOOKUP(F783,[4]在职!$A:$M,13,0) -> 黄芳 | F783: 廖静 | G783: =VLOOKUP(F783,[4]在职!$A:$B,2,0) -> 00040 | H783: =VLOOKUP(F783,[4]在职!$A:$I,9,0) -> 分公司总经理 | I783: 已签到 | J783: 46078 | K783: 《讲师TTT培训》 | L783: 《讲师TTT培训》
A784: 782 | B784: 2月 | C784: =VLOOKUP(F784,[4]在职!$A:$E,5,0) -> 河南 | D784: =VLOOKUP(F784,[4]在职!$A:$G,7,0) -> 河南销售部 | E784: =VLOOKUP(F784,[4]在职!$A:$M,13,0) -> 毛孝树 | F784: 周吉双 | G784: =VLOOKUP(F784,[4]在职!$A:$B,2,0) -> 00270 | H784: =VLOOKUP(F784,[4]在职!$A:$I,9,0) -> 部长 | I784: 已签到 | J784: 46077 | K784: 《讲师TTT培训》 | L784: 《讲师TTT培训》
A785: 783 | B785: 2月 | C785: =VLOOKUP(F785,[4]在职!$A:$E,5,0) -> 河南 | D785: =VLOOKUP(F785,[4]在职!$A:$G,7,0) -> 0 | E785: =VLOOKUP(F785,[4]在职!$A:$M,13,0) -> 廖静 | F785: 毛孝树 | G785: =VLOOKUP(F785,[4]在职!$A:$B,2,0) -> 00010 | H785: =VLOOKUP(F785,[4]在职!$A:$I,9,0) -> 分公司副总经理 | I785: 已签到 | J785: 46077 | K785: 《讲师TTT培训》 | L785: 《讲师TTT培训》
A786: 784 | B786: 2月 | C786: =VLOOKUP(F786,[4]在职!$A:$E,5,0) -> 河南 | D786: =VLOOKUP(F786,[4]在职!$A:$G,7,0) -> 河南销售部 | E786: =VLOOKUP(F786,[4]在职!$A:$M,13,0) -> 毛孝树 | F786: 周吉双 | G786: =VLOOKUP(F786,[4]在职!$A:$B,2,0) -> 00270 | H786: =VLOOKUP(F786,[4]在职!$A:$I,9,0) -> 部长 | I786: 已签到 | J786: 46078 | K786: 《讲师TTT培训》 | L786: 《讲师TTT培训》
A787: 785 | B787: 2月 | C787: =VLOOKUP(F787,[4]在职!$A:$E,5,0) -> 河南 | D787: =VLOOKUP(F787,[4]在职!$A:$G,7,0) -> 0 | E787: =VLOOKUP(F787,[4]在职!$A:$M,13,0) -> 廖静 | F787: 毛孝树 | G787: =VLOOKUP(F787,[4]在职!$A:$B,2,0) -> 00010 | H787: =VLOOKUP(F787,[4]在职!$A:$I,9,0) -> 分公司副总经理 | I787: 已签到 | J787: 46078 | K787: 《讲师TTT培训》 | L787: 《讲师TTT培训》
A788: 786 | B788: 2月 | C788: =VLOOKUP(F788,[4]在职!$A:$E,5,0) -> 湖北 | D788: =VLOOKUP(F788,[4]在职!$A:$G,7,0) -> 湖北1部 | E788: =VLOOKUP(F788,[4]在职!$A:$M,13,0) -> 范庚 | F788: 林浩 | G788: =VLOOKUP(F788,[4]在职!$A:$B,2,0) -> 00333 | H788: =VLOOKUP(F788,[4]在职!$A:$I,9,0) -> 部长 | I788: 已签到 | J788: 46077 | K788: 《讲师TTT培训》 | L788: 《讲师TTT培训》
A789: 787 | B789: 2月 | C789: =VLOOKUP(F789,[4]在职!$A:$E,5,0) -> 湖北 | D789: =VLOOKUP(F789,[4]在职!$A:$G,7,0) -> 湖北1部 | E789: =VLOOKUP(F789,[4]在职!$A:$M,13,0) -> 范庚 | F789: 林浩 | G789: =VLOOKUP(F789,[4]在职!$A:$B,2,0) -> 00333 | H789: =VLOOKUP(F789,[4]在职!$A:$I,9,0) -> 部长 | I789: 已签到 | J789: 46078 | K789: 《讲师TTT培训》 | L789: 《讲师TTT培训》
A790: 788 | B790: 2月 | C790: =VLOOKUP(F790,[4]在职!$A:$E,5,0) -> 湖北 | D790: =VLOOKUP(F790,[4]在职!$A:$G,7,0) -> 湖北2部 | E790: =VLOOKUP(F790,[4]在职!$A:$M,13,0) -> 范庚 | F790: 陈晓辉 | G790: =VLOOKUP(F790,[4]在职!$A:$B,2,0) -> 00549 | H790: =VLOOKUP(F790,[4]在职!$A:$I,9,0) -> 部长 | I790: 已签到 | J790: 46077 | K790: 《讲师TTT培训》 | L790: 《讲师TTT培训》
A791: 789 | B791: 2月 | C791: =VLOOKUP(F791,[4]在职!$A:$E,5,0) -> 湖北 | D791: =VLOOKUP(F791,[4]在职!$A:$G,7,0) -> 湖北2部 | E791: =VLOOKUP(F791,[4]在职!$A:$M,13,0) -> 范庚 | F791: 陈晓辉 | G791: =VLOOKUP(F791,[4]在职!$A:$B,2,0) -> 00549 | H791: =VLOOKUP(F791,[4]在职!$A:$I,9,0) -> 部长 | I791: 已签到 | J791: 46078 | K791: 《讲师TTT培训》 | L791: 《讲师TTT培训》
A792: 790 | B792: 2月 | C792: =VLOOKUP(F792,[4]在职!$A:$E,5,0) -> 湖北 | D792: 湖北拓展部 | E792: =VLOOKUP(F792,[4]在职!$A:$M,13,0) -> 黄芳 | F792: 范庚 | G792: =VLOOKUP(F792,[4]在职!$A:$B,2,0) -> 00004 | H792: =VLOOKUP(F792,[4]在职!$A:$I,9,0) -> 分公司总经理 | I792: 已签到 | J792: 46077 | K792: 《讲师TTT培训》 | L792: 《讲师TTT培训》
A793: 791 | B793: 2月 | C793: =VLOOKUP(F793,[4]在职!$A:$E,5,0) -> 湖北 | D793: 湖北1部 | E793: =VLOOKUP(F793,[4]在职!$A:$M,13,0) -> 黄芳 | F793: 范庚 | G793: =VLOOKUP(F793,[4]在职!$A:$B,2,0) -> 00004 | H793: =VLOOKUP(F793,[4]在职!$A:$I,9,0) -> 分公司总经理 | I793: 已签到 | J793: 46078 | K793: 《讲师TTT培训》 | L793: 《讲师TTT培训》
A794: 792 | B794: 2月 | C794: =VLOOKUP(F794,[4]在职!$A:$E,5,0) -> 湖南 | D794: 湖南拓展部 | E794: =VLOOKUP(F794,[4]在职!$A:$M,13,0) -> 王超飞 | F794: 刘岷 | G794: =VLOOKUP(F794,[4]在职!$A:$B,2,0) -> 00235 | H794: =VLOOKUP(F794,[4]在职!$A:$I,9,0) -> 二星拓展专员 | I794: 已签到 | J794: 46077 | K794: 《讲师TTT培训》 | L794: 《讲师TTT培训》
A795: 793 | B795: 2月 | C795: =VLOOKUP(F795,[4]在职!$A:$E,5,0) -> 湖南 | D795: 湖南拓展部 | E795: =VLOOKUP(F795,[4]在职!$A:$M,13,0) -> 黄芳 | F795: 王超飞 | G795: =VLOOKUP(F795,[4]在职!$A:$B,2,0) -> 00094 | H795: =VLOOKUP(F795,[4]在职!$A:$I,9,0) -> 分公司总经理 | I795: 已签到 | J795: 46077 | K795: 《讲师TTT培训》 | L795: 《讲师TTT培训》
A796: 794 | B796: 2月 | C796: =VLOOKUP(F796,[4]在职!$A:$E,5,0) -> 湖南 | D796: 湖南拓展部 | E796: =VLOOKUP(F796,[4]在职!$A:$M,13,0) -> 王超飞 | F796: 刘岷 | G796: =VLOOKUP(F796,[4]在职!$A:$B,2,0) -> 00235 | H796: =VLOOKUP(F796,[4]在职!$A:$I,9,0) -> 二星拓展专员 | I796: 已签到 | J796: 46078 | K796: 《讲师TTT培训》 | L796: 《讲师TTT培训》
A797: 795 | B797: 2月 | C797: =VLOOKUP(F797,[4]在职!$A:$E,5,0) -> 湖南 | D797: 湖南拓展部 | E797: =VLOOKUP(F797,[4]在职!$A:$M,13,0) -> 黄芳 | F797: 王超飞 | G797: =VLOOKUP(F797,[4]在职!$A:$B,2,0) -> 00094 | H797: =VLOOKUP(F797,[4]在职!$A:$I,9,0) -> 分公司总经理 | I797: 已签到 | J797: 46078 | K797: 《讲师TTT培训》 | L797: 《讲师TTT培训》
A798: 796 | B798: 2月 | C798: =VLOOKUP(F798,[4]在职!$A:$E,5,0) -> 湖南 | D798: =VLOOKUP(F798,[4]在职!$A:$G,7,0) -> 湖南销售部 | E798: =VLOOKUP(F798,[4]在职!$A:$M,13,0) -> 王超飞 | F798: 刘进 | G798: =VLOOKUP(F798,[4]在职!$A:$B,2,0) -> 00050 | H798: =VLOOKUP(F798,[4]在职!$A:$I,9,0) -> 分公司副总经理 | I798: 已签到 | J798: 46077 | K798: 《讲师TTT培训》 | L798: 《讲师TTT培训》
A799: 797 | B799: 2月 | C799: =VLOOKUP(F799,[4]在职!$A:$E,5,0) -> 湖南 | D799: =VLOOKUP(F799,[4]在职!$A:$G,7,0) -> 湖南销售部 | E799: =VLOOKUP(F799,[4]在职!$A:$M,13,0) -> 王超飞 | F799: 刘进 | G799: =VLOOKUP(F799,[4]在职!$A:$B,2,0) -> 00050 | H799: =VLOOKUP(F799,[4]在职!$A:$I,9,0) -> 分公司副总经理 | I799: 已签到 | J799: 46078 | K799: 《讲师TTT培训》 | L799: 《讲师TTT培训》
A800: 798 | B800: 2月 | C800: =VLOOKUP(F800,[4]在职!$A:$E,5,0) -> 辽宁 | D800: 辽宁拓展部 | E800: =VLOOKUP(F800,[4]在职!$A:$M,13,0) -> 黄芳 | F800: 聂仕平 | G800: =VLOOKUP(F800,[4]在职!$A:$B,2,0) -> 00057 | H800: =VLOOKUP(F800,[4]在职!$A:$I,9,0) -> 分公司总经理 | I800: 已签到 | J800: 46077 | K800: 《讲师TTT培训》 | L800: 《讲师TTT培训》
A801: 799 | B801: 2月 | C801: =VLOOKUP(F801,[4]在职!$A:$E,5,0) -> 辽宁 | D801: 辽宁拓展部 | E801: =VLOOKUP(F801,[4]在职!$A:$M,13,0) -> 黄芳 | F801: 聂仕平 | G801: =VLOOKUP(F801,[4]在职!$A:$B,2,0) -> 00057 | H801: =VLOOKUP(F801,[4]在职!$A:$I,9,0) -> 分公司总经理 | I801: 已签到 | J801: 46078 | K801: 《讲师TTT培训》 | L801: 《讲师TTT培训》
A802: 800 | B802: 2月 | C802: =VLOOKUP(F802,[4]在职!$A:$E,5,0) -> 辽宁 | D802: =VLOOKUP(F802,[4]在职!$A:$G,7,0) -> 0 | E802: =VLOOKUP(F802,[4]在职!$A:$M,13,0) -> 聂仕平 | F802: 赖慧 | G802: =VLOOKUP(F802,[4]在职!$A:$B,2,0) -> 00016 | H802: =VLOOKUP(F802,[4]在职!$A:$I,9,0) -> 分公司副总经理 | I802: 已签到 | J802: 46077 | K802: 《讲师TTT培训》 | L802: 《讲师TTT培训》
A803: 801 | B803: 2月 | C803: =VLOOKUP(F803,[4]在职!$A:$E,5,0) -> 辽宁 | D803: =VLOOKUP(F803,[4]在职!$A:$G,7,0) -> 0 | E803: =VLOOKUP(F803,[4]在职!$A:$M,13,0) -> 聂仕平 | F803: 赖慧 | G803: =VLOOKUP(F803,[4]在职!$A:$B,2,0) -> 00016 | H803: =VLOOKUP(F803,[4]在职!$A:$I,9,0) -> 分公司副总经理 | I803: 已签到 | J803: 46078 | K803: 《讲师TTT培训》 | L803: 《讲师TTT培训》
A804: 802 | B804: 2月 | C804: =VLOOKUP(F804,[4]在职!$A:$E,5,0) -> 内蒙古 | D804: 内蒙古拓展部 | E804: =VLOOKUP(F804,[4]在职!$A:$M,13,0) -> 刘文宇 | F804: 刘宇 | G804: =VLOOKUP(F804,[4]在职!$A:$B,2,0) -> 00154 | H804: =VLOOKUP(F804,[4]在职!$A:$I,9,0) -> 分公司总经理 | I804: 已签到 | J804: 46077 | K804: 《讲师TTT培训》 | L804: 《讲师TTT培训》
A805: 803 | B805: 2月 | C805: =VLOOKUP(F805,[4]在职!$A:$E,5,0) -> 内蒙古 | D805: 内蒙古拓展中心 | E805: =VLOOKUP(F805,[4]在职!$A:$M,13,0) -> 刘文宇 | F805: 刘宇 | G805: =VLOOKUP(F805,[4]在职!$A:$B,2,0) -> 00154 | H805: =VLOOKUP(F805,[4]在职!$A:$I,9,0) -> 分公司总经理 | I805: 已签到 | J805: 46078 | K805: 《讲师TTT培训》 | L805: 《讲师TTT培训》
A806: 804 | B806: 2月 | C806: =VLOOKUP(F806,[4]在职!$A:$E,5,0) -> 山东 | D806: 宁夏拓展中心 | E806: =VLOOKUP(F806,[4]在职!$A:$M,13,0) -> 刘文宇 | F806: 黄小东 | G806: =VLOOKUP(F806,[4]在职!$A:$B,2,0) -> 00215 | H806: =VLOOKUP(F806,[4]在职!$A:$I,9,0) -> 区域拓展总监 | I806: 已签到 | J806: 46078 | K806: 《讲师TTT培训》 | L806: 《讲师TTT培训》
A807: 805 | B807: 2月 | C807: 宁夏 | D807: 宁夏拓展中心 | E807: =VLOOKUP(F807,[4]在职!$A:$M,13,0) -> 刘文宇 | F807: 黄小东 | G807: =VLOOKUP(F807,[4]在职!$A:$B,2,0) -> 00215 | H807: =VLOOKUP(F807,[4]在职!$A:$I,9,0) -> 区域拓展总监 | I807: 已签到 | J807: 46077 | K807: 《讲师TTT培训》 | L807: 《讲师TTT培训》
A808: 806 | B808: 2月 | C808: =VLOOKUP(F808,[4]在职!$A:$E,5,0) -> 山东 | D808: 山东拓展部 | E808: =VLOOKUP(F808,[4]在职!$A:$M,13,0) -> 李丹 | F808: 向润 | G808: =VLOOKUP(F808,[4]在职!$A:$B,2,0) -> 00315 | H808: =VLOOKUP(F808,[4]在职!$A:$I,9,0) -> 区域拓展总监 | I808: 已签到 | J808: 46077 | K808: 《讲师TTT培训》 | L808: 《讲师TTT培训》
A809: 807 | B809: 2月 | C809: =VLOOKUP(F809,[4]在职!$A:$E,5,0) -> 山东 | D809: 山东拓展部 | E809: =VLOOKUP(F809,[4]在职!$A:$M,13,0) -> 黄芳 | F809: 李丹 | G809: =VLOOKUP(F809,[4]在职!$A:$B,2,0) -> 00067 | H809: =VLOOKUP(F809,[4]在职!$A:$I,9,0) -> 分公司总经理 | I809: 已签到 | J809: 46077 | K809: 《讲师TTT培训》 | L809: 《讲师TTT培训》
A810: 808 | B810: 2月 | C810: =VLOOKUP(F810,[4]在职!$A:$E,5,0) -> 山东 | D810: 山东拓展部 | E810: =VLOOKUP(F810,[4]在职!$A:$M,13,0) -> 李丹 | F810: 向润 | G810: =VLOOKUP(F810,[4]在职!$A:$B,2,0) -> 00315 | H810: =VLOOKUP(F810,[4]在职!$A:$I,9,0) -> 区域拓展总监 | I810: 已签到 | J810: 46078 | K810: 《讲师TTT培训》 | L810: 《讲师TTT培训》
A811: 809 | B811: 2月 | C811: =VLOOKUP(F811,[4]在职!$A:$E,5,0) -> 山东 | D811: 山东拓展部 | E811: =VLOOKUP(F811,[4]在职!$A:$M,13,0) -> 黄芳 | F811: 李丹 | G811: =VLOOKUP(F811,[4]在职!$A:$B,2,0) -> 00067 | H811: =VLOOKUP(F811,[4]在职!$A:$I,9,0) -> 分公司总经理 | I811: 已签到 | J811: 46078 | K811: 《讲师TTT培训》 | L811: 《讲师TTT培训》
A812: 810 | B812: 2月 | C812: =VLOOKUP(F812,[4]在职!$A:$E,5,0) -> 山东 | D812: =VLOOKUP(F812,[4]在职!$A:$G,7,0) -> 山东销售部 | E812: =VLOOKUP(F812,[4]在职!$A:$M,13,0) -> 李丹 | F812: 苏晓青 | G812: =VLOOKUP(F812,[4]在职!$A:$B,2,0) -> 00166 | H812: =VLOOKUP(F812,[4]在职!$A:$I,9,0) -> 二星正式经理 | I812: 已签到 | J812: 46077 | K812: 《讲师TTT培训》 | L812: 《讲师TTT培训》
A813: 811 | B813: 2月 | C813: =VLOOKUP(F813,[4]在职!$A:$E,5,0) -> 山东 | D813: =VLOOKUP(F813,[4]在职!$A:$G,7,0) -> 山东销售部 | E813: =VLOOKUP(F813,[4]在职!$A:$M,13,0) -> 李丹 | F813: 肖佳 | G813: =VLOOKUP(F813,[4]在职!$A:$B,2,0) -> 00521 | H813: =VLOOKUP(F813,[4]在职!$A:$I,9,0) -> 一星正式经理 | I813: 已签到 | J813: 46077 | K813: 《讲师TTT培训》 | L813: 《讲师TTT培训》
A814: 812 | B814: 2月 | C814: =VLOOKUP(F814,[4]在职!$A:$E,5,0) -> 山东 | D814: =VLOOKUP(F814,[4]在职!$A:$G,7,0) -> 山东销售部 | E814: =VLOOKUP(F814,[4]在职!$A:$M,13,0) -> 李丹 | F814: 苏晓青 | G814: =VLOOKUP(F814,[4]在职!$A:$B,2,0) -> 00166 | H814: =VLOOKUP(F814,[4]在职!$A:$I,9,0) -> 二星正式经理 | I814: 已签到 | J814: 46078 | K814: 《讲师TTT培训》 | L814: 《讲师TTT培训》
A815: 813 | B815: 2月 | C815: =VLOOKUP(F815,[4]在职!$A:$E,5,0) -> 山东 | D815: =VLOOKUP(F815,[4]在职!$A:$G,7,0) -> 山东销售部 | E815: =VLOOKUP(F815,[4]在职!$A:$M,13,0) -> 李丹 | F815: 肖佳 | G815: =VLOOKUP(F815,[4]在职!$A:$B,2,0) -> 00521 | H815: =VLOOKUP(F815,[4]在职!$A:$I,9,0) -> 一星正式经理 | I815: 已签到 | J815: 46078 | K815: 《讲师TTT培训》 | L815: 《讲师TTT培训》
A816: 814 | B816: 2月 | C816: =VLOOKUP(F816,[4]在职!$A:$E,5,0) -> 山西 | D816: 山西拓展部 | E816: =VLOOKUP(F816,[4]在职!$A:$M,13,0) -> 黄芳 | F816: 吴川江 | G816: =VLOOKUP(F816,[4]在职!$A:$B,2,0) -> 00695 | H816: =VLOOKUP(F816,[4]在职!$A:$I,9,0) -> 分公司总经理 | I816: 已签到 | J816: 46077 | K816: 《讲师TTT培训》 | L816: 《讲师TTT培训》
A817: 815 | B817: 2月 | C817: =VLOOKUP(F817,[4]在职!$A:$E,5,0) -> 山西 | D817: 山西拓展部 | E817: =VLOOKUP(F817,[4]在职!$A:$M,13,0) -> 黄芳 | F817: 吴川江 | G817: =VLOOKUP(F817,[4]在职!$A:$B,2,0) -> 00695 | H817: =VLOOKUP(F817,[4]在职!$A:$I,9,0) -> 分公司总经理 | I817: 已签到 | J817: 46078 | K817: 《讲师TTT培训》 | L817: 《讲师TTT培训》
A818: 816 | B818: 2月 | C818: =VLOOKUP(F818,[4]在职!$A:$E,5,0) -> 山西 | D818: =VLOOKUP(F818,[4]在职!$A:$G,7,0) -> 山西销售部 | E818: =VLOOKUP(F818,[4]在职!$A:$M,13,0) -> 吴川江 | F818: 吴志虎 | G818: =VLOOKUP(F818,[4]在职!$A:$B,2,0) -> 00160 | H818: =VLOOKUP(F818,[4]在职!$A:$I,9,0) -> 部长 | I818: 已签到 | J818: 46077 | K818: 《讲师TTT培训》 | L818: 《讲师TTT培训》
A819: 817 | B819: 2月 | C819: =VLOOKUP(F819,[4]在职!$A:$E,5,0) -> 山西 | D819: =VLOOKUP(F819,[4]在职!$A:$G,7,0) -> 0 | E819: =VLOOKUP(F819,[4]在职!$A:$M,13,0) -> 吴川江 | F819: 刘辉 | G819: =VLOOKUP(F819,[4]在职!$A:$B,2,0) -> 00015 | H819: =VLOOKUP(F819,[4]在职!$A:$I,9,0) -> 分公司副总经理 | I819: 已签到 | J819: 46077 | K819: 《讲师TTT培训》 | L819: 《讲师TTT培训》
A820: 818 | B820: 2月 | C820: =VLOOKUP(F820,[4]在职!$A:$E,5,0) -> 山西 | D820: =VLOOKUP(F820,[4]在职!$A:$G,7,0) -> 山西销售部 | E820: =VLOOKUP(F820,[4]在职!$A:$M,13,0) -> 吴川江 | F820: 吴志虎 | G820: =VLOOKUP(F820,[4]在职!$A:$B,2,0) -> 00160 | H820: =VLOOKUP(F820,[4]在职!$A:$I,9,0) -> 部长 | I820: 已签到 | J820: 46078 | K820: 《讲师TTT培训》 | L820: 《讲师TTT培训》
A821: 819 | B821: 2月 | C821: =VLOOKUP(F821,[4]在职!$A:$E,5,0) -> 山西 | D821: =VLOOKUP(F821,[4]在职!$A:$G,7,0) -> 0 | E821: =VLOOKUP(F821,[4]在职!$A:$M,13,0) -> 吴川江 | F821: 刘辉 | G821: =VLOOKUP(F821,[4]在职!$A:$B,2,0) -> 00015 | H821: =VLOOKUP(F821,[4]在职!$A:$I,9,0) -> 分公司副总经理 | I821: 已签到 | J821: 46078 | K821: 《讲师TTT培训》 | L821: 《讲师TTT培训》
A822: 820 | B822: 2月 | C822: =VLOOKUP(F822,[4]在职!$A:$E,5,0) -> 陕西 | D822: =VLOOKUP(F822,[4]在职!$A:$G,7,0) -> 陕西1部 | E822: =VLOOKUP(F822,[4]在职!$A:$M,13,0) -> 廖小朋 | F822: 李丝丝 | G822: =VLOOKUP(F822,[4]在职!$A:$B,2,0) -> 00090 | H822: =VLOOKUP(F822,[4]在职!$A:$I,9,0) -> 部长 | I822: 已签到 | J822: 46077 | K822: 《讲师TTT培训》 | L822: 《讲师TTT培训》
A823: 821 | B823: 2月 | C823: =VLOOKUP(F823,[4]在职!$A:$E,5,0) -> 陕西 | D823: =VLOOKUP(F823,[4]在职!$A:$G,7,0) -> 陕西1部 | E823: =VLOOKUP(F823,[4]在职!$A:$M,13,0) -> 廖小朋 | F823: 李丝丝 | G823: =VLOOKUP(F823,[4]在职!$A:$B,2,0) -> 00090 | H823: =VLOOKUP(F823,[4]在职!$A:$I,9,0) -> 部长 | I823: 已签到 | J823: 46078 | K823: 《讲师TTT培训》 | L823: 《讲师TTT培训》
A824: 822 | B824: 2月 | C824: =VLOOKUP(F824,[4]在职!$A:$E,5,0) -> 陕西 | D824: =VLOOKUP(F824,[4]在职!$A:$G,7,0) -> 陕西2部 | E824: =VLOOKUP(F824,[4]在职!$A:$M,13,0) -> 廖小朋 | F824: 李耀 | G824: =VLOOKUP(F824,[4]在职!$A:$B,2,0) -> 00077 | H824: =VLOOKUP(F824,[4]在职!$A:$I,9,0) -> 部长 | I824: 已签到 | J824: 46077 | K824: 《讲师TTT培训》 | L824: 《讲师TTT培训》
A825: 823 | B825: 2月 | C825: =VLOOKUP(F825,[4]在职!$A:$E,5,0) -> 陕西 | D825: =VLOOKUP(F825,[4]在职!$A:$G,7,0) -> 陕西2部 | E825: =VLOOKUP(F825,[4]在职!$A:$M,13,0) -> 廖小朋 | F825: 李耀 | G825: =VLOOKUP(F825,[4]在职!$A:$B,2,0) -> 00077 | H825: =VLOOKUP(F825,[4]在职!$A:$I,9,0) -> 部长 | I825: 已签到 | J825: 46078 | K825: 《讲师TTT培训》 | L825: 《讲师TTT培训》
A826: 824 | B826: 2月 | C826: =VLOOKUP(F826,[4]在职!$A:$E,5,0) -> 陕西 | D826: 陕西拓展部 | E826: =VLOOKUP(F826,[4]在职!$A:$M,13,0) -> 黄芳 | F826: 廖小朋 | G826: =VLOOKUP(F826,[4]在职!$A:$B,2,0) -> 00009 | H826: =VLOOKUP(F826,[4]在职!$A:$I,9,0) -> 分公司总经理 | I826: 已签到 | J826: 46077 | K826: 《讲师TTT培训》 | L826: 《讲师TTT培训》
A827: 825 | B827: 2月 | C827: =VLOOKUP(F827,[4]在职!$A:$E,5,0) -> 陕西 | D827: 陕西1部 | E827: =VLOOKUP(F827,[4]在职!$A:$M,13,0) -> 黄芳 | F827: 廖小朋 | G827: =VLOOKUP(F827,[4]在职!$A:$B,2,0) -> 00009 | H827: =VLOOKUP(F827,[4]在职!$A:$I,9,0) -> 分公司总经理 | I827: 已签到 | J827: 46078 | K827: 《讲师TTT培训》 | L827: 《讲师TTT培训》
A828: 826 | B828: 2月 | C828: =VLOOKUP(F828,[4]在职!$A:$E,5,0) -> 西南总部 | D828: 西南拓展中心 | E828: =VLOOKUP(F828,[4]在职!$A:$M,13,0) -> 刘文宇 | F828: 黄伟 | G828: =VLOOKUP(F828,[4]在职!$A:$B,2,0) -> 00043 | H828: =VLOOKUP(F828,[4]在职!$A:$I,9,0) -> 分公司总经理 | I828: 已签到 | J828: 46077 | K828: 《讲师TTT培训》 | L828: 《讲师TTT培训》
A829: 827 | B829: 2月 | C829: 河北 | D829: 河北拓展部 | E829: =VLOOKUP(F829,[4]在职!$A:$M,13,0) -> 刘文宇 | F829: 黄伟 | G829: =VLOOKUP(F829,[4]在职!$A:$B,2,0) -> 00043 | H829: =VLOOKUP(F829,[4]在职!$A:$I,9,0) -> 分公司总经理 | I829: 已签到 | J829: 46078 | K829: 《讲师TTT培训》 | L829: 《讲师TTT培训》
A830: 828 | B830: 2月 | C830: =VLOOKUP(F830,[4]在职!$A:$E,5,0) -> 湖南 | D830: =VLOOKUP(F830,[4]在职!$A:$G,7,0) -> 湖南销售部 | E830: =VLOOKUP(F830,[4]在职!$A:$M,13,0) -> 刘进 | F830: 孙小龙 | G830: =VLOOKUP(F830,[4]在职!$A:$B,2,0) -> 00288 | H830: =VLOOKUP(F830,[4]在职!$A:$I,9,0) -> 二星正式经理 | I830: 已签到 | J830: 46077 | K830: 《讲师TTT培训》 | L830: 《讲师TTT培训》
A831: 829 | B831: 2月 | C831: =VLOOKUP(F831,[4]在职!$A:$E,5,0) -> 西南总部 | D831: =VLOOKUP(F831,[4]在职!$A:$G,7,0) -> 营业二部 | E831: =VLOOKUP(F831,[4]在职!$A:$M,13,0) -> 柏刚 | F831: 魏飞翔 | G831: =VLOOKUP(F831,[4]在职!$A:$B,2,0) -> 00522 | H831: =VLOOKUP(F831,[4]在职!$A:$I,9,0) -> 一星正式经理 | I831: 已签到 | J831: 46077 | K831: 《讲师TTT培训》 | L831: 《讲师TTT培训》
A832: 830 | B832: 2月 | C832: =VLOOKUP(F832,[4]在职!$A:$E,5,0) -> 西南总部 | D832: =VLOOKUP(F832,[4]在职!$A:$G,7,0) -> 营业二部 | E832: =VLOOKUP(F832,[4]在职!$A:$M,13,0) -> 欧松林 | F832: 柏刚 | G832: =VLOOKUP(F832,[4]在职!$A:$B,2,0) -> 00060 | H832: =VLOOKUP(F832,[4]在职!$A:$I,9,0) -> 部长 | I832: 已签到 | J832: 46077 | K832: 《讲师TTT培训》 | L832: 《讲师TTT培训》
A833: 831 | B833: 2月 | C833: =VLOOKUP(F833,[4]在职!$A:$E,5,0) -> 湖南 | D833: =VLOOKUP(F833,[4]在职!$A:$G,7,0) -> 湖南销售部 | E833: =VLOOKUP(F833,[4]在职!$A:$M,13,0) -> 刘进 | F833: 孙小龙 | G833: =VLOOKUP(F833,[4]在职!$A:$B,2,0) -> 00288 | H833: =VLOOKUP(F833,[4]在职!$A:$I,9,0) -> 二星正式经理 | I833: 已签到 | J833: 46078 | K833: 《讲师TTT培训》 | L833: 《讲师TTT培训》
A834: 832 | B834: 2月 | C834: =VLOOKUP(F834,[4]在职!$A:$E,5,0) -> 西南总部 | D834: =VLOOKUP(F834,[4]在职!$A:$G,7,0) -> 营业二部 | E834: =VLOOKUP(F834,[4]在职!$A:$M,13,0) -> 柏刚 | F834: 魏飞翔 | G834: =VLOOKUP(F834,[4]在职!$A:$B,2,0) -> 00522 | H834: =VLOOKUP(F834,[4]在职!$A:$I,9,0) -> 一星正式经理 | I834: 已签到 | J834: 46078 | K834: 《讲师TTT培训》 | L834: 《讲师TTT培训》
A835: 833 | B835: 2月 | C835: =VLOOKUP(F835,[4]在职!$A:$E,5,0) -> 西南总部 | D835: =VLOOKUP(F835,[4]在职!$A:$G,7,0) -> 营业二部 | E835: =VLOOKUP(F835,[4]在职!$A:$M,13,0) -> 欧松林 | F835: 柏刚 | G835: =VLOOKUP(F835,[4]在职!$A:$B,2,0) -> 00060 | H835: =VLOOKUP(F835,[4]在职!$A:$I,9,0) -> 部长 | I835: 已签到 | J835: 46078 | K835: 《讲师TTT培训》 | L835: 《讲师TTT培训》
A836: 834 | B836: 2月 | C836: =VLOOKUP(F836,[4]在职!$A:$E,5,0) -> 西南总部 | D836: =VLOOKUP(F836,[4]在职!$A:$G,7,0) -> 营业六部 | E836: =VLOOKUP(F836,[4]在职!$A:$M,13,0) -> 欧松林 | F836: 毛富林 | G836: =VLOOKUP(F836,[4]在职!$A:$B,2,0) -> 00087 | H836: =VLOOKUP(F836,[4]在职!$A:$I,9,0) -> 部长 | I836: 已签到 | J836: 46077 | K836: 《讲师TTT培训》 | L836: 《讲师TTT培训》
A837: 835 | B837: 2月 | C837: =VLOOKUP(F837,[4]在职!$A:$E,5,0) -> 西南总部 | D837: =VLOOKUP(F837,[4]在职!$A:$G,7,0) -> 营业六部 | E837: =VLOOKUP(F837,[4]在职!$A:$M,13,0) -> 欧松林 | F837: 毛富林 | G837: =VLOOKUP(F837,[4]在职!$A:$B,2,0) -> 00087 | H837: =VLOOKUP(F837,[4]在职!$A:$I,9,0) -> 部长 | I837: 已签到 | J837: 46078 | K837: 《讲师TTT培训》 | L837: 《讲师TTT培训》
A838: 836 | B838: 2月 | C838: =VLOOKUP(F838,[4]在职!$A:$E,5,0) -> 西南总部 | D838: =VLOOKUP(F838,[4]在职!$A:$G,7,0) -> 营业七部 | E838: =VLOOKUP(F838,[4]在职!$A:$M,13,0) -> 欧松林 | F838: 程新浩 | G838: =VLOOKUP(F838,[4]在职!$A:$B,2,0) -> 00345 | H838: =VLOOKUP(F838,[4]在职!$A:$I,9,0) -> 部长 | I838: 已签到 | J838: 46077 | K838: 《讲师TTT培训》 | L838: 《讲师TTT培训》
A839: 837 | B839: 2月 | C839: =VLOOKUP(F839,[4]在职!$A:$E,5,0) -> 西南总部 | D839: =VLOOKUP(F839,[4]在职!$A:$G,7,0) -> 营业七部 | E839: =VLOOKUP(F839,[4]在职!$A:$M,13,0) -> 欧松林 | F839: 程新浩 | G839: =VLOOKUP(F839,[4]在职!$A:$B,2,0) -> 00345 | H839: =VLOOKUP(F839,[4]在职!$A:$I,9,0) -> 部长 | I839: 已签到 | J839: 46078 | K839: 《讲师TTT培训》 | L839: 《讲师TTT培训》
A840: 838 | B840: 2月 | C840: =VLOOKUP(F840,[4]在职!$A:$E,5,0) -> 西南总部 | D840: =VLOOKUP(F840,[4]在职!$A:$G,7,0) -> 营业三部 | E840: =VLOOKUP(F840,[4]在职!$A:$M,13,0) -> 周吉双 | F840: 肖秀丽 | G840: =VLOOKUP(F840,[4]在职!$A:$B,2,0) -> 00204 | H840: =VLOOKUP(F840,[4]在职!$A:$I,9,0) -> 二星正式经理 | I840: 已签到 | J840: 46077 | K840: 《讲师TTT培训》 | L840: 《讲师TTT培训》
A841: 839 | B841: 2月 | C841: =VLOOKUP(F841,[4]在职!$A:$E,5,0) -> 西南总部 | D841: =VLOOKUP(F841,[4]在职!$A:$G,7,0) -> 营业三部 | E841: =VLOOKUP(F841,[4]在职!$A:$M,13,0) -> 姚瑶 | F841: 刘盼 | G841: =VLOOKUP(F841,[4]在职!$A:$B,2,0) -> 00036 | H841: =VLOOKUP(F841,[4]在职!$A:$I,9,0) -> 督导 | I841: 已签到 | J841: 46077 | K841: 《讲师TTT培训》 | L841: 《讲师TTT培训》
... A851: 849 | B851: 2月 | C851: =VLOOKUP(F851,[4]在职!$A:$E,5,0) -> 西南总部 | D851: =VLOOKUP(F851,[4]在职!$A:$G,7,0) -> 营业一部 | E851: =VLOOKUP(F851,[4]在职!$A:$M,13,0) -> 欧松林 | F851: 雷小金 | G851: =VLOOKUP(F851,[4]在职!$A:$B,2,0) -> 00011 | H851: =VLOOKUP(F851,[4]在职!$A:$I,9,0) -> 部长 | I851: 已签到 | J851: 46078 | K851: 《讲师TTT培训》 | L851: 《讲师TTT培训》
A852: 850 | B852: 2月 | C852: =VLOOKUP(F852,[4]在职!$A:$E,5,0) -> 集团职能 | D852: =VLOOKUP(F852,[4]在职!$A:$G,7,0) -> 总经办 | E852: 黄芳 | F852: 黄芳 | G852: =VLOOKUP(F852,[4]在职!$A:$B,2,0) -> 00001 | H852: =VLOOKUP(F852,[4]在职!$A:$I,9,0) -> 总经理 | I852: 已签到 | J852: 46077 | K852: 《讲师TTT培训》 | L852: 《讲师TTT培训》
A853: 851 | B853: 2月 | C853: =VLOOKUP(F853,[4]在职!$A:$E,5,0) -> 集团职能 | D853: =VLOOKUP(F853,[4]在职!$A:$G,7,0) -> 人资行政部 | E853: =VLOOKUP(F853,[4]在职!$A:$M,13,0) -> 黄芳 | F853: 孔群慧 | G853: =VLOOKUP(F853,[4]在职!$A:$B,2,0) -> 01918 | H853: =VLOOKUP(F853,[4]在职!$A:$I,9,0) -> 人资行政经理 | I853: 已签到 | J853: 46077 | K853: 《讲师TTT培训》 | L853: 《讲师TTT培训》
A854: 852 | B854: 2月 | C854: =VLOOKUP(F854,[4]在职!$A:$E,5,0) -> 集团职能 | D854: 职能总部 | E854: =VLOOKUP(F854,[4]在职!$A:$M,13,0) -> 刘盼 | F854: 杨薇 | G854: =VLOOKUP(F854,[4]在职!$A:$B,2,0) -> 00456 | H854: =VLOOKUP(F854,[4]在职!$A:$I,9,0) -> 运营经理 | I854: 已签到 | J854: 46077 | K854: 《讲师TTT培训》 | L854: 《讲师TTT培训》
A855: 853 | B855: 2月 | C855: =VLOOKUP(F855,[4]在职!$A:$E,5,0) -> 集团职能 | D855: =VLOOKUP(F855,[4]在职!$A:$G,7,0) -> 技术部 | E855: =VLOOKUP(F855,[4]在职!$A:$M,13,0) -> 黄芳 | F855: 张亚东 | G855: =VLOOKUP(F855,[4]在职!$A:$B,2,0) -> 00120 | H855: =VLOOKUP(F855,[4]在职!$A:$I,9,0) -> 技术总监 | I855: 已签到 | J855: 46077 | K855: 《讲师TTT培训》 | L855: 《讲师TTT培训》
...

Sheet 《授课类型》维度的参训明细
A1: 《授课类型》维度的参训明细（1-3月）
A2: 序号 | B2: 月份 | C2: 城市 | D2: 营业部 | E2: 直系上级 | F2: 应参训人姓名 | G2: 工号 | H2: 职级 | I2: 签到情况 | J2: 培训时间 | K2: 授课类型
A3: 1 | B3: 1月 | C3: 西南总部 | D3: 营业五部 | E3: 安芮内蒙古 | F3: 蒋婷 | G3: 01011 | H3: 一星销售顾问 | I3: 未签到 | J3: 46035 | K3: 销售提升训
A4: 2 | B4: 1月 | C4: 西南总部 | D4: 营业五部 | E4: 安芮内蒙古 | F4: 孙智港 | G4: 01423 | H4: 一星销售顾问 | I4: 未签到 | J4: 46035 | K4: 销售提升训
A5: 3 | B5: 1月 | C5: 西南总部 | D5: 营业五部 | E5: 安芮内蒙古 | F5: 李裕楷 | G5: 01412 | H5: 一星销售顾问 | I5: 未签到 | J5: 46035 | K5: 销售提升训
A6: 4 | B6: 1月 | C6: 西南总部 | D6: 营业二部 | E6: 柏刚 | F6: 税小蓉 | G6: 01684 | H6: 一星销售顾问 | I6: 已签到 | J6: 46035 | K6: 销售提升训
A7: 5 | B7: 1月 | C7: 陕西 | D7: 陕西2部 | E7: 李丝丝 | F7: 李松 | G7: 01689 | H7: 一星销售顾问 | I7: 已签到 | J7: 46035 | K7: 销售提升训
A8: 6 | B8: 1月 | C8: 西南总部 | D8: 营业一部 | E8: 白世根 | F8: 先波 | G8: 01512 | H8: 二星销售顾问 | I8: 未签到 | J8: 46035 | K8: 销售提升训
A9: 7 | B9: 1月 | C9: 西南总部 | D9: 营业七部 | E9: 陈彪 | F9: 田丰 | G9: 01500 | H9: 一星销售顾问 | I9: 未签到 | J9: 46035 | K9: 销售提升训
A10: 8 | B10: 1月 | C10: 西南总部 | D10: 营业四部 | E10: 陈帅 | F10: 邓孝礼 | G10: 01621 | H10: 一星销售顾问 | I10: 已签到 | J10: 46035 | K10: 销售提升训
A11: 9 | B11: 1月 | C11: 湖北 | D11: 湖北1部 | E11: 张宗铭湖北 | F11: 黄建 | G11: 01657 | H11: 一星销售顾问 | I11: 未签到 | J11: 46035 | K11: 销售提升训
A12: 10 | B12: 1月 | C12: 西南总部 | D12: 营业四部 | E12: 陈嘉文 | F12: 向巡 | G12: 01634 | H12: 一星销售顾问 | I12: 未签到 | J12: 46035 | K12: 销售提升训
A13: 11 | B13: 1月 | C13: 西南总部 | D13: 营业四部 | E13: 陈嘉文 | F13: 陈帅2 | G13: 01488 | H13: 二星销售顾问 | I13: 未签到 | J13: 46035 | K13: 销售提升训
A14: 12 | B14: 1月 | C14: 陕西 | D14: 陕西2部 | E14: 冀敏 | F14: 涂正丽 | G14: 01654 | H14: 一星销售顾问 | I14: 未签到 | J14: 46035 | K14: 销售提升训
... A329: 327 | B329: 1月 | C329: 西南总部 | D329: 职能营销 | E329: 督导部 | F329: 易束梅 | G329: 01872 | H329: 售后 | I329: 已签到 | J329: 46051 | K329: 销售新人入职培训
A330: 328 | B330: 2月 | C330: =VLOOKUP(F330,[4]在职!$A:$E,5,0) -> 集团职能 | D330: 职能总部 | E330: 黄芳 | F330: 黄芳 | G330: =VLOOKUP(F330,[4]在职!$A:$B,2,0) -> 00001 | H330: =VLOOKUP(F330,[4]在职!$A:$I,9,0) -> 总经理 | I330: 已签到 | J330: 46077 | K330: 《讲师TTT培训》
A331: 329 | B331: 2月 | C331: 宁夏 | D331: 宁夏拓展中心 | E331: 刘文宇 | F331: 黄小东 | G331: =VLOOKUP(F331,[4]在职!$A:$B,2,0) -> 00215 | H331: =VLOOKUP(F331,[4]在职!$A:$I,9,0) -> 区域拓展总监 | I331: 已签到 | J331: 46077 | K331: 《讲师TTT培训》
A332: 330 | B332: 2月 | C332: =VLOOKUP(F332,[4]在职!$A:$E,5,0) -> 西南总部 | D332: 川北 | E332: 刘文宇 | F332: 蒋婉萍 | G332: =VLOOKUP(F332,[4]在职!$A:$B,2,0) -> 00745 | H332: =VLOOKUP(F332,[4]在职!$A:$I,9,0) -> 区域拓展总监 | I332: 已签到 | J332: 46077 | K332: 《讲师TTT培训》
A333: 331 | B333: 2月 | C333: =VLOOKUP(F333,[4]在职!$A:$E,5,0) -> 集团职能 | D333: 职能总部 | E333: 黄芳 | F333: 孔群慧 | G333: =VLOOKUP(F333,[4]在职!$A:$B,2,0) -> 01918 | H333: =VLOOKUP(F333,[4]在职!$A:$I,9,0) -> 人资行政经理 | I333: 已签到 | J333: 46077 | K333: 《讲师TTT培训》
A334: 332 | B334: 2月 | C334: =VLOOKUP(F334,[4]在职!$A:$E,5,0) -> 河北 | D334: 河北销售部 | E334: 张冀 | F334: 李港一 | G334: =VLOOKUP(F334,[4]在职!$A:$B,2,0) -> 00008 | H334: =VLOOKUP(F334,[4]在职!$A:$I,9,0) -> 分公司副总经理 | I334: 已签到 | J334: 46077 | K334: 《讲师TTT培训》
A335: 333 | B335: 2月 | C335: =VLOOKUP(F335,[4]在职!$A:$E,5,0) -> 陕西 | D335: 陕西2部 | E335: 廖小朋 | F335: 李耀 | G335: =VLOOKUP(F335,[4]在职!$A:$B,2,0) -> 00077 | H335: =VLOOKUP(F335,[4]在职!$A:$I,9,0) -> 部长 | I335: 已签到 | J335: 46077 | K335: 《讲师TTT培训》
A336: 334 | B336: 2月 | C336: =VLOOKUP(F336,[4]在职!$A:$E,5,0) -> 湖南 | D336: 湖南销售部 | E336: 王超飞 | F336: 刘进 | G336: =VLOOKUP(F336,[4]在职!$A:$B,2,0) -> 00050 | H336: =VLOOKUP(F336,[4]在职!$A:$I,9,0) -> 分公司副总经理 | I336: 已签到 | J336: 46077 | K336: 《讲师TTT培训》
A337: 335 | B337: 2月 | C337: =VLOOKUP(F337,[4]在职!$A:$E,5,0) -> 河南 | D337: 河南销售部 | E337: 毛孝树 | F337: 周吉双 | G337: =VLOOKUP(F337,[4]在职!$A:$B,2,0) -> 00270 | H337: =VLOOKUP(F337,[4]在职!$A:$I,9,0) -> 部长 | I337: 已签到 | J337: 46077 | K337: 《讲师TTT培训》
A338: 336 | B338: 2月 | C338: =VLOOKUP(F338,[4]在职!$A:$E,5,0) -> 河北 | D338: 河北销售部 | E338: 李港一 | F338: 韩旭 | G338: =VLOOKUP(F338,[4]在职!$A:$B,2,0) -> 00263 | H338: =VLOOKUP(F338,[4]在职!$A:$I,9,0) -> 一星正式经理 | I338: 已签到 | J338: 46077 | K338: 《讲师TTT培训》
A339: 337 | B339: 2月 | C339: =VLOOKUP(F339,[4]在职!$A:$E,5,0) -> 西南总部 | D339: 西南拓展中心 | E339: 刘文宇 | F339: 黄伟 | G339: =VLOOKUP(F339,[4]在职!$A:$B,2,0) -> 00043 | H339: =VLOOKUP(F339,[4]在职!$A:$I,9,0) -> 分公司总经理 | I339: 已签到 | J339: 46077 | K339: 《讲师TTT培训》
A340: 338 | B340: 2月 | C340: =VLOOKUP(F340,[4]在职!$A:$E,5,0) -> 辽宁 | D340: 辽宁销售部 | E340: 聂仕平 | F340: 赖慧 | G340: =VLOOKUP(F340,[4]在职!$A:$B,2,0) -> 00016 | H340: =VLOOKUP(F340,[4]在职!$A:$I,9,0) -> 分公司副总经理 | I340: 已签到 | J340: 46077 | K340: 《讲师TTT培训》
A341: 339 | B341: 2月 | C341: =VLOOKUP(F341,[4]在职!$A:$E,5,0) -> 甘肃 | D341: 甘肃拓展部 | E341: 黄芳 | F341: 雷鸣 | G341: =VLOOKUP(F341,[4]在职!$A:$B,2,0) -> 00248 | H341: =VLOOKUP(F341,[4]在职!$A:$I,9,0) -> 区域拓展总监 | I341: 已签到 | J341: 46077 | K341: 《讲师TTT培训》
A342: 340 | B342: 2月 | C342: =VLOOKUP(F342,[4]在职!$A:$E,5,0) -> 陕西 | D342: 陕西1部 | E342: 廖小朋 | F342: 李丝丝 | G342: =VLOOKUP(F342,[4]在职!$A:$B,2,0) -> 00090 | H342: =VLOOKUP(F342,[4]在职!$A:$I,9,0) -> 部长 | I342: 已签到 | J342: 46077 | K342: 《讲师TTT培训》
A343: 341 | B343: 2月 | C343: =VLOOKUP(F343,[4]在职!$A:$E,5,0) -> 陕西 | D343: 陕西拓展部 | E343: 黄芳 | F343: 廖小朋 | G343: =VLOOKUP(F343,[4]在职!$A:$B,2,0) -> 00009 | H343: =VLOOKUP(F343,[4]在职!$A:$I,9,0) -> 分公司总经理 | I343: 已签到 | J343: 46077 | K343: 《讲师TTT培训》
... A439: 437 | B439: 2月 | C439: =VLOOKUP(F439,[4]在职!$A:$E,5,0) -> 山东 | D439: 山东销售部 | E439: 李丹 | F439: 肖佳 | G439: =VLOOKUP(F439,[4]在职!$A:$B,2,0) -> 00521 | H439: =VLOOKUP(F439,[4]在职!$A:$I,9,0) -> 一星正式经理 | I439: 已签到 | J439: 46078 | K439: 《讲师TTT培训》
A440: 438 | B440: 3月 | C440: =VLOOKUP(F440,[4]在职!$A:$E,5,0) -> 湖北 | D440: =VLOOKUP(F440,[4]在职!$A:$G,7,0) -> 湖北2部 | E440: =VLOOKUP(F440,[4]在职!$A:$M,13,0) -> 陈晓辉 | F440: 陈亮 | G440: =VLOOKUP(F440,[4]在职!$A:$B,2,0) -> 01320 | H440: =VLOOKUP(F440,[4]在职!$A:$I,9,0) -> 三星销售顾问 | I440: 已签到 | J440: 46085 | K440: B岗培训
A441: 439 | B441: 3月 | C441: =VLOOKUP(F441,[4]在职!$A:$E,5,0) -> 西南总部 | D441: =VLOOKUP(F441,[4]在职!$A:$G,7,0) -> 营业四部 | E441: =VLOOKUP(F441,[4]在职!$A:$M,13,0) -> 刘亮 | F441: 罗宁2 | G441: =VLOOKUP(F441,[4]在职!$A:$B,2,0) -> 01105 | H441: =VLOOKUP(F441,[4]在职!$A:$I,9,0) -> B岗经理 | I441: 已签到 | J441: 46085 | K441: B岗培训
A442: 440 | B442: 3月 | C442: =VLOOKUP(F442,[4]在职!$A:$E,5,0) -> 陕西 | D442: =VLOOKUP(F442,[4]在职!$A:$G,7,0) -> 陕西1部 | E442: =VLOOKUP(F442,[4]在职!$A:$M,13,0) -> 杨永梅 | F442: 何飞 | G442: =VLOOKUP(F442,[4]在职!$A:$B,2,0) -> 01158 | H442: =VLOOKUP(F442,[4]在职!$A:$I,9,0) -> 三星销售顾问 | I442: 已签到 | J442: 46085 | K442: B岗培训
A443: 441 | B443: 3月 | C443: =VLOOKUP(F443,[4]在职!$A:$E,5,0) -> 西南总部 | D443: =VLOOKUP(F443,[4]在职!$A:$G,7,0) -> 营业五部 | E443: =VLOOKUP(F443,[4]在职!$A:$M,13,0) -> 杨科 | F443: 文尤洋 | G443: =VLOOKUP(F443,[4]在职!$A:$B,2,0) -> 01351 | H443: =VLOOKUP(F443,[4]在职!$A:$I,9,0) -> B岗经理 | I443: 已签到 | J443: 46085 | K443: B岗培训
A444: 442 | B444: 3月 | C444: =VLOOKUP(F444,[4]在职!$A:$E,5,0) -> 西南总部 | D444: =VLOOKUP(F444,[4]在职!$A:$G,7,0) -> 营业二部 | E444: =VLOOKUP(F444,[4]在职!$A:$M,13,0) -> 杨芊 | F444: 杨鹏 | G444: =VLOOKUP(F444,[4]在职!$A:$B,2,0) -> 00950 | H444: =VLOOKUP(F444,[4]在职!$A:$I,9,0) -> 三星销售顾问 | I444: 已签到 | J444: 46085 | K444: B岗培训
A445: 443 | B445: 3月 | C445: =VLOOKUP(F445,[4]在职!$A:$E,5,0) -> 陕西 | D445: =VLOOKUP(F445,[4]在职!$A:$G,7,0) -> 陕西2部 | E445: =VLOOKUP(F445,[4]在职!$A:$M,13,0) -> 王辉 | F445: 王锦涛 | G445: =VLOOKUP(F445,[4]在职!$A:$B,2,0) -> 00978 | H445: =VLOOKUP(F445,[4]在职!$A:$I,9,0) -> 三星销售顾问 | I445: 已签到 | J445: 46085 | K445: B岗培训
A446: 444 | B446: 3月 | C446: =VLOOKUP(F446,[4]在职!$A:$E,5,0) -> 河南 | D446: =VLOOKUP(F446,[4]在职!$A:$G,7,0) -> 河南销售部 | E446: =VLOOKUP(F446,[4]在职!$A:$M,13,0) -> 余金梅 | F446: 顾大局 | G446: =VLOOKUP(F446,[4]在职!$A:$B,2,0) -> 01421 | H446: =VLOOKUP(F446,[4]在职!$A:$I,9,0) -> 二星销售顾问 | I446: 已签到 | J446: 46085 | K446: B岗培训
A447: 445 | B447: 3月 | C447: =VLOOKUP(F447,[4]在职!$A:$E,5,0) -> 西南总部 | D447: =VLOOKUP(F447,[4]在职!$A:$G,7,0) -> 营业七部 | E447: =VLOOKUP(F447,[4]在职!$A:$M,13,0) -> 谢沁霜 | F447: 吴洪蝶 | G447: =VLOOKUP(F447,[4]在职!$A:$B,2,0) -> 00893 | H447: =VLOOKUP(F447,[4]在职!$A:$I,9,0) -> 三星销售顾问 | I447: 已签到 | J447: 46085 | K447: B岗培训
A448: 446 | B448: 3月 | C448: =VLOOKUP(F448,[4]在职!$A:$E,5,0) -> 陕西 | D448: =VLOOKUP(F448,[4]在职!$A:$G,7,0) -> 陕西2部 | E448: =VLOOKUP(F448,[4]在职!$A:$M,13,0) -> 李耀 | F448: 王超2 | G448: =VLOOKUP(F448,[4]在职!$A:$B,2,0) -> 00945 | H448: =VLOOKUP(F448,[4]在职!$A:$I,9,0) -> 三星销售顾问 | I448: 已签到 | J448: 46085 | K448: B岗培训
A449: 447 | B449: 3月 | C449: =VLOOKUP(F449,[4]在职!$A:$E,5,0) -> 西南总部 | D449: =VLOOKUP(F449,[4]在职!$A:$G,7,0) -> 营业七部 | E449: =VLOOKUP(F449,[4]在职!$A:$M,13,0) -> 蒋杨 | F449: 霍雪毅 | G449: =VLOOKUP(F449,[4]在职!$A:$B,2,0) -> 01374 | H449: =VLOOKUP(F449,[4]在职!$A:$I,9,0) -> B岗经理 | I449: 已签到 | J449: 46085 | K449: B岗培训
A450: 448 | B450: 3月 | C450: =VLOOKUP(F450,[4]在职!$A:$E,5,0) -> 西南总部 | D450: =VLOOKUP(F450,[4]在职!$A:$G,7,0) -> 营业二部 | E450: =VLOOKUP(F450,[4]在职!$A:$M,13,0) -> 魏飞翔 | F450: 刘军 | G450: =VLOOKUP(F450,[4]在职!$A:$B,2,0) -> 00856 | H450: =VLOOKUP(F450,[4]在职!$A:$I,9,0) -> B岗经理 | I450: 已签到 | J450: 46085 | K450: B岗培训
A451: 449 | B451: 3月 | C451: =VLOOKUP(F451,[4]在职!$A:$E,5,0) -> 河南 | D451: =VLOOKUP(F451,[4]在职!$A:$G,7,0) -> 河南销售部 | E451: =VLOOKUP(F451,[4]在职!$A:$M,13,0) -> 任枭月 | F451: 朱思刚 | G451: =VLOOKUP(F451,[4]在职!$A:$B,2,0) -> 00718 | H451: =VLOOKUP(F451,[4]在职!$A:$I,9,0) -> 二星销售顾问 | I451: 已签到 | J451: 46085 | K451: B岗培训
... A682: 720 | B682: 3月 | C682: =VLOOKUP(F682,[4]在职!$A:$E,5,0) -> 山东 | D682: =VLOOKUP(F682,[4]在职!$A:$G,7,0) -> 山东销售部 | E682: =VLOOKUP(F682,[4]在职!$A:$M,13,0) -> 肖佳 | F682: 张杰 | G682: =VLOOKUP(F682,[4]在职!$A:$B,2,0) -> 01956 | H682: =VLOOKUP(F682,[4]在职!$A:$I,9,0) -> 实习销售 | I682: 已签到 | J682: 46106 | K682: 销售新人入职培训
A683: 721 | B683: 3月 | C683: 集团职能 | D683: 人资行政部 | E683: 孔群慧 | F683: 何承莲 | G683: 02013 | H683: 人资行政部 | I683: 已签到 | J683: 46106 | K683: 销售新人入职培训
A684: 722 | B684: 3月 | C684: =VLOOKUP(F684,[4]在职!$A:$E,5,0) -> 集团职能 | D684: =VLOOKUP(F684,[4]在职!$A:$G,7,0) -> 人资行政部 | E684: =VLOOKUP(F684,[4]在职!$A:$M,13,0) -> 孔群慧 | F684: 孙敏 | G684: =VLOOKUP(F684,[4]在职!$A:$B,2,0) -> 01984 | H684: =VLOOKUP(F684,[4]在职!$A:$I,9,0) -> 人事专员 | I684: 已签到 | J684: 46106 | K684: 销售新人入职培训
A685: 723 | B685: 3月 | C685: =VLOOKUP(F685,[4]在职!$A:$E,5,0) -> 集团职能 | D685: =VLOOKUP(F685,[4]在职!$A:$G,7,0) -> 人资行政部 | E685: =VLOOKUP(F685,[4]在职!$A:$M,13,0) -> 孔群慧 | F685: 陈雪莲 | G685: =VLOOKUP(F685,[4]在职!$A:$B,2,0) -> 02001 | H685: =VLOOKUP(F685,[4]在职!$A:$I,9,0) -> 薪酬专员 | I685: 已签到 | J685: 46106 | K685: 销售新人入职培训
A686: 724 | B686: 3月 | C686: =VLOOKUP(F686,[4]在职!$A:$E,5,0) -> 河北 | D686: =VLOOKUP(F686,[4]在职!$A:$G,7,0) -> 河北销售部 | E686: =VLOOKUP(F686,[4]在职!$A:$M,13,0) -> 陈东2 | F686: 赵旭升 | G686: =VLOOKUP(F686,[4]在职!$A:$B,2,0) -> 01962 | H686: =VLOOKUP(F686,[4]在职!$A:$I,9,0) -> 实习销售 | I686: 未签到 | J686: 46106 | K686: 销售新人入职培训
A687: 725 | B687: 3月 | C687: =VLOOKUP(F687,[4]在职!$A:$E,5,0) -> 河北 | D687: =VLOOKUP(F687,[4]在职!$A:$G,7,0) -> 河北销售部 | E687: =VLOOKUP(F687,[4]在职!$A:$M,13,0) -> 陈东2 | F687: 王晓潮 | G687: =VLOOKUP(F687,[4]在职!$A:$B,2,0) -> 01902 | H687: =VLOOKUP(F687,[4]在职!$A:$I,9,0) -> 实习销售 | I687: 未签到 | J687: 46106 | K687: 销售新人入职培训
A688: 726 | B688: 3月 | C688: =VLOOKUP(F688,[4]在职!$A:$E,5,0) -> 西南总部 | D688: =VLOOKUP(F688,[4]在职!$A:$G,7,0) -> 营业四部 | E688: =VLOOKUP(F688,[4]在职!$A:$M,13,0) -> 贾萍 | F688: 石丹 | G688: =VLOOKUP(F688,[4]在职!$A:$B,2,0) -> 01922 | H688: =VLOOKUP(F688,[4]在职!$A:$I,9,0) -> 实习销售 | I688: 未签到 | J688: 46106 | K688: 销售新人入职培训
A689: 727 | B689: 3月 | C689: =VLOOKUP(F689,[4]在职!$A:$E,5,0) -> 湖南 | D689: =VLOOKUP(F689,[4]在职!$A:$G,7,0) -> 湖南销售部 | E689: =VLOOKUP(F689,[4]在职!$A:$M,13,0) -> 孙小龙 | F689: 王杰2 | G689: =VLOOKUP(F689,[4]在职!$A:$B,2,0) -> 01731 | H689: =VLOOKUP(F689,[4]在职!$A:$I,9,0) -> 一星销售顾问 | I689: 未签到 | J689: 46106 | K689: 销售新人入职培训
A690: 728 | B690: 3月 | C690: =VLOOKUP(F690,[4]在职!$A:$E,5,0) -> 西南总部 | D690: =VLOOKUP(F690,[4]在职!$A:$G,7,0) -> 营业七部 | E690: =VLOOKUP(F690,[4]在职!$A:$M,13,0) -> 蒋杨 | F690: 唐伟 | G690: =VLOOKUP(F690,[4]在职!$A:$B,2,0) -> 01933 | H690: =VLOOKUP(F690,[4]在职!$A:$I,9,0) -> 实习销售 | I690: 未签到 | J690: 46106 | K690: 销售新人入职培训
A691: 729 | B691: 3月 | C691: =VLOOKUP(F691,[4]在职!$A:$E,5,0) -> 西南总部 | D691: =VLOOKUP(F691,[4]在职!$A:$G,7,0) -> 营业四部 | E691: =VLOOKUP(F691,[4]在职!$A:$M,13,0) -> 陈帅 | F691: 徐泰 | G691: =VLOOKUP(F691,[4]在职!$A:$B,2,0) -> 01758 | H691: =VLOOKUP(F691,[4]在职!$A:$I,9,0) -> 实习销售 | I691: 未签到 | J691: 46106 | K691: 销售新人入职培训
A692: 730 | B692: 3月 | C692: =VLOOKUP(F692,[4]在职!$A:$E,5,0) -> 西南总部 | D692: =VLOOKUP(F692,[4]在职!$A:$G,7,0) -> 营业四部 | E692: =VLOOKUP(F692,[4]在职!$A:$M,13,0) -> 陈帅 | F692: 王成鑫 | G692: =VLOOKUP(F692,[4]在职!$A:$B,2,0) -> 01882 | H692: =VLOOKUP(F692,[4]在职!$A:$I,9,0) -> 实习销售 | I692: 未签到 | J692: 46106 | K692: 销售新人入职培训
A693: 731 | B693: 3月 | C693: =VLOOKUP(F693,[4]在职!$A:$E,5,0) -> 西南总部 | D693: =VLOOKUP(F693,[4]在职!$A:$G,7,0) -> 营业七部 | E693: =VLOOKUP(F693,[4]在职!$A:$M,13,0) -> 程新浩 | F693: 杨婷婷 | G693: =VLOOKUP(F693,[4]在职!$A:$B,2,0) -> 01945 | H693: =VLOOKUP(F693,[4]在职!$A:$I,9,0) -> 实习销售 | I693: 未签到 | J693: 46106 | K693: 销售新人入职培训
A694: 732 | B694: 3月 | C694: =VLOOKUP(F694,[4]在职!$A:$E,5,0) -> 西南总部 | D694: =VLOOKUP(F694,[4]在职!$A:$G,7,0) -> 营业七部 | E694: =VLOOKUP(F694,[4]在职!$A:$M,13,0) -> 程新浩 | F694: 何松键 | G694: =VLOOKUP(F694,[4]在职!$A:$B,2,0) -> 01916 | H694: =VLOOKUP(F694,[4]在职!$A:$I,9,0) -> 实习销售 | I694: 未签到 | J694: 46106 | K694: 销售新人入职培训
A695: 733 | B695: 3月 | C695: =VLOOKUP(F695,[4]在职!$A:$E,5,0) -> 西南总部 | D695: =VLOOKUP(F695,[4]在职!$A:$G,7,0) -> 营业七部 | E695: =VLOOKUP(F695,[4]在职!$A:$M,13,0) -> 申慧 | F695: 王强3 | G695: =VLOOKUP(F695,[4]在职!$A:$B,2,0) -> 01951 | H695: =VLOOKUP(F695,[4]在职!$A:$I,9,0) -> 实习销售 | I695: 未签到 | J695: 46106 | K695: 销售新人入职培训
... A721: 759 | B721: 3月 | C721: =VLOOKUP(F721,[4]在职!$A:$E,5,0) -> 西南总部 | D721: =VLOOKUP(F721,[4]在职!$A:$G,7,0) -> 营业五部 | E721: =VLOOKUP(F721,[4]在职!$A:$M,13,0) -> 张萍2 | F721: 王小蓬 | G721: =VLOOKUP(F721,[4]在职!$A:$B,2,0) -> 01898 | H721: =VLOOKUP(F721,[4]在职!$A:$I,9,0) -> 实习销售 | I721: 未签到 | J721: 46106 | K721: 销售新人入职培训

Sheet 各类培训类型参训率（人数为维度）
A1: 各类培训类型参训率（人数为维度）1-3月
A2: 月份 | B2: 城市 | C2: 营业部 | D2: 授课类型 | E2: 培训时间 | F2: 应参训人数 | G2: 实到人数 | H2: 参训率
A3: 1月 | B3: 西南总部 | C3: 职能营销 | D3: 销售新人入职培训 | E3: 46051 | F3: =COUNTIFS([1]《授课类型》维度的参训明细!B:B,A3,[1]《授课类型》维度的参训明细!C:C,B3,[1]《授课类型》维度的参训明细!D:D,C3,[1]《授课类型》维度的参训明细!K:K,D3) -> 6 | G3: =COUNTIFS([1]《授课类型》维度的参训明细!B:B,A3,[1]《授课类型》维度的参训明细!C:C,B3,[1]《授课类型》维度的参训明细!D:D,C3,[1]《授课类型》维度的参训明细!K:K,D3,[1]《授课类型》维度的参训明细!I:I,"已签到") -> 5 | H3: =G3/F3 -> 0.83333333
A4: 1月 | B4: 湖南 | C4: 湖南销售部 | D4: 销售新人入职培训 | E4: 46051 | F4: =COUNTIFS([1]《授课类型》维度的参训明细!B:B,A4,[1]《授课类型》维度的参训明细!C:C,B4,[1]《授课类型》维度的参训明细!D:D,C4,[1]《授课类型》维度的参训明细!K:K,D4) -> 6 | G4: =COUNTIFS([1]《授课类型》维度的参训明细!B:B,A4,[1]《授课类型》维度的参训明细!C:C,B4,[1]《授课类型》维度的参训明细!D:D,C4,[1]《授课类型》维度的参训明细!K:K,D4,[1]《授课类型》维度的参训明细!I:I,"已签到") -> 3 | H4: =G4/F4 -> 0.5
A5: 1月 | B5: 陕西 | C5: 陕西2部 | D5: 销售新人入职培训 | E5: 46051 | F5: =COUNTIFS([1]《授课类型》维度的参训明细!B:B,A5,[1]《授课类型》维度的参训明细!C:C,B5,[1]《授课类型》维度的参训明细!D:D,C5,[1]《授课类型》维度的参训明细!K:K,D5) -> 4 | G5: =COUNTIFS([1]《授课类型》维度的参训明细!B:B,A5,[1]《授课类型》维度的参训明细!C:C,B5,[1]《授课类型》维度的参训明细!D:D,C5,[1]《授课类型》维度的参训明细!K:K,D5,[1]《授课类型》维度的参训明细!I:I,"已签到") -> 4 | H5: =G5/F5 -> 1
A6: 1月 | B6: 西南总部 | C6: 营业一部 | D6: 销售新人入职培训 | E6: 46051 | F6: =COUNTIFS([1]《授课类型》维度的参训明细!B:B,A6,[1]《授课类型》维度的参训明细!C:C,B6,[1]《授课类型》维度的参训明细!D:D,C6,[1]《授课类型》维度的参训明细!K:K,D6) -> 7 | G6: =COUNTIFS([1]《授课类型》维度的参训明细!B:B,A6,[1]《授课类型》维度的参训明细!C:C,B6,[1]《授课类型》维度的参训明细!D:D,C6,[1]《授课类型》维度的参训明细!K:K,D6,[1]《授课类型》维度的参训明细!I:I,"已签到") -> 4 | H6: =G6/F6 -> 0.57142857
A7: 1月 | B7: 西南总部 | C7: 营业七部 | D7: 销售新人入职培训 | E7: 46051 | F7: =COUNTIFS([1]《授课类型》维度的参训明细!B:B,A7,[1]《授课类型》维度的参训明细!C:C,B7,[1]《授课类型》维度的参训明细!D:D,C7,[1]《授课类型》维度的参训明细!K:K,D7) -> 7 | G7: =COUNTIFS([1]《授课类型》维度的参训明细!B:B,A7,[1]《授课类型》维度的参训明细!C:C,B7,[1]《授课类型》维度的参训明细!D:D,C7,[1]《授课类型》维度的参训明细!K:K,D7,[1]《授课类型》维度的参训明细!I:I,"已签到") -> 3 | H7: =G7/F7 -> 0.42857143
A8: 1月 | B8: 西南总部 | C8: 营业二部 | D8: 销售新人入职培训 | E8: 46051 | F8: =COUNTIFS([1]《授课类型》维度的参训明细!B:B,A8,[1]《授课类型》维度的参训明细!C:C,B8,[1]《授课类型》维度的参训明细!D:D,C8,[1]《授课类型》维度的参训明细!K:K,D8) -> 6 | G8: =COUNTIFS([1]《授课类型》维度的参训明细!B:B,A8,[1]《授课类型》维度的参训明细!C:C,B8,[1]《授课类型》维度的参训明细!D:D,C8,[1]《授课类型》维度的参训明细!K:K,D8,[1]《授课类型》维度的参训明细!I:I,"已签到") -> 2 | H8: =G8/F8 -> 0.33333333
A9: 1月 | B9: 河南 | C9: 河南销售部 | D9: 销售新人入职培训 | E9: 46051 | F9: =COUNTIFS([1]《授课类型》维度的参训明细!B:B,A9,[1]《授课类型》维度的参训明细!C:C,B9,[1]《授课类型》维度的参训明细!D:D,C9,[1]《授课类型》维度的参训明细!K:K,D9) -> 6 | G9: =COUNTIFS([1]《授课类型》维度的参训明细!B:B,A9,[1]《授课类型》维度的参训明细!C:C,B9,[1]《授课类型》维度的参训明细!D:D,C9,[1]《授课类型》维度的参训明细!K:K,D9,[1]《授课类型》维度的参训明细!I:I,"已签到") -> 5 | H9: =G9/F9 -> 0.83333333
A10: 1月 | B10: 西南总部 | C10: 营业三部 | D10: 销售新人入职培训 | E10: 46051 | F10: =COUNTIFS([1]《授课类型》维度的参训明细!B:B,A10,[1]《授课类型》维度的参训明细!C:C,B10,[1]《授课类型》维度的参训明细!D:D,C10,[1]《授课类型》维度的参训明细!K:K,D10) -> 7 | G10: =COUNTIFS([1]《授课类型》维度的参训明细!B:B,A10,[1]《授课类型》维度的参训明细!C:C,B10,[1]《授课类型》维度的参训明细!D:D,C10,[1]《授课类型》维度的参训明细!K:K,D10,[1]《授课类型》维度的参训明细!I:I,"已签到") -> 2 | H10: =G10/F10 -> 0.28571429
A11: 1月 | B11: 西南总部 | C11: 营业四部 | D11: 销售新人入职培训 | E11: 46051 | F11: =COUNTIFS([1]《授课类型》维度的参训明细!B:B,A11,[1]《授课类型》维度的参训明细!C:C,B11,[1]《授课类型》维度的参训明细!D:D,C11,[1]《授课类型》维度的参训明细!K:K,D11) -> 5 | G11: =COUNTIFS([1]《授课类型》维度的参训明细!B:B,A11,[1]《授课类型》维度的参训明细!C:C,B11,[1]《授课类型》维度的参训明细!D:D,C11,[1]《授课类型》维度的参训明细!K:K,D11,[1]《授课类型》维度的参训明细!I:I,"已签到") -> 1 | H11: =G11/F11 -> 0.2
A12: 1月 | B12: 湖北 | C12: 湖北2部 | D12: 销售新人入职培训 | E12: 46051 | F12: =COUNTIFS([1]《授课类型》维度的参训明细!B:B,A12,[1]《授课类型》维度的参训明细!C:C,B12,[1]《授课类型》维度的参训明细!D:D,C12,[1]《授课类型》维度的参训明细!K:K,D12) -> 1 | G12: =COUNTIFS([1]《授课类型》维度的参训明细!B:B,A12,[1]《授课类型》维度的参训明细!C:C,B12,[1]《授课类型》维度的参训明细!D:D,C12,[1]《授课类型》维度的参训明细!K:K,D12,[1]《授课类型》维度的参训明细!I:I,"已签到") -> 1 | H12: =G12/F12 -> 1
A13: 1月 | B13: 甘肃 | C13: 甘肃销售部 | D13: 销售新人入职培训 | E13: 46051 | F13: =COUNTIFS([1]《授课类型》维度的参训明细!B:B,A13,[1]《授课类型》维度的参训明细!C:C,B13,[1]《授课类型》维度的参训明细!D:D,C13,[1]《授课类型》维度的参训明细!K:K,D13) -> 1 | G13: =COUNTIFS([1]《授课类型》维度的参训明细!B:B,A13,[1]《授课类型》维度的参训明细!C:C,B13,[1]《授课类型》维度的参训明细!D:D,C13,[1]《授课类型》维度的参训明细!K:K,D13,[1]《授课类型》维度的参训明细!I:I,"已签到") -> 1 | H13: =G13/F13 -> 1
A14: 1月 | B14: 山东 | C14: 山东销售部 | D14: 销售新人入职培训 | E14: 46051 | F14: =COUNTIFS([1]《授课类型》维度的参训明细!B:B,A14,[1]《授课类型》维度的参训明细!C:C,B14,[1]《授课类型》维度的参训明细!D:D,C14,[1]《授课类型》维度的参训明细!K:K,D14) -> 2 | G14: =COUNTIFS([1]《授课类型》维度的参训明细!B:B,A14,[1]《授课类型》维度的参训明细!C:C,B14,[1]《授课类型》维度的参训明细!D:D,C14,[1]《授课类型》维度的参训明细!K:K,D14,[1]《授课类型》维度的参训明细!I:I,"已签到") -> 2 | H14: =G14/F14 -> 1
... A36: 1月 | B36: 河北 | C36: 河北销售部 | D36: 销售经理培训 | E36: 46043 | F36: =COUNTIFS([1]《授课类型》维度的参训明细!B:B,A36,[1]《授课类型》维度的参训明细!C:C,B36,[1]《授课类型》维度的参训明细!D:D,C36,[1]《授课类型》维度的参训明细!K:K,D36) -> 2 | G36: =COUNTIFS([1]《授课类型》维度的参训明细!B:B,A36,[1]《授课类型》维度的参训明细!C:C,B36,[1]《授课类型》维度的参训明细!D:D,C36,[1]《授课类型》维度的参训明细!K:K,D36,[1]《授课类型》维度的参训明细!I:I,"已签到") -> 2 | H36: =G36/F36 -> 1
A37: 1月 | B37: 山西 | C37: 山西销售部 | D37: B岗培训 | E37: 46031 | F37: =COUNTIFS([1]《授课类型》维度的参训明细!B:B,A37,[1]《授课类型》维度的参训明细!C:C,B37,[1]《授课类型》维度的参训明细!D:D,C37,[1]《授课类型》维度的参训明细!K:K,D37,[1]《授课类型》维度的参训明细!J:J,E37) -> 1 | G37: =COUNTIFS([1]《授课类型》维度的参训明细!B:B,A37,[1]《授课类型》维度的参训明细!C:C,B37,[1]《授课类型》维度的参训明细!D:D,C37,[1]《授课类型》维度的参训明细!K:K,D37,[1]《授课类型》维度的参训明细!J:J,E37,[1]《授课类型》维度的参训明细!I:I,"已签到") -> 1 | H37: =G37/F37 -> 1
A38: 1月 | B38: 西南总部 | C38: 营业三部 | D38: B岗培训 | E38: 46031 | F38: =COUNTIFS([1]《授课类型》维度的参训明细!B:B,A38,[1]《授课类型》维度的参训明细!C:C,B38,[1]《授课类型》维度的参训明细!D:D,C38,[1]《授课类型》维度的参训明细!K:K,D38,[1]《授课类型》维度的参训明细!J:J,E38) -> 3 | G38: =COUNTIFS([1]《授课类型》维度的参训明细!B:B,A38,[1]《授课类型》维度的参训明细!C:C,B38,[1]《授课类型》维度的参训明细!D:D,C38,[1]《授课类型》维度的参训明细!K:K,D38,[1]《授课类型》维度的参训明细!J:J,E38,[1]《授课类型》维度的参训明细!I:I,"已签到") -> 3 | H38: =G38/F38 -> 1
A39: 1月 | B39: 山东 | C39: 山东销售部 | D39: B岗培训 | E39: 46031 | F39: =COUNTIFS([1]《授课类型》维度的参训明细!B:B,A39,[1]《授课类型》维度的参训明细!C:C,B39,[1]《授课类型》维度的参训明细!D:D,C39,[1]《授课类型》维度的参训明细!K:K,D39,[1]《授课类型》维度的参训明细!J:J,E39) -> 3 | G39: =COUNTIFS([1]《授课类型》维度的参训明细!B:B,A39,[1]《授课类型》维度的参训明细!C:C,B39,[1]《授课类型》维度的参训明细!D:D,C39,[1]《授课类型》维度的参训明细!K:K,D39,[1]《授课类型》维度的参训明细!J:J,E39,[1]《授课类型》维度的参训明细!I:I,"已签到") -> 3 | H39: =G39/F39 -> 1
A40: 1月 | B40: 湖南 | C40: 湖南销售部 | D40: B岗培训 | E40: 46031 | F40: =COUNTIFS([1]《授课类型》维度的参训明细!B:B,A40,[1]《授课类型》维度的参训明细!C:C,B40,[1]《授课类型》维度的参训明细!D:D,C40,[1]《授课类型》维度的参训明细!K:K,D40,[1]《授课类型》维度的参训明细!J:J,E40) -> 3 | G40: =COUNTIFS([1]《授课类型》维度的参训明细!B:B,A40,[1]《授课类型》维度的参训明细!C:C,B40,[1]《授课类型》维度的参训明细!D:D,C40,[1]《授课类型》维度的参训明细!K:K,D40,[1]《授课类型》维度的参训明细!J:J,E40,[1]《授课类型》维度的参训明细!I:I,"已签到") -> 3 | H40: =G40/F40 -> 1
A41: 1月 | B41: 西南总部 | C41: 营业一部 | D41: B岗培训 | E41: 46031 | F41: =COUNTIFS([1]《授课类型》维度的参训明细!B:B,A41,[1]《授课类型》维度的参训明细!C:C,B41,[1]《授课类型》维度的参训明细!D:D,C41,[1]《授课类型》维度的参训明细!K:K,D41,[1]《授课类型》维度的参训明细!J:J,E41) -> 1 | G41: =COUNTIFS([1]《授课类型》维度的参训明细!B:B,A41,[1]《授课类型》维度的参训明细!C:C,B41,[1]《授课类型》维度的参训明细!D:D,C41,[1]《授课类型》维度的参训明细!K:K,D41,[1]《授课类型》维度的参训明细!J:J,E41,[1]《授课类型》维度的参训明细!I:I,"已签到") -> 1 | H41: =G41/F41 -> 1
A42: 1月 | B42: 西南总部 | C42: 营业六部 | D42: B岗培训 | E42: 46031 | F42: =COUNTIFS([1]《授课类型》维度的参训明细!B:B,A42,[1]《授课类型》维度的参训明细!C:C,B42,[1]《授课类型》维度的参训明细!D:D,C42,[1]《授课类型》维度的参训明细!K:K,D42,[1]《授课类型》维度的参训明细!J:J,E42) -> 1 | G42: =COUNTIFS([1]《授课类型》维度的参训明细!B:B,A42,[1]《授课类型》维度的参训明细!C:C,B42,[1]《授课类型》维度的参训明细!D:D,C42,[1]《授课类型》维度的参训明细!K:K,D42,[1]《授课类型》维度的参训明细!J:J,E42,[1]《授课类型》维度的参训明细!I:I,"已签到") -> 1 | H42: =G42/F42 -> 1
A43: 1月 | B43: 西南总部 | C43: 营业五部 | D43: B岗培训 | E43: 46031 | F43: =COUNTIFS([1]《授课类型》维度的参训明细!B:B,A43,[1]《授课类型》维度的参训明细!C:C,B43,[1]《授课类型》维度的参训明细!D:D,C43,[1]《授课类型》维度的参训明细!K:K,D43,[1]《授课类型》维度的参训明细!J:J,E43) -> 3 | G43: =COUNTIFS([1]《授课类型》维度的参训明细!B:B,A43,[1]《授课类型》维度的参训明细!C:C,B43,[1]《授课类型》维度的参训明细!D:D,C43,[1]《授课类型》维度的参训明细!K:K,D43,[1]《授课类型》维度的参训明细!J:J,E43,[1]《授课类型》维度的参训明细!I:I,"已签到") -> 3 | H43: =G43/F43 -> 1
A44: 1月 | B44: 湖北 | C44: 湖北1部 | D44: B岗培训 | E44: 46031 | F44: =COUNTIFS([1]《授课类型》维度的参训明细!B:B,A44,[1]《授课类型》维度的参训明细!C:C,B44,[1]《授课类型》维度的参训明细!D:D,C44,[1]《授课类型》维度的参训明细!K:K,D44,[1]《授课类型》维度的参训明细!J:J,E44) -> 2 | G44: =COUNTIFS([1]《授课类型》维度的参训明细!B:B,A44,[1]《授课类型》维度的参训明细!C:C,B44,[1]《授课类型》维度的参训明细!D:D,C44,[1]《授课类型》维度的参训明细!K:K,D44,[1]《授课类型》维度的参训明细!J:J,E44,[1]《授课类型》维度的参训明细!I:I,"已签到") -> 2 | H44: =G44/F44 -> 1
A45: 1月 | B45: 陕西 | C45: 陕西2部 | D45: B岗培训 | E45: 46031 | F45: =COUNTIFS([1]《授课类型》维度的参训明细!B:B,A45,[1]《授课类型》维度的参训明细!C:C,B45,[1]《授课类型》维度的参训明细!D:D,C45,[1]《授课类型》维度的参训明细!K:K,D45,[1]《授课类型》维度的参训明细!J:J,E45) -> 3 | G45: =COUNTIFS([1]《授课类型》维度的参训明细!B:B,A45,[1]《授课类型》维度的参训明细!C:C,B45,[1]《授课类型》维度的参训明细!D:D,C45,[1]《授课类型》维度的参训明细!K:K,D45,[1]《授课类型》维度的参训明细!J:J,E45,[1]《授课类型》维度的参训明细!I:I,"已签到") -> 3 | H45: =G45/F45 -> 1
A46: 1月 | B46: 山东 | C46: 山东销售部 | D46: B岗培训 | E46: 46037 | F46: =COUNTIFS([1]《授课类型》维度的参训明细!B:B,A46,[1]《授课类型》维度的参训明细!C:C,B46,[1]《授课类型》维度的参训明细!D:D,C46,[1]《授课类型》维度的参训明细!K:K,D46,[1]《授课类型》维度的参训明细!J:J,E46) -> 3 | G46: =COUNTIFS([1]《授课类型》维度的参训明细!B:B,A46,[1]《授课类型》维度的参训明细!C:C,B46,[1]《授课类型》维度的参训明细!D:D,C46,[1]《授课类型》维度的参训明细!K:K,D46,[1]《授课类型》维度的参训明细!J:J,E46,[1]《授课类型》维度的参训明细!I:I,"已签到") -> 3 | H46: =G46/F46 -> 1
A47: 1月 | B47: 西南总部 | C47: 营业六部 | D47: B岗培训 | E47: 46037 | F47: =COUNTIFS([1]《授课类型》维度的参训明细!B:B,A47,[1]《授课类型》维度的参训明细!C:C,B47,[1]《授课类型》维度的参训明细!D:D,C47,[1]《授课类型》维度的参训明细!K:K,D47,[1]《授课类型》维度的参训明细!J:J,E47) -> 1 | G47: =COUNTIFS([1]《授课类型》维度的参训明细!B:B,A47,[1]《授课类型》维度的参训明细!C:C,B47,[1]《授课类型》维度的参训明细!D:D,C47,[1]《授课类型》维度的参训明细!K:K,D47,[1]《授课类型》维度的参训明细!J:J,E47,[1]《授课类型》维度的参训明细!I:I,"已签到") -> 1 | H47: =G47/F47 -> 1
A48: 1月 | B48: 西南总部 | C48: 营业一部 | D48: B岗培训 | E48: 46037 | F48: =COUNTIFS([1]《授课类型》维度的参训明细!B:B,A48,[1]《授课类型》维度的参训明细!C:C,B48,[1]《授课类型》维度的参训明细!D:D,C48,[1]《授课类型》维度的参训明细!K:K,D48,[1]《授课类型》维度的参训明细!J:J,E48) -> 1 | G48: =COUNTIFS([1]《授课类型》维度的参训明细!B:B,A48,[1]《授课类型》维度的参训明细!C:C,B48,[1]《授课类型》维度的参训明细!D:D,C48,[1]《授课类型》维度的参训明细!K:K,D48,[1]《授课类型》维度的参训明细!J:J,E48,[1]《授课类型》维度的参训明细!I:I,"已签到") -> 1 | H48: =G48/F48 -> 1
... A115: 1月 | B115: 辽宁 | C115: 辽宁销售部 | D115: 销售提升训 | E115: 46035 | F115: =COUNTIFS([1]《授课类型》维度的参训明细!B:B,A115,[1]《授课类型》维度的参训明细!C:C,B115,[1]《授课类型》维度的参训明细!D:D,C115,[1]《授课类型》维度的参训明细!K:K,D115,[1]《授课类型》维度的参训明细!J:J,E115) -> 1 | G115: =COUNTIFS([1]《授课类型》维度的参训明细!B:B,A115,[1]《授课类型》维度的参训明细!C:C,B115,[1]《授课类型》维度的参训明细!D:D,C115,[1]《授课类型》维度的参训明细!K:K,D115,[1]《授课类型》维度的参训明细!J:J,E115,[1]《授课类型》维度的参训明细!I:I,"已签到") -> 1 | H115: =G115/F115 -> 1
A116: 2月 | B116: 西南总部 | C116: 职能营销 | D116: 《讲师TTT培训》 | E116: 46077 | F116: =COUNTIFS('2026年度培训主表'!N:N,C116,'2026年度培训主表'!E:E,D116)/2 -> 10 | G116: =COUNTIFS('2026年度培训主表'!N:N,C116,'2026年度培训主表'!E:E,D116,'2026年度培训主表'!L:L,"已签到")/2 -> 10 | H116: =G116/F116 -> 1
A117: 2月 | B117: 宁夏 | C117: 宁夏拓展中心 | D117: 《讲师TTT培训》 | E117: 46077 | F117: =COUNTIFS('2026年度培训主表'!N:N,C117,'2026年度培训主表'!E:E,D117)/2 -> 1 | G117: =COUNTIFS('2026年度培训主表'!N:N,C117,'2026年度培训主表'!E:E,D117,'2026年度培训主表'!L:L,"已签到")/2 -> 1 | H117: =G117/F117 -> 1
A118: 2月 | B118: 西南总部 | C118: 川北 | D118: 《讲师TTT培训》 | E118: 46077 | F118: =COUNTIFS('2026年度培训主表'!N:N,C118,'2026年度培训主表'!E:E,D118)/2 -> 1 | G118: =COUNTIFS('2026年度培训主表'!N:N,C118,'2026年度培训主表'!E:E,D118,'2026年度培训主表'!L:L,"已签到")/2 -> 1 | H118: =G118/F118 -> 1
A119: 2月 | B119: 河北 | C119: 河北销售部 | D119: 《讲师TTT培训》 | E119: 46077 | F119: =COUNTIFS('2026年度培训主表'!N:N,C119,'2026年度培训主表'!E:E,D119)/2 -> 1 | G119: =COUNTIFS('2026年度培训主表'!N:N,C119,'2026年度培训主表'!E:E,D119,'2026年度培训主表'!L:L,"已签到")/2 -> 1 | H119: =G119/F119 -> 1
A120: 2月 | B120: 陕西 | C120: 陕西2部 | D120: 《讲师TTT培训》 | E120: 46077 | F120: =COUNTIFS('2026年度培训主表'!N:N,C120,'2026年度培训主表'!E:E,D120)/2 -> 1 | G120: =COUNTIFS('2026年度培训主表'!N:N,C120,'2026年度培训主表'!E:E,D120,'2026年度培训主表'!L:L,"已签到")/2 -> 1 | H120: =G120/F120 -> 1
A121: 2月 | B121: 湖南 | C121: 湖南销售部 | D121: 《讲师TTT培训》 | E121: 46077 | F121: =COUNTIFS('2026年度培训主表'!N:N,C121,'2026年度培训主表'!E:E,D121)/2 -> 3 | G121: =COUNTIFS('2026年度培训主表'!N:N,C121,'2026年度培训主表'!E:E,D121,'2026年度培训主表'!L:L,"已签到")/2 -> 3 | H121: =G121/F121 -> 1
A122: 2月 | B122: 河南 | C122: 河南销售部 | D122: 《讲师TTT培训》 | E122: 46077 | F122: =COUNTIFS('2026年度培训主表'!N:N,C122,'2026年度培训主表'!E:E,D122)/2 -> 1 | G122: =COUNTIFS('2026年度培训主表'!N:N,C122,'2026年度培训主表'!E:E,D122,'2026年度培训主表'!L:L,"已签到")/2 -> 1 | H122: =G122/F122 -> 1
A123: 2月 | B123: 辽宁 | C123: 辽宁销售部 | D123: 《讲师TTT培训》 | E123: 46077 | F123: =COUNTIFS('2026年度培训主表'!N:N,C123,'2026年度培训主表'!E:E,D123)/2 -> 0 | G123: =COUNTIFS('2026年度培训主表'!N:N,C123,'2026年度培训主表'!E:E,D123,'2026年度培训主表'!L:L,"已签到")/2 -> 0 | H123: =G123/F123 -> #DIV/0!
A124: 2月 | B124: 甘肃 | C124: 甘肃拓展部 | D124: 《讲师TTT培训》 | E124: 46077 | F124: =COUNTIFS('2026年度培训主表'!N:N,C124,'2026年度培训主表'!E:E,D124)/2 -> 1 | G124: =COUNTIFS('2026年度培训主表'!N:N,C124,'2026年度培训主表'!E:E,D124,'2026年度培训主表'!L:L,"已签到")/2 -> 1 | H124: =G124/F124 -> 1
A125: 2月 | B125: 陕西 | C125: 陕西1部 | D125: 《讲师TTT培训》 | E125: 46077 | F125: =COUNTIFS('2026年度培训主表'!N:N,C125,'2026年度培训主表'!E:E,D125)/2 -> 2 | G125: =COUNTIFS('2026年度培训主表'!N:N,C125,'2026年度培训主表'!E:E,D125,'2026年度培训主表'!L:L,"已签到")/2 -> 2 | H125: =G125/F125 -> 1
A126: 2月 | B126: 西南总部 | C126: 川东 | D126: 《讲师TTT培训》 | E126: 46077 | F126: =COUNTIFS('2026年度培训主表'!N:N,C126,'2026年度培训主表'!E:E,D126)/2 -> 2 | G126: =COUNTIFS('2026年度培训主表'!N:N,C126,'2026年度培训主表'!E:E,D126,'2026年度培训主表'!L:L,"已签到")/2 -> 2 | H126: =G126/F126 -> 1
A127: 2月 | B127: 西南总部 | C127: 营业三部 | D127: 《讲师TTT培训》 | E127: 46077 | F127: =COUNTIFS('2026年度培训主表'!N:N,C127,'2026年度培训主表'!E:E,D127)/2 -> 2 | G127: =COUNTIFS('2026年度培训主表'!N:N,C127,'2026年度培训主表'!E:E,D127,'2026年度培训主表'!L:L,"已签到")/2 -> 2 | H127: =G127/F127 -> 1
... A146: 2月 | B146: 辽宁 | C146: 辽宁拓展部 | D146: 《讲师TTT培训》 | E146: 46077 | F146: =COUNTIFS('2026年度培训主表'!N:N,C146,'2026年度培训主表'!E:E,D146)/2 -> 1 | G146: =COUNTIFS('2026年度培训主表'!N:N,C146,'2026年度培训主表'!E:E,D146,'2026年度培训主表'!L:L,"已签到")/2 -> 1 | H146: =G146/F146 -> 1
A147: 3月 | B147: 河北 | C147: 河北销售部 | D147: 销售新人入职培训 | E147: 46106 | F147: =COUNTIFS(《授课类型》维度的参训明细!J:J,E147,《授课类型》维度的参训明细!D:D,C147,《授课类型》维度的参训明细!K:K,D147) -> 4 | G147: =COUNTIFS(《授课类型》维度的参训明细!J:J,E147,《授课类型》维度的参训明细!D:D,C147,《授课类型》维度的参训明细!K:K,D147,《授课类型》维度的参训明细!I:I,"已签到") -> 2 | H147: =G147/F147 -> 0.5
A148: 3月 | B148: 河南 | C148: 河南销售部 | D148: 销售新人入职培训 | E148: 46106 | F148: =COUNTIFS(《授课类型》维度的参训明细!J:J,E148,《授课类型》维度的参训明细!D:D,C148,《授课类型》维度的参训明细!K:K,D148) -> 3 | G148: =COUNTIFS(《授课类型》维度的参训明细!J:J,E148,《授课类型》维度的参训明细!D:D,C148,《授课类型》维度的参训明细!K:K,D148,《授课类型》维度的参训明细!I:I,"已签到") -> 2 | H148: =G148/F148 -> 0.66666667
A149: 3月 | B149: 湖北 | C149: 湖北1部 | D149: 销售新人入职培训 | E149: 46106 | F149: =COUNTIFS(《授课类型》维度的参训明细!J:J,E149,《授课类型》维度的参训明细!D:D,C149,《授课类型》维度的参训明细!K:K,D149) -> 3 | G149: =COUNTIFS(《授课类型》维度的参训明细!J:J,E149,《授课类型》维度的参训明细!D:D,C149,《授课类型》维度的参训明细!K:K,D149,《授课类型》维度的参训明细!I:I,"已签到") -> 2 | H149: =G149/F149 -> 0.66666667
A150: 3月 | B150: 湖北 | C150: 湖北2部 | D150: 销售新人入职培训 | E150: 46106 | F150: =COUNTIFS(《授课类型》维度的参训明细!J:J,E150,《授课类型》维度的参训明细!D:D,C150,《授课类型》维度的参训明细!K:K,D150) -> 1 | G150: =COUNTIFS(《授课类型》维度的参训明细!J:J,E150,《授课类型》维度的参训明细!D:D,C150,《授课类型》维度的参训明细!K:K,D150,《授课类型》维度的参训明细!I:I,"已签到") -> 1 | H150: =G150/F150 -> 1
A151: 3月 | B151: 湖南 | C151: 湖南销售部 | D151: 销售新人入职培训 | E151: 46106 | F151: =COUNTIFS(《授课类型》维度的参训明细!J:J,E151,《授课类型》维度的参训明细!D:D,C151,《授课类型》维度的参训明细!K:K,D151) -> 5 | G151: =COUNTIFS(《授课类型》维度的参训明细!J:J,E151,《授课类型》维度的参训明细!D:D,C151,《授课类型》维度的参训明细!K:K,D151,《授课类型》维度的参训明细!I:I,"已签到") -> 4 | H151: =G151/F151 -> 0.8
A152: 3月 | B152: 辽宁 | C152: 辽宁销售部 | D152: 销售新人入职培训 | E152: 46106 | F152: =COUNTIFS(《授课类型》维度的参训明细!J:J,E152,《授课类型》维度的参训明细!D:D,C152,《授课类型》维度的参训明细!K:K,D152) -> 2 | G152: =COUNTIFS(《授课类型》维度的参训明细!J:J,E152,《授课类型》维度的参训明细!D:D,C152,《授课类型》维度的参训明细!K:K,D152,《授课类型》维度的参训明细!I:I,"已签到") -> 2 | H152: =G152/F152 -> 1
A153: 3月 | B153: 山东 | C153: 山东销售部 | D153: 销售新人入职培训 | E153: 46106 | F153: =COUNTIFS(《授课类型》维度的参训明细!J:J,E153,《授课类型》维度的参训明细!D:D,C153,《授课类型》维度的参训明细!K:K,D153) -> 3 | G153: =COUNTIFS(《授课类型》维度的参训明细!J:J,E153,《授课类型》维度的参训明细!D:D,C153,《授课类型》维度的参训明细!K:K,D153,《授课类型》维度的参训明细!I:I,"已签到") -> 3 | H153: =G153/F153 -> 1
A154: 3月 | B154: 陕西 | C154: 陕西1部 | D154: 销售新人入职培训 | E154: 46106 | F154: =COUNTIFS(《授课类型》维度的参训明细!J:J,E154,《授课类型》维度的参训明细!D:D,C154,《授课类型》维度的参训明细!K:K,D154) -> 2 | G154: =COUNTIFS(《授课类型》维度的参训明细!J:J,E154,《授课类型》维度的参训明细!D:D,C154,《授课类型》维度的参训明细!K:K,D154,《授课类型》维度的参训明细!I:I,"已签到") -> 2 | H154: =G154/F154 -> 1
A155: 3月 | B155: 陕西 | C155: 陕西2部 | D155: 销售新人入职培训 | E155: 46106 | F155: =COUNTIFS(《授课类型》维度的参训明细!J:J,E155,《授课类型》维度的参训明细!D:D,C155,《授课类型》维度的参训明细!K:K,D155) -> 3 | G155: =COUNTIFS(《授课类型》维度的参训明细!J:J,E155,《授课类型》维度的参训明细!D:D,C155,《授课类型》维度的参训明细!K:K,D155,《授课类型》维度的参训明细!I:I,"已签到") -> 3 | H155: =G155/F155 -> 1
A156: 3月 | B156: 西南总部 | C156: 营业二部 | D156: 销售新人入职培训 | E156: 46106 | F156: =COUNTIFS(《授课类型》维度的参训明细!J:J,E156,《授课类型》维度的参训明细!D:D,C156,《授课类型》维度的参训明细!K:K,D156) -> 5 | G156: =COUNTIFS(《授课类型》维度的参训明细!J:J,E156,《授课类型》维度的参训明细!D:D,C156,《授课类型》维度的参训明细!K:K,D156,《授课类型》维度的参训明细!I:I,"已签到") -> 0 | H156: =G156/F156 -> 0
A157: 3月 | B157: 西南总部 | C157: 营业六部 | D157: 销售新人入职培训 | E157: 46106 | F157: =COUNTIFS(《授课类型》维度的参训明细!J:J,E157,《授课类型》维度的参训明细!D:D,C157,《授课类型》维度的参训明细!K:K,D157) -> 10 | G157: =COUNTIFS(《授课类型》维度的参训明细!J:J,E157,《授课类型》维度的参训明细!D:D,C157,《授课类型》维度的参训明细!K:K,D157,《授课类型》维度的参训明细!I:I,"已签到") -> 4 | H157: =G157/F157 -> 0.4
A158: 3月 | B158: 西南总部 | C158: 营业七部 | D158: 销售新人入职培训 | E158: 46106 | F158: =COUNTIFS(《授课类型》维度的参训明细!J:J,E158,《授课类型》维度的参训明细!D:D,C158,《授课类型》维度的参训明细!K:K,D158) -> 9 | G158: =COUNTIFS(《授课类型》维度的参训明细!J:J,E158,《授课类型》维度的参训明细!D:D,C158,《授课类型》维度的参训明细!K:K,D158,《授课类型》维度的参训明细!I:I,"已签到") -> 2 | H158: =G158/F158 -> 0.22222222
... A162: 3月 | B162: 西南总部 | C162: 营业一部 | D162: 销售新人入职培训 | E162: 46106 | F162: =COUNTIFS(《授课类型》维度的参训明细!J:J,E162,《授课类型》维度的参训明细!D:D,C162,《授课类型》维度的参训明细!K:K,D162) -> 13 | G162: =COUNTIFS(《授课类型》维度的参训明细!J:J,E162,《授课类型》维度的参训明细!D:D,C162,《授课类型》维度的参训明细!K:K,D162,《授课类型》维度的参训明细!I:I,"已签到") -> 9 | H162: =G162/F162 -> 0.69230769
A163: 3月 | B163: 西南总部 | C163: 职能营销 | D163: 销售新人入职培训 | E163: 46106
A164: 3月 | B164: 河北 | C164: 河北销售部 | D164: 销售提升训 | E164: 46093 | F164: =COUNTIFS(《授课类型》维度的参训明细!J:J,E164,《授课类型》维度的参训明细!D:D,C164,《授课类型》维度的参训明细!K:K,D164) -> 4 | G164: =COUNTIFS(《授课类型》维度的参训明细!J:J,E164,《授课类型》维度的参训明细!D:D,C164,《授课类型》维度的参训明细!K:K,D164,《授课类型》维度的参训明细!I:I,"已签到") -> 2 | H164: =G164/F164 -> 0.5
A165: 3月 | B165: 河南 | C165: 河南销售部 | D165: 销售提升训 | E165: 46093 | F165: =COUNTIFS(《授课类型》维度的参训明细!J:J,E165,《授课类型》维度的参训明细!D:D,C165,《授课类型》维度的参训明细!K:K,D165) -> 8 | G165: =COUNTIFS(《授课类型》维度的参训明细!J:J,E165,《授课类型》维度的参训明细!D:D,C165,《授课类型》维度的参训明细!K:K,D165,《授课类型》维度的参训明细!I:I,"已签到") -> 7 | H165: =G165/F165 -> 0.875
A166: 3月 | B166: 湖北 | C166: 湖北1部 | D166: 销售提升训 | E166: 46093 | F166: =COUNTIFS(《授课类型》维度的参训明细!J:J,E166,《授课类型》维度的参训明细!D:D,C166,《授课类型》维度的参训明细!K:K,D166) -> 9 | G166: =COUNTIFS(《授课类型》维度的参训明细!J:J,E166,《授课类型》维度的参训明细!D:D,C166,《授课类型》维度的参训明细!K:K,D166,《授课类型》维度的参训明细!I:I,"已签到") -> 9 | H166: =G166/F166 -> 1
A167: 3月 | B167: 湖北 | C167: 湖北2部 | D167: 销售提升训 | E167: 46093 | F167: =COUNTIFS(《授课类型》维度的参训明细!J:J,E167,《授课类型》维度的参训明细!D:D,C167,《授课类型》维度的参训明细!K:K,D167) -> 1 | G167: =COUNTIFS(《授课类型》维度的参训明细!J:J,E167,《授课类型》维度的参训明细!D:D,C167,《授课类型》维度的参训明细!K:K,D167,《授课类型》维度的参训明细!I:I,"已签到") -> 0 | H167: =G167/F167 -> 0
A168: 3月 | B168: 湖南 | C168: 湖南销售部 | D168: 销售提升训 | E168: 46093 | F168: =COUNTIFS(《授课类型》维度的参训明细!J:J,E168,《授课类型》维度的参训明细!D:D,C168,《授课类型》维度的参训明细!K:K,D168) -> 3 | G168: =COUNTIFS(《授课类型》维度的参训明细!J:J,E168,《授课类型》维度的参训明细!D:D,C168,《授课类型》维度的参训明细!K:K,D168,《授课类型》维度的参训明细!I:I,"已签到") -> 2 | H168: =G168/F168 -> 0.66666667
A169: 3月 | B169: 辽宁 | C169: 辽宁销售部 | D169: 销售提升训 | E169: 46093 | F169: =COUNTIFS(《授课类型》维度的参训明细!J:J,E169,《授课类型》维度的参训明细!D:D,C169,《授课类型》维度的参训明细!K:K,D169) -> 2 | G169: =COUNTIFS(《授课类型》维度的参训明细!J:J,E169,《授课类型》维度的参训明细!D:D,C169,《授课类型》维度的参训明细!K:K,D169,《授课类型》维度的参训明细!I:I,"已签到") -> 2 | H169: =G169/F169 -> 1
A170: 3月 | B170: 内蒙古 | C170: 内蒙古销售部 | D170: 销售提升训 | E170: 46093 | F170: =COUNTIFS(《授课类型》维度的参训明细!J:J,E170,《授课类型》维度的参训明细!D:D,C170,《授课类型》维度的参训明细!K:K,D170) -> 3 | G170: =COUNTIFS(《授课类型》维度的参训明细!J:J,E170,《授课类型》维度的参训明细!D:D,C170,《授课类型》维度的参训明细!K:K,D170,《授课类型》维度的参训明细!I:I,"已签到") -> 3 | H170: =G170/F170 -> 1
A171: 3月 | B171: 山东 | C171: 山东销售部 | D171: 销售提升训 | E171: 46093 | F171: =COUNTIFS(《授课类型》维度的参训明细!J:J,E171,《授课类型》维度的参训明细!D:D,C171,《授课类型》维度的参训明细!K:K,D171) -> 6 | G171: =COUNTIFS(《授课类型》维度的参训明细!J:J,E171,《授课类型》维度的参训明细!D:D,C171,《授课类型》维度的参训明细!K:K,D171,《授课类型》维度的参训明细!I:I,"已签到") -> 3 | H171: =G171/F171 -> 0.5
A172: 3月 | B172: 山西 | C172: 山西销售部 | D172: 销售提升训 | E172: 46093 | F172: =COUNTIFS(《授课类型》维度的参训明细!J:J,E172,《授课类型》维度的参训明细!D:D,C172,《授课类型》维度的参训明细!K:K,D172) -> 7 | G172: =COUNTIFS(《授课类型》维度的参训明细!J:J,E172,《授课类型》维度的参训明细!D:D,C172,《授课类型》维度的参训明细!K:K,D172,《授课类型》维度的参训明细!I:I,"已签到") -> 7 | H172: =G172/F172 -> 1
A173: 3月 | B173: 陕西 | C173: 陕西1部 | D173: 销售提升训 | E173: 46093 | F173: =COUNTIFS(《授课类型》维度的参训明细!J:J,E173,《授课类型》维度的参训明细!D:D,C173,《授课类型》维度的参训明细!K:K,D173) -> 6 | G173: =COUNTIFS(《授课类型》维度的参训明细!J:J,E173,《授课类型》维度的参训明细!D:D,C173,《授课类型》维度的参训明细!K:K,D173,《授课类型》维度的参训明细!I:I,"已签到") -> 2 | H173: =G173/F173 -> 0.33333333
A174: 3月 | B174: 陕西 | C174: 陕西2部 | D174: 销售提升训 | E174: 46093 | F174: =COUNTIFS(《授课类型》维度的参训明细!J:J,E174,《授课类型》维度的参训明细!D:D,C174,《授课类型》维度的参训明细!K:K,D174) -> 7 | G174: =COUNTIFS(《授课类型》维度的参训明细!J:J,E174,《授课类型》维度的参训明细!D:D,C174,《授课类型》维度的参训明细!K:K,D174,《授课类型》维度的参训明细!I:I,"已签到") -> 5 | H174: =G174/F174 -> 0.71428571
A175: 3月 | B175: 西南总部 | C175: 营业二部 | D175: 销售提升训 | E175: 46093 | F175: =COUNTIFS(《授课类型》维度的参训明细!J:J,E175,《授课类型》维度的参训明细!D:D,C175,《授课类型》维度的参训明细!K:K,D175) -> 4 | G175: =COUNTIFS(《授课类型》维度的参训明细!J:J,E175,《授课类型》维度的参训明细!D:D,C175,《授课类型》维度的参训明细!K:K,D175,《授课类型》维度的参训明细!I:I,"已签到") -> 2 | H175: =G175/F175 -> 0.5
... A229: 3月 | B229: 西南总部 | C229: 营业五部 | D229: B岗培训 | E229: 46098 | F229: =COUNTIFS(《授课类型》维度的参训明细!J:J,E229,《授课类型》维度的参训明细!D:D,C229,《授课类型》维度的参训明细!K:K,D229) -> 2 | G229: =COUNTIFS(《授课类型》维度的参训明细!J:J,E229,《授课类型》维度的参训明细!D:D,C229,《授课类型》维度的参训明细!K:K,D229,《授课类型》维度的参训明细!I:I,"已签到") -> 2 | H229: =G229/F229 -> 1

Sheet 团队项目通关明细表
A1: 经理团队项目话术通关明细
A2: 序号 | B2: 年份 | C2: 月份 | D2: 项目名称 | E2: 项目经理 | F2: 城市 | G2: 项目人数 | H2: 通关时间
A3: 1 | B3: 2026 | C3: 1月 | D3: 南充阳光临江邸 | E3: 周远芮 | F3: =VLOOKUP(E3,[3]在职!$A:$E,5,0) -> 西南总部 | G3: 3 | H3: 46026
A4: 2 | B4: 2026 | C4: 1月 | D4: 公园世家 | E4: 刘佳 | F4: =VLOOKUP(E4,[3]在职!$A:$E,5,0) -> 西南总部 | G4: 6 | H4: 46026
A5: 3 | B5: 2026 | C5: 1月 | D5: 金房生活艺术城第2场次 | E5: 徐子康 | F5: =VLOOKUP(E5,[3]在职!$A:$E,5,0) -> 湖南 | G5: 3 | H5: 46026
A6: 4 | B6: 2026 | C6: 1月 | D6: 凯鑫华府 | E6: 张圣梁 | F6: =VLOOKUP(E6,[3]在职!$A:$E,5,0) -> 西南总部 | G6: 3 | H6: 46027
A7: 5 | B7: 2026 | C7: 1月 | D7: 眉山市滨江翡翠龙湾A区第3场次 | E7: 李先洪 | F7: =VLOOKUP(E7,[3]在职!$A:$E,5,0) -> 西南总部 | G7: 6 | H7: 46028
A8: 6 | B8: 2026 | C8: 1月 | D8: 宜宾江安县名都丽景 | E8: 郑雄 | F8: =VLOOKUP(E8,[3]在职!$A:$E,5,0) -> 西南总部 | G8: 2 | H8: 46030
A9: 7 | B9: 2026 | C9: 1月 | D9: 蜀镇观澜湖 | E9: 吴建鑫 | F9: =VLOOKUP(E9,[3]在职!$A:$E,5,0) -> 西南总部 | G9: 4 | H9: 46030
A10: 8 | B10: 2026 | C10: 1月 | D10: 澄波湖7号第1场次 | E10: 李祥春 | F10: =VLOOKUP(E10,[3]在职!$A:$E,5,0) -> 山东 | G10: 4 | H10: 46031
A11: 9 | B11: 2026 | C11: 1月 | D11: 永川时代国际 | E11: 郑景慕 | F11: =VLOOKUP(E11,[3]在职!$A:$E,5,0) -> 西南总部 | G11: 5 | H11: 46031
A12: 10 | B12: 2026 | C12: 1月 | D12: 蜀镇锦悦府 | E12: 陈彪 | F12: =VLOOKUP(E12,[3]在职!$A:$E,5,0) -> 西南总部 | G12: 6 | H12: 46031
A13: 11 | B13: 2026 | C13: 1月 | D13: 汇龙苑第1场次 | E13: 吴江平 | F13: =VLOOKUP(E13,[3]在职!$A:$E,5,0) -> 山东 | G13: 3 | H13: 46031
A14: 12 | B14: 2026 | C14: 1月 | D14: 东邦棠宁府 | E14: 杨翠茹 | F14: =VLOOKUP(E14,[3]在职!$A:$E,5,0) -> 西南总部 | G14: 4 | H14: 46032
... A23: 21 | B23: 2026 | C23: 1月 | D23: 康斯丹郡 | E23: 闫柏年 | F23: =VLOOKUP(E23,[3]在职!$A:$E,5,0) -> 湖南 | G23: 4 | H23: 46037
A24: 22 | B24: 2026 | C24: 1月 | D24: 眉山万为江南里 | E24: 张佩瑶 | F24: =VLOOKUP(E24,[3]在职!$A:$E,5,0) -> 西南总部 | G24: 顺卖
A25: 23 | B25: 2026 | C25: 1月 | D25: 武胜安泰凤凰城 | E25: 韩颖 | F25: =VLOOKUP(E25,[3]在职!$A:$E,5,0) -> 西南总部 | G25: 6 | H25: 46038
A26: 24 | B26: 2026 | C26: 1月 | D26: 南充兴业香槟尚城 | E26: 大张萍 | F26: =VLOOKUP(E26,[3]在职!$A:$E,5,0) -> #N/A | G26: 5 | H26: 46038
A27: 25 | B27: 2026 | C27: 1月 | D27: 武胜安泰幸福里 | E27: 唐浪波 | F27: =VLOOKUP(E27,[3]在职!$A:$E,5,0) -> 西南总部 | G27: 4 | H27: 46038
A28: 26 | B28: 2026 | C28: 1月 | D28: 营山永康丽都国际第1场次 | E28: 杨威 | F28: =VLOOKUP(E28,[3]在职!$A:$E,5,0) -> 西南总部 | G28: 3 | H28: 46039
A29: 27 | B29: 2026 | C29: 1月 | D29: 越地香港花园 | E29: 陈嘉文 | F29: =VLOOKUP(E29,[3]在职!$A:$E,5,0) -> 西南总部 | G29: 6 | H29: 46039
A30: 28 | B30: 2026 | C30: 1月 | D30: 绿景未来城 | E30: 赵龙 | F30: =VLOOKUP(E30,[3]在职!$A:$E,5,0) -> 山西 | G30: 4 | H30: 46042
A31: 29 | B31: 2026 | C31: 1月 | D31: 香楠国际 | E31: 曾竞超 | F31: =VLOOKUP(E31,[3]在职!$A:$E,5,0) -> 西南总部 | G31: 4 | H31: 46043
A32: 30 | B32: 2026 | C32: 1月 | D32: 领地凤鸣蘭台 | E32: 黄俊 | F32: =VLOOKUP(E32,[3]在职!$A:$E,5,0) -> 湖北 | G32: 3 | H32: 46043
A33: 31 | B33: 2026 | C33: 1月 | D33: 江夏区滨湖壹号 | E33: 阮阳 | F33: =VLOOKUP(E33,[3]在职!$A:$E,5,0) -> 湖北 | G33: 2 | H33: 46043
A34: 32 | B34: 2026 | C34: 1月 | D34: 华邦天悦华府 | E34: 彭小琴 | F34: =VLOOKUP(E34,[3]在职!$A:$E,5,0) -> 西南总部 | G34: 5 | H34: 46044
A35: 33 | B35: 2026 | C35: 1月 | D35: 华邦天悦城一期 | E35: 张家涛 | F35: =VLOOKUP(E35,[3]在职!$A:$E,5,0) -> 西南总部 | G35: 4 | H35: 46044
A36: 34 | B36: 2026 | C36: 1月 | D36: 雄飞北尚广场第1场次 | E36: 税锐 | F36: =VLOOKUP(E36,[3]在职!$A:$E,5,0) -> 西南总部 | G36: 5 | H36: 46044
... A47: 45 | B47: 2026 | C47: 1月 | D47: 金坤苑（欧莱雅郡西区） | E47: 罗敏 | F47: =VLOOKUP(E47,[3]在职!$A:$E,5,0) -> 湖南 | G47: 3 | H47: 46053
A48: 1 | B48: 2026 | C48: 2月 | D48: 御府揽岳阁 | E48: 文鹏羽 | F48: 西南总部 | G48: 5 | H48: 46055
A49: 2 | B49: 2026 | C49: 2月 | D49: 梓潼水岸花都第1场次 | E49: 李培金 | F49: 西南总部 | G49: 5 | H49: 46055
A50: 3 | B50: 2026 | C50: 2月 | D50: 温莎公馆 | E50: 李海艳 | F50: 西南总部 | G50: 5 | H50: 46055
A51: 4 | B51: 2026 | C51: 2月 | D51: 乐山阳光青江壹号 | E51: 扈岭楠 | F51: 西南总部 | G51: 7 | H51: 46056
A52: 5 | B52: 2026 | C52: 2月 | D52: 阳光临江邸二区 | E52: 周远芮 | F52: 西南总部 | G52: 2 | H52: 46056
A53: 6 | B53: 2026 | C53: 2月 | D53: 德康天子湖 | E53: 朱家艳 | F53: 西南总部 | G53: 6 | H53: 46056
A54: 7 | B54: 2026 | C54: 2月 | D54: 中铁骑士府邸 | E54: 张圣梁 | F54: 西南总部 | G54: 4 | H54: 46058
A55: 8 | B55: 2026 | C55: 2月 | D55: 缤纷时代第1场次 | E55: 贾萍 | F55: 西南总部 | G55: 3 | H55: 46059
A56: 9 | B56: 2026 | C56: 2月 | D56: 中央香榭 | E56: 陈炳佑 | F56: 湖南 | G56: 4 | H56: 46059
A57: 10 | B57: 2026 | C57: 2月 | D57: 森柯尚江国际 | E57: 陈彪 | F57: 西南总部 | G57: 3 | H57: 46061
A58: 11 | B58: 2026 | C58: 2月 | D58: 乐山领丰嘉州外滩第1场次 | E58: 白世根 | F58: 西南总部 | G58: 3 | H58: 46063
A59: 12 | B59: 2026 | C59: 2月 | D59: 宏博楿滨城 | E59: 郑雄 | F59: 西南总部 | G59: 2 | H59: 46078
A60: 13 | B60: 2026 | C60: 2月 | D60: 南源丽都 | E60: 吴江平 | F60: 山东 | G60: 5 | H60: 46081

Sheet 26年转正＋试岗
A1: 新人试岗＋转正数据+项目话术汇总
A2: 月份 | B2: 城市 | C2: 试岗通关 （实际人数） | D2: 试岗通关 （淘汰人数） | E2: 试岗淘汰率 | F2: 转正通关 （通过人数） | G2: 项目话术通关 （通关个数）
A3: 1月 | B3: 西南总部 | C3: 22 | D3: 6 | E3: =D3/C3 -> 0.27272727 | F3: 19 | G3: 32
A4: 1月 | B4: 陕西 | C4: 1 | D4: 0 | E4: =D4/C4 -> 0 | F4: 6 | G4: 2
A5: 1月 | B5: 山西 | C5: 0 | D5: 0 | E5: 0 | F5: 3 | G5: 1
A6: 1月 | B6: 山东 | C6: 1 | D6: 1 | E6: =D6/C6 -> 1 | F6: 1 | G6: 2
A7: 1月 | B7: 辽宁 | C7: 1 | D7: 0 | E7: =D7/C7 -> 0 | F7: 0 | G7: 0
A8: 1月 | B8: 湖南 | C8: 6 | D8: 1 | E8: =D8/C8 -> 0.16666667 | F8: 2 | G8: 4
A9: 1月 | B9: 湖北 | C9: 0 | D9: 0 | E9: 0 | F9: 1 | G9: 2
A10: 1月 | B10: 河南 | C10: 2 | D10: 0 | E10: =D10/C10 -> 0 | F10: 4 | G10: 1
A11: 1月 | B11: 河北 | C11: 3 | D11: 1 | E11: =D11/C11 -> 0.33333333 | F11: 0 | G11: 0
A12: 汇总 | C12: 36 | D12: 9 | E12: =D12/C12 -> 0.25 | F12: 36 | G12: 44
A13: 2月 | B13: 河北 | C13: 0 | D13: 0 | E13: 0 | F13: 1 | G13: 0
A14: 2月 | B14: 河南 | C14: 0 | D14: 0 | E14: 0 | F14: 1 | G14: 0
A15: 2月 | B15: 山东 | C15: 2 | D15: 1 | E15: =D15/C15 -> 0.5 | F15: 2 | G15: 1
A16: 2月 | B16: 山西 | C16: 0 | D16: 0 | E16: 0 | F16: 3 | G16: 0
A17: 2月 | B17: 陕西 | C17: 2 | D17: 0 | E17: =D17/C17 -> 0 | F17: 4 | G17: 0
A18: 2月 | B18: 西南总部 | C18: 5 | D18: 2 | E18: =D18/C18 -> 0.4 | F18: 9 | G18: 11
A19: 2月 | B19: 湖南 | C19: 0 | D19: 0 | E19: 0 | F19: 0 | G19: 1
A20: 汇总 | C20: =SUM(C13:C18) -> 9 | D20: =SUM(D13:D18) -> 3 | E20: =D20/C20 -> 0.33333333 | F20: =SUM(F13:F18) -> 20 | G20: 13

Sheet 试岗通关明细
A1: 2026年1-2月新人试岗通关明细
A2: 序号 | B2: 城市 | C2: 月份 | D2: 时间 | E2: 试岗人员姓名 | F2: 性别 | G2: 年龄 | H2: 渠道 （内推/外招） | I2: 通关时间 | J2: 招聘负责人 | K2: 通关方式（线上/线下） | L2: 通关人 | M2: 项目经理姓名 | N2: 经理通关打分 | O2: 试岗项目 | P2: 通关分数 | Q2: 通关状态 | R2: 入职日期 | S2: 就职状态 | T2: 离职日期 | U2: 所差资料 | V2: 师傅姓名 | W2: 师傅带教情况 | X2: 其他通关情况备注
A3: 1 | B3: 湖南 | C3: 1月 | D3: 2026.1.4 | E3: 杨鹏鹏 | F3: 男 | G3: 20 | H3: 校招 | I3: 0.41666667 | J3: 唐雨星 | K3: 线上 | L3: 夏明珠 | M3: 王晶晶 | N3: 91 | O3: 湖景新外滩 | P3: 90 | Q3: 通过 | U3: 无 | W3: 正常带教 | X3: 话术有点生硬，抗性话术没有说服力，到现场接待的时候抗性话术都没有说，业主说要回去考虑一下，就直接放业主回去考虑了 跟进总沟通，留下这个人
A4: 2 | B4: 湖南 | C4: 1月 | D4: 2026.1.4 | E4: 蒋宇 | F4: 男 | G4: 26 | H4: 外招 | I4: 0.625 | J4: 翁碧霞 | K4: 线上 | L4: 夏明珠 | M4: 刘进 | N4: 91 | O4: 创发城 | P4: 91 | Q4: 通过 | U4: 无 | W4: 正常带教 | X4: 抗性话术具有说服力，按照业主的真实类型进行抗性回应，但是小区的稀缺性表达得很少，业主有什么抗性就回答什么抗性， 不会提前给业主制造没有车位的焦虑
A5: 3 | B5: 西南 | C5: 1月 | D5: 2026.1.5 | E5: 谭霜鹰 | F5: 女 | G5: 30 | H5: 内推 | I5: 0.58333333 | J5: 李鑫 | K5: 线上 | L5: 夏明珠 | M5: 彭小琴 | N5: 91 | O5: 美城云庭 | P5: 90 | Q5: 通过 | U5: 无 | W5: 一天只演练两次， 其他时间都在看六脉神剑 | X5: 话术技巧性不强，但是可以正常应对业主抗性只是说服力一般，业主拒绝多次以后就比较容易放弃容易放弃
A6: 4 | B6: 西南 | C6: 1月 | D6: 2026.1.5 | E6: 杜俊杰 | F6: 男 | G6: 31 | H6: 内推 | I6: 0.61111111 | J6: 谭琴 | K6: 线上 | L6: 夏明珠 | M6: 韩颖 | N6: 93 | O6: 灏景泊岸森邻 | P6: 90 | Q6: 通过 | U6: 无 | W6: 正常带教 | X6: 抗性话术有点差，会应对的点有点少，不过灵活性还不错，但是业主拒绝很多次的话也会比较容易放弃
A7: 5 | B7: 西南 | C7: 1月 | D7: 2026.1.5 | E7: 王小蓬 | F7: 男 | G7: 35 | H7: 内推 | I7: 0.63888889 | J7: 杨茜影 | K7: 线上 | L7: 夏明珠 | M7: 党虹 | N7: 93 | O7: 锦江华府 | P7: 92 | Q7: 通过 | U7: 无 | W7: 正常带教 | X7: 话术声情并茂，抗性回答说服力强不错
A8: 6 | B8: 西南 | C8: 1月 | D8: 2026.1.5 | E8: 陈长 | F8: 男 | G8: 28 | H8: 外招 | I8: 0.66666667 | J8: 谭琴 | K8: 线上 | L8: 夏明珠 | M8: 韩颖 | N8: 93 | O8: 灏景泊岸森邻 | P8: 90 | Q8: 通过 | U8: 无 | W8: 正常带教 | X8: 销售风格落落大方，话术自然流畅，但是话术技巧性抗性话术有点欠缺
A9: 7 | B9: 西南 | C9: 1月 | D9: 2026.1.6 | E9: 田浩 | F9: 男 | G9: 21 | H9: 内推 | I9: 0.58333333 | J9: 翁碧霞 | K9: 线上 | L9: 夏明珠 | M9: 彭小琴 | N9: 92 | O9: 美城云庭 | P9: 90 | Q9: 通过 | U9: 无 | W9: 通关这天已经是第七天了，学习有点久 | X9: 话术流畅，语气很有激情，正常简单的话术是没有问题的，就是遇到刁难的业主缺乏专业知识，抗性回答说服力一般
A10: 8 | B10: 河北 | C10: 1月 | D10: 2026.1.8 | E10: 王晓潮 | F10: 男 | G10: 29 | H10: 外招 | I10: 0.58333333 | J10: 李鑫 | K10: 线上 | L10: 夏明珠 | M10: 韦霞 | N10: 94 | O10: 恒茂国际都会 | P10: 90 | Q10: 通过 | U10: 无 | W10: 学的第二天，经理最近 都没空，大多是师傅给过了一遍话术 | X10: 抗性话术：抗性话术没问题，逻辑思维也可以，但是就是个别点的话术不够闭环，说服力不强，比较普通 流程问题：现场接待的流程不对（带看直接从地下室接业主，说河北现在冷，都是从地下室接待业主），业主信息挖掘不够（自己很少挖掘，全靠业主输出），车位介绍简单（没介绍车位号，没输出车位卖点）， 通关评价：做了很多年的车位销售，自认为很懂，没有空杯心态
A11: 9 | B11: 河南 | C11: 1月 | D11: 2026.1.8 | E11: 王振东 | F11: 男 | G11: 24 | H11: 外招 | I11: 0.60416667 | J11: 李鑫 | K11: 线上 | L11: 夏明珠 | M11: 余金梅 | N11: 96 | O11: 天地湾佳苑 | P11: 91 | Q11: 通过 | U11: 无 | W11: 正常带教 | X11: 话术流畅，抗性话术没有太大的问题，但是现场接待的时候业主拒绝太多次就不太会坚持，并且话术技巧性还要再提升一下
A12: 10 | B12: 河南 | C12: 1月 | D12: 2026.1.8 | E12: 赵雪勤 | F12: 女 | G12: 22 | H12: 外招 | I12: 0.625 | J12: 卢思琴 | K12: 线上 | L12: 夏明珠 | M12: 任枭月 | N12: 100 | O12: 中国铁建·东来尚城 | P12: 90 | Q12: 通过 | U12: 无 | W12: 正常带教 | X12: 脑子很灵活，话术很灵敏，会举一反三，但是技巧性的话术储备量还是太少了 没有有意识的主动去挖掘业主信息，价格拉扯的时候有点被业主带着跑
A13: 11 | B13: 西南 | C13: 1月 | D13: 2026.1.8 | E13: 吴中敬 | F13: 男 | G13: 35 | H13: 内推 | I13: 0.66666667 | J13: 卢思琴 | K13: 线上 | L13: 夏明珠 | M13: 李培金 | N13: 90 | O13: 财富又一城 | P13: 82 | Q13: 淘汰 | U13: 无 | W13: 正常带教 | X13: 语气：太平了，没有任何的高低起伏 抗性话术：现场接待通关前我已经把客户类型说得很清楚了，但是抗性话术没有一个说到点上面，说服我， 淘汰原因：抗性话术太差了，一个点都说服不了人
A14: 12 | B14: 西南 | C14: 1月 | D14: 2026.1.9 | E14: 唐筠 | F14: 女 | G14: 38 | H14: 内推 | I14: 0.54166667 | J14: 谭琴 | K14: 线上 | L14: 夏明珠 | M14: 肖秀丽 | N14: 90 | O14: 阳光书香九里 | P14: 91 | Q14: 通过 | U14: 无 | W14: 正常带教 | X14: 话术储备量比较多，没有问题，但是话术更多是单向沟通，一直输出话术，没有得到业主的反馈
... A17: 15 | B17: 陕西 | C17: 1月 | D17: 2026.1.12 | E17: 张玲霞 | F17: 女 | G17: 28 | H17: 外招 | I17: 0.58333333 | J17: 李鑫 | K17: 线上 | L17: 游月 | M17: 邵亮 | N17: 93 | O17: 就掌灯 | P17: 90 | Q17: 通过 | U17: 无 | W17: 正常带教 | X17: 1、形象，状态很好，亲和力高；2、过程中对于反馈有做记录；3、小区数据在话术运用中很薄弱，没有强相关；4、话术灵活，不死板，需求挖掘演练中不全，单独问可以回答上；
A18: 16 | B18: 湖南 | C18: 1月 | D18: 2026.1.12 | E18: 敖玉 | F18: 女 | G18: 36 | H18: 外招 | I18: 0.625 | J18: 杨茜影 | K18: 线上 | L18: 夏明珠 | M18: 徐子康 | N18: 91 | O18: 金房生活艺术城 | P18: 91 | Q18: 通过 | W18: 正常带教 | X18: 话术没有问题，语气语态有紧迫的氛围感，但是话术不够深入，停留在表面，
A19: 17 | B19: 河北 | C19: 1月 | D19: 2026.1.12 | E19: 付康 | F19: 男 | G19: 32 | H19: 外招 | I19: 0.61111111 | J19: 谭琴 | K19: 线上 | L19: 游月 | M19: 韦霞 | N19: 90 | O19: 恒茂国际都会 | P19: 88 | Q19: 淘汰 | U19: 无 | W19: 通关时了解到： 1、贷款资料费不清楚； | X19: 1、客户需求挖掘不足，7个问题，4板斧单独抽问，回答不全；2、优惠介绍错误，第一次算价关于5年管理费直接给业主介绍时抹掉，解释不清楚；业主按照落位単自己算成交价差4200（5年管理费）；3、2笔刷解释信任度不足
A20: 18 | B20: 西南 | C20: 1月 | D20: 2026.1.12 | E20: 赵成 | F20: 男 | G20: 27 | H20: 外招 | I20: 0.58333333 | J20: 翁碧霞 | K20: 线上 | L20: 夏明珠 | M20: 张萍2 | N20: 92 | O20: 南充兴业香槟尚城 | P20: 90 | Q20: 通过 | W20: 正常带教 | X20: 话术逻辑还是有，痛点打击，流畅，不卡壳，但是就是缺乏一点狠的逼定类型的技巧性话术
A21: 19 | B21: 西南 | C21: 1月 | D21: 2026.1.13 | E21: 郑昌豪 | F21: 男 | G21: 24 | H21: 内推 | I21: 0.58333333 | J21: 翁碧霞 | K21: 线上 | L21: 游月 | M21: 胡雪梅 | N21: 92 | O21: 珠江御景湾 | P21: 90 | Q21: 通过 | U21: 无 | W21: 通关时了解到： 1、师傅带教说可以在地下室直接算价格 | X21: 1、话术整体流畅合格，有意识让业主交小定，一直不放价格持续游说客户；2、话术中有自己的思考，但是由于经验不足的原因，没办法把话术说的很灵活，看得出来有去背诵话术。逼定方面没有太结合业主情况进行挤压。
A22: 20 | B22: 西南 | C22: 1月 | D22: 2026.1.14 | E22: 谷起 | F22: 男 | G22: 35 | H22: 外招 | I22: 0.625 | J22: 谭琴 | K22: 线上 | L22: 夏明珠 | M22: 柏刚 | N22: 92 | O22: 建宏山水福都 | P22: 84 | Q22: 淘汰 | U22: 无 | W22: 正常带教 | X22: 抗性话术：话术逻辑是有的，但是整个抗性话术抓不住重点，并且已经把业主类型说得很明白了，话术还是没有强关联性， 说话很拖，很慢 逼定四板斧：我单独问的，可以说，但是都是废话，没有说服力
A23: 21 | B23: 河北 | C23: 1月 | D23: 2026.1.16 | E23: 王应刚 | F23: 男 | G23: 31 | H23: 内推 | I23: 0.58333333 | J23: 唐雨星 | K23: 线上 | L23: 夏明珠 | M23: 韩旭 | N23: 97 | O23: 锦融尚御 | P23: 90 | Q23: 通过 | U23: 无 | W23: 正常带教 | X23: 车位没有报车位号，并且全程是没有可以去挖掘业主的信息的，基本是业主自己在说， 但是抗性话术是具有说服力的，在现有的业主信息里面，可以说出针对这个的针对性话术的，
A24: 22 | B24: 山东 | C24: 1月 | D24: 2026.1.16 | E24: 陈沫 | F24: 男 | G24: 27 | H24: 外招 | I24: 0.64583333 | J24: 翁碧霞 | K24: 线上 | L24: 夏明珠 | M24: 王杰 | N24: 90 | O24: 颐高公馆 | P24: 80 | Q24: 淘汰 | U24: 无 | W24: 正常带教 | X24: 抗性话术：找不到业主的抗性是什么，抗性话术也说不出来，说话没头绪，阐述问题找不到重点 通关点评：通关话术的时候放不开，不管业主什么类型，就是话术就随便说的，跟这个业主有没有关系也不管
A25: 23 | B25: 湖南 | C25: 1月 | D25: 2026.1.20 | E25: 李根 | F25: 男 | G25: 31 | H25: 外招 | I25: 0.39583333 | J25: 卢思琴 | K25: 线上 | L25: 夏明珠 游月 | M25: 刘进 | N25: 90 | O25: 润景园（上园） | P25: 89/ 90 | Q25: 淘汰 第二次通过 | U25: 资料都没有，原因是项目刚接手， 都还没做这些东西 | W25: 项目因为刚进场， 所以只有背六脉神剑的话术，项目的抗性跟卖点不太了解 | X25: 好的点：业主痛点打击比较很有针对性，抨击业主，业主对价格有抗性，进行价格对比，提高业主心理预期，会夸奖业主，给予业主情绪价值 待提升点：抗性话术大多是万能公式话术，跟业主强关键性低，说服力不强，没有根据业主的自身情况结合小区卖点进行话术逼定，逼定四板弗，我是单独问的，不知道是没理解到还是怎么地，说不到重点，没有任何说服力，跟业主没有强关联性
A26: 24 | B26: 西南 | C26: 1月 | D26: 2026.1.23 | E26: 张迪丰 | F26: 男 | G26: 27 | H26: 外招 | I26: 0.39583333 | J26: 杨茜影 | K26: 线上 | L26: 夏明珠 | M26: 申慧 | N26: 84 | O26: 新大香格里拉 | P26: 80 | Q26: 淘汰 | U26: 无 | W26: 正常带教 | X26: 抗性话术：没有说服力，并且对于业主的抗性，答非所问，抓不住重点，想到什么说什么，也不管业主什么样的态度 逻辑思维：会比较乱，没有先后顺序，想到什么说什么，
A27: 25 | B27: 西南 | C27: 1月 | D27: 2026.1.23 | E27: 杨曼 | F27: 女 | G27: 33 | H27: 外招 | I27: 0.625 | J27: 谭琴 | K27: 线上 | L27: 夏明珠 | M27: 陈嘉文 | N27: 90 | O27: 越地香港花园 | P27: 88 | Q27: 淘汰 | U27: 没有新能源知识单 | W27: 说师傅没有具体给 她讲过逼定四板斧 | X27: 逼定四板斧：一个个问的，不能灵活的使用四板斧，并且，我问竞买挤压懂不起这个意思，说师傅没给她说 抗性话术：痛点输出很不错，但是没有输出小区稀缺性，没有使用数据的习惯 总体评估：话术说着说着就卡壳，说话反应有点慢，没有技巧性，
A28: 26 | B28: 西南 | C28: 1月 | D28: 2026.1.24 | E28: 何松键 | F28: 男 | G28: 32 | H28: 外招 | I28: 0.39583333 | J28: 唐雨星 | K28: 线上 | L28: 夏明珠 | M28: 贾萍 | N28: 94 | O28: 空港云尚花园 | P28: 91 | Q28: 通过 | U28: 无 | W28: 正常带教 | X28: 思路逻辑清楚，话术没有问题，但是跟业主的沟通大多是单方向的沟通，很少跟业主进行沟通
A29: 27 | B29: 湖南 | C29: 1月 | D29: 2026.1.26 | E29: 殷俊 | F29: 男 | G29: 36 | H29: 内推 | I29: 0.58333333 | J29: 李鑫 | K29: 线上 | L29: 夏明珠 | M29: 庄素芳 | N29: 90 | O29: 爵士湘 | P29: 88 | Q29: 淘汰 | U29: 无 | W29: 正常带教 | X29: 抗性话术：没有什么说服力，常用就是“挺优惠的，买一个吧”，输出不了其他的抗性话术，话术库有限，但是也学了5天了 总体评估：跨行，以前不是做销售的，学了五天抗性话术输出也很有限，
A30: 28 | B30: 西南 | C30: 1月 | D30: 2026.1.27 | E30: 陈国钊 | F30: 男 | G30: 23 | H30: 外招 | I30: 0.625 | J30: 唐雨星 | K30: 线上 | L30: 夏明珠 | M30: 朱家艳 | N30: 92 | O30: 铜梁北京城建欧陆经典 | P30: 90 | Q30: 通过 | U30: 无 | W30: 正常带教 | X30: 针对话术技巧性不够，只是可以说出一个观点，解释话术没有说的意识， 但是在现有的话术知识储备上整体说得还是有一定的说服力的
A31: 29 | B31: 湖南 | C31: 1月 | D31: 2026.1.28 | E31: 邓松元 | F31: 男 | G31: 29 | H31: 外招 | I31: 0.45833333 | J31: 卢思琴 | K31: 线上 | L31: 夏明珠 | M31: 刘进 | N31: 90 | O31: 润景园（上园） | P31: 90 | Q31: 通过 | U31: 缺少新能源单 | W31: 正常带教 | X31: 话术没有什么太大的问题，就是习惯性单向输出话术，跟业主没有过多的沟通，话术缺少技巧性
A32: 30 | B32: 西南 | C32: 1月 | D32: 2026.1.29 | E32: 李恒 | F32: 男 | G32: 32 | H32: 外招 | I32: 0.45833333 | J32: 谭琴 | K32: 线上 | L32: 夏明珠 | M32: 魏飞翔 | N32: 93 | O32: 置铖荣华府一期 | P32: 90 | Q32: 通过 | U32: 无 | W32: 正常带教 | X32: 话术没有问题，有说服力，但是话术技巧性不是很好
A33: 31 | B33: 西南 | C33: 1月 | D33: 2026.1.30 | E33: 米东 | F33: 男 | G33: 34 | H33: 内推 | I33: 0.54166667 | J33: 谭琴 | K33: 线上 | L33: 夏明珠 | M33: 贾雪英 | N33: 96 | O33: 美每家华龙城E区 | P33: 87 | Q33: 淘汰（担保入职） | U33: 无 | W33: 正常带教 | X33: 抗性话术：很紧张，话都说不清楚，抗性话术某个干点点还是可以说到，但是没有说服力，语言组织能力稍微有点欠缺
A34: 32 | B34: 西南 | C34: 1月 | D34: 2026.1.30 | E34: 敖之美 | F34: 女 | G34: 36 | H34: 内推 | I34: 0.5625 | J34: 杨茜影 | K34: 线上 | L34: 夏明珠 | M34: 杨翠茹 | N34: 90 | O34: 东邦棠宁府 | P34: 90 | Q34: 通过 | U34: 无 | W34: 正常带教 | X34: 话术可以，没有什么大问题，逻辑清楚
A35: 33 | B35: 西南 | C35: 1月 | D35: 2026.1.30 | E35: 石丹 | F35: 女 | G35: 38 | H35: 内推 | I35: 0.625 | J35: 卢思琴 | K35: 线上 | L35: 夏明珠 | M35: 贾萍 | N35: 92 | O35: 空港云尚花园 | P35: 90 | Q35: 通过 | U35: 无 | W35: 正常带教 | X35: 话术流畅度可以，并且具有一定的说服力，但是很少跟业主有互动，对业主进行需求挖掘，业主说什么就是什么
A36: 34 | B36: 西南 | C36: 1月 | D36: 2026.1.30 | E36: 肖文君 | F36: 女 | G36: 33 | H36: 外招 | I36: 0.64583333 | J36: 谭琴 | K36: 线上 | L36: 夏明珠 | M36: 白世根 | N36: 90 | O36: 金欧城联邦一二期 | P36: 84 | Q36: 淘汰（担保入职） | U36: 无 | W36: 不知道小区交房 时间，经理也没有考核过这个方面 | X36: 抗性话术：没有说服力，不知道业主该怎么去逼定，业主多拒绝两次就放弃了 小区稀缺性几乎没表达过，被业主给问住了，没有结合小区的优势去进行逼定，导致逼定话术没有说服力 话术评估：形象气质好，但是话术一般，逼定停留表面，没有说服力
A37: 35 | B37: 辽宁 | C37: 1月 | D37: 2026.1.31 | E37: 徐潇洋 | F37: 男 | G37: 29 | H37: 外招 | I37: 0.58333333 | J37: 杨茜影 | K37: 线上 | L37: 夏明珠 | M37: 孙科 | N37: 96 | O37: 新湖仙林金谷北区 | P37: 91 | Q37: 通过 | U37: 无 | W37: 正常带教 | X37: 话术不错，逻辑贯通，思路清晰
... A43: 41 | B43: 山东 | C43: 2月 | D43: 2026.2.10 | E43: 田震 | F43: 男 | G43: 35 | H43: 外招 | I43: 0.41666667 | J43: 唐雨星 | K43: 线上 | L43: 游月 | M43: 苏晓青 | N43: 90 | O43: 银丰玺悦 | P43: 88 | Q43: 未通过 | U43: 无 | W43: 正常带教 | X43: 话术比较流畅，演练过程中感受到有销售经验，互动有注意听业主的反馈。但是在做异议处理时针对业主抗性时举的例子过于刻意，抗性处理没有结合已知的小区基础情况（ 只卖不租，外围道路已交付）进行卖点输出和放大业主未来停车选择局限且成本高的痛点。整个流程有小瑕疵（未问到业主本次买车位的原因，报价前未确认喜好车位），逼定四板斧中竞买挤压和成本计算未涉及到，业主明确拒绝按揭的情况下依然尝试给业主推荐按揭，没有太顾虑业主的情绪
A44: 42 | B44: 西南 | C44: 2月 | D44: 2026.2.10 | E44: 傅成艳 | F44: 女 | G44: 31 | H44: 内推 | I44: 0.58333333 | J44: 卢思琴 | K44: 线上 | L44: 游月 | M44: 杨科 | N44: 93 | O44: 力扬时代 | P44: 90 | Q44: 通过 | U44: 无 | V44: 朱静 | W44: 正常带教 | X44: 亲和力很强，应对灵活看的出来过往销售经验丰富。在通关中 有流程性的错误（不介绍车位号、地下室直接报成交价格）
A45: 43 | B45: 西南 | C45: 2月 | D45: 2026.2.12 | E45: 包彩霞 | F45: 女 | G45: 40 | H45: 外招 | I45: 0.41666667 | J45: 翁碧霞 | K45: 线上 | L45: 游月 | M45: 曾竞超 | N45: 90 | O45: 香楠国际 | P45: 86 | Q45: 未通过 | U45: 无 | V45: 周思鸿 | W45: 学员认为师傅正常带教结束，但是学员流程方面的问题很大 | X45: 有点紧张，亲和力强；流程性错误：带看流程未介绍车位号，车位情况；接待流程跳过了销控图直接带往地下室；报价是在地下室报价；喜欢和业主对抗并且没有根据业主的抗性和回答做出反馈，业主反复提到不喜欢新能源不打算换新能源，学员依旧不停提新能源。
A46: 44 | B46: 西南 | C46: 2月 | D46: 2026.2.12 | E46: 何娜 | F46: 女 | G46: 32 | H46: 内推 | I46: 0.58333333 | J46: 翁碧霞 | K46: 线上 | L46: 游月 | M46: 肖秀丽 | N46: 90 | O46: 鹭岛国际 | P46: 90 | Q46: 通关 | U46: 无 | V46: 张鹏 | W46: 正常带教 | X46: 演练过程亲和力强，整体流程较为规范化，熟悉基本话术框架，演练过程中可以感受到一定的销售经验，互动聆听业主的需求及反馈。针对业主砍价问题，应结合产品情况回复（包括但不限于小区具体情况、车位情况、业主实时需求反馈等）
A47: 45 | B47: 山东 | C47: 2月 | D47: 2026.2.28 | E47: 张新月 | F47: 男 | G47: 36 | H47: 外招 | I47: 0.45833333 | J47: 李鑫 | K47: 线上 | L47: 黄雪茹 | M47: 赵文涛 | N47: 95 | O47: 华润置地青岛润府 | P47: 94 | Q47: 通关 | U47: 无 | V47: 罗瑶 | W47: 正常带教 | X47: 演练过程灵活、亲和力强，整体流程较为规范化，熟悉基本话术框架，演练过程中可以感受到一定的销售经验，互动聆听业主的需求及反馈。针对业主还可加大挖掘力度，缺少一定的数据支撑，业主反复提及资金不足时，应结合业主实际情况理性推销购买第二个车位

Sheet 转正通关明细 
A1: 2026年转正通关明细（做表日期一个月更新一次）
A2: 姓名 | B2: 工号 | C2: 入职日期 | D2: 公司 | E2: 营业部 | F2: 直系上级 | G2: 职务 | H2: 性别 | I2: 是否在职 | J2: 做表日期 | K2: 离职日期 | L2: 在职时长(月) | M2: 六脉考试日期 | N2: 是否通过 | O2: 转正日期 | P2: 转正时常(月） | Q2: 备注
A3: 李恒 | B3: 01921 | C3: 46048 | D3: 西南总部 | E3: 营业一部 | F3: 朱家艳 | G3: 实习销售 | H3: 男 | I3: 在职 | J3: 46055 | K3: 0 | L3: 0.23333333
A4: 邓松元 | B4: 01920 | C4: 46048 | D4: 湖南 | E4: 湖南销售部 | F4: 庄素芳 | G4: 实习销售 | H4: 男 | I4: 在职 | J4: 46055 | K4: 0 | L4: 0.23333333
A5: 陈国钊 | B5: 01919 | C5: 46045 | D5: 西南总部 | E5: 营业二部 | F5: 文鹏羽 | G5: 实习销售 | H5: 男 | I5: 在职 | J5: 46055 | K5: 0 | L5: 0.33333333
A6: 陈兴银 | B6: 01888 | C6: 46022 | D6: #N/A | E6: #N/A | F6: #N/A | G6: 实习销售 | H6: 男 | I6: #N/A | J6: 46055 | K6: 46032 | L6: 0.33333333
A7: 周光泚 | B7: 01877 | C7: 46016 | D7: #N/A | E7: #N/A | F7: #N/A | G7: 实习销售 | H7: 男 | I7: #N/A | J7: 46055 | K7: 46027 | L7: 0.36666667
A8: 程钦 | B8: 01847 | C8: 46000 | D8: #N/A | E8: #N/A | F8: #N/A | G8: 实习销售 | H8: 男 | I8: #N/A | J8: 46055 | K8: 46011 | L8: 0.36666667
A9: 何松键 | B9: 01916 | C9: 46042 | D9: 西南总部 | E9: 营业七部 | F9: 袁小龙 | G9: 实习销售 | H9: 男 | I9: 在职 | J9: 46055 | K9: 0 | L9: 0.43333333
A10: 周耀纯 | B10: 01890 | C10: 46022 | D10: #N/A | E10: #N/A | F10: #N/A | G10: 实习销售 | H10: 女 | I10: #N/A | J10: 46055 | K10: 46035 | L10: 0.43333333
A11: 李根 | B11: 01914 | C11: 46039 | D11: 湖南 | E11: 湖南销售部 | F11: 庄素芳 | G11: 实习销售 | H11: 男 | I11: 在职 | J11: 46055 | K11: 0 | L11: 0.53333333
A12: 王应刚 | B12: 01912 | C12: 46035 | D12: 河北 | E12: 河北销售部 | F12: 韩旭 | G12: 实习销售 | H12: 男 | I12: 在职 | J12: 46055 | K12: 0 | L12: 0.66666667
A13: 郑昌豪 | B13: 01910 | C13: 46031 | D13: 西南总部 | E13: 营业一部 | F13: 胡雪梅 | G13: 实习销售 | H13: 男 | I13: 在职 | J13: 46055 | K13: 0 | L13: 0.8
A14: 赵成 | B14: 01909 | C14: 46031 | D14: 西南总部 | E14: 营业一部 | F14: 唐浪波 | G14: 实习销售 | H14: 男 | I14: 在职 | J14: 46055 | K14: 0 | L14: 0.8
A15: 张玲霞 | B15: 01906 | C15: 46031 | D15: 陕西 | E15: 陕西2部 | F15: 王天成 | G15: 实习销售 | H15: 女 | I15: 在职 | J15: 46055 | K15: 0 | L15: 0.8
A16: 敖玉 | B16: 01907 | C16: 46030 | D16: 湖南 | E16: 湖南销售部 | F16: 刘元发 | G16: 实习销售 | H16: 女 | I16: 在职 | J16: 46055 | K16: 0 | L16: 0.83333333
A17: 陈思丹 | B17: 01885 | C17: 46022 | D17: #N/A | E17: #N/A | F17: #N/A | G17: 实习销售 | H17: 女 | I17: #N/A | J17: 46055 | K17: 46048 | L17: 0.86666667
A18: 唐筠 | B18: 01905 | C18: 46027 | D18: 西南总部 | E18: 营业七部 | F18: 张家涛 | G18: 实习销售 | H18: 女 | I18: 在职 | J18: 46055 | K18: 0 | L18: 0.93333333
A19: 王晓潮 | B19: 01902 | C19: 46026 | D19: 河北 | E19: 河北销售部 | F19: 陈东2河北 | G19: 实习销售 | H19: 男 | I19: 在职 | J19: 46055 | K19: 0 | L19: 0.96666667
A20: 王振东 | B20: 01903 | C20: 46026 | D20: 河南 | E20: 河南销售部 | F20: 杜雄 | G20: 实习销售 | H20: 男 | I20: 在职 | J20: 46055 | K20: 0 | L20: 0.96666667
A21: 陈长 | B21: 01899 | C21: 46025 | D21: 西南总部 | E21: 营业六部 | F21: 韩颖 | G21: 实习销售 | H21: 男 | I21: 在职 | J21: 46055 | K21: 0 | L21: 1
A22: 王小蓬 | B22: 01898 | C22: 46025 | D22: 西南总部 | E22: 营业五部 | F22: 张萍2 | G22: 实习销售 | H22: 男 | I22: 在职 | J22: 46055 | K22: 0 | L22: 1
A23: 赵雪勤 | B23: 01904 | C23: 46024 | D23: 河南 | E23: 河南销售部 | F23: 任枭月 | G23: 实习销售 | H23: 女 | I23: 在职 | J23: 46055 | K23: 0 | L23: 1.0333333
A24: 李沁 | B24: 01865 | C24: 46010 | D24: #N/A | E24: #N/A | F24: #N/A | G24: 实习销售 | H24: 女 | I24: #N/A | J24: 46055 | K24: 46041 | L24: 1.0333333
A25: 刘鹏程 | B25: 01887 | C25: 46022 | D25: 西南总部 | E25: 营业一部 | F25: 白世根 | G25: 实习销售 | H25: 男 | I25: 在职 | J25: 46055 | K25: 0 | L25: 1.1
A26: 王成鑫 | B26: 01882 | C26: 46022 | D26: 西南总部 | E26: 营业四部 | F26: 陈帅 | G26: 实习销售 | H26: 男 | I26: 在职 | J26: 46055 | K26: 0 | L26: 1.1
A27: 刘兴东 | B27: 01884 | C27: 46022 | D27: 西南总部 | E27: 营业一部 | F27: 胡雪梅 | G27: 实习销售 | H27: 男 | I27: 在职 | J27: 46055 | K27: 0 | L27: 1.1
A28: 陈浩 | B28: 01883 | C28: 46022 | D28: 西南总部 | E28: 营业三部 | F28: 扈岭楠 | G28: 实习销售 | H28: 男 | I28: 在职 | J28: 46055 | K28: 0 | L28: 1.1
A29: 邓双梅 | B29: 01879 | C29: 46022 | D29: 西南总部 | E29: 营业七部 | F29: 申慧 | G29: 实习销售 | H29: 女 | I29: 在职 | J29: 46055 | K29: 0 | L29: 1.1
A30: 红英 | B30: 01889 | C30: 46022 | D30: 西南总部 | E30: 营业二部 | F30: 魏飞翔 | G30: 实习销售 | H30: 女 | I30: 在职 | J30: 46055 | K30: 0 | L30: 1.1
A31: 曹雪浩 | B31: 01886 | C31: 46022 | D31: 西南总部 | E31: 营业五部 | F31: 杨科 | G31: 实习销售 | H31: 男 | I31: 在职 | J31: 46055 | K31: 0 | L31: 1.1
A32: 徐超2 | B32: 01892 | C32: 46022 | D32: 西南总部 | E32: 营业五部 | F32: 杨科 | G32: 实习销售 | H32: 男 | I32: 在职 | J32: 46055 | K32: 0 | L32: 1.1
A33: 吴海蛟 | B33: 01881 | C33: 46022 | D33: 西南总部 | E33: 营业五部 | F33: 张萍2 | G33: 实习销售 | H33: 男 | I33: 在职 | J33: 46055 | K33: 0 | L33: 1.1
A34: 杨孟 | B34: 01891 | C34: 46020 | D34: 山东 | E34: 山东销售部 | F34: 蒲建宇山东 | G34: 实习销售 | H34: 男 | I34: 在职 | J34: 46055 | K34: 0 | L34: 1.1666667
A35: 侯春红 | B35: 01893 | C35: 46019 | D35: 西南总部 | E35: 营业三部 | F35: 郑景慕 | G35: 实习销售 | H35: 女 | I35: 在职 | J35: 46055 | K35: 0 | L35: 1.2
A36: 杨康 | B36: 01610 | C36: 46018 | D36: 西南总部 | E36: 营业二部 | F36: 蒋吉勇 | G36: 实习销售 | H36: 男 | I36: 在职 | J36: 46055 | K36: 0 | L36: 1.2333333
... A39: 董衡 | B39: 01876 | C39: 46017 | D39: 西南总部 | E39: 营业五部 | F39: 张萍2 | G39: 实习销售 | H39: 男 | I39: 在职 | J39: 46055 | K39: 0 | L39: 1.2666667
A40: 郑仪 | B40: 01831 | C40: 45998 | D40: #N/A | E40: #N/A | F40: #N/A | G40: 实习销售 | H40: 女 | I40: #N/A | J40: 46055 | K40: 46037 | L40: 1.3
A41: 沈锐 | B41: 01880 | C41: 46015 | D41: 西南总部 | E41: 营业三部 | F41: 扈岭楠 | G41: 实习销售 | H41: 男 | I41: 在职 | J41: 46055 | K41: 0 | L41: 1.3333333
A42: 黄畅 | B42: 01874 | C42: 46015 | D42: 湖南 | E42: 湖南销售部 | F42: 庄素芳 | G42: 实习销售 | H42: 女 | I42: 在职 | J42: 46055 | K42: 0 | L42: 1.3333333
A43: 杨鹏鹏 | B43: 01894 | C43: 46014 | D43: 湖南 | E43: 湖南销售部 | F43: 王晶晶 | G43: 实习销售 | H43: 男 | I43: 在职 | J43: 46055 | K43: 0 | L43: 1.3666667
A44: 邓联红 | B44: 01873 | C44: 46013 | D44: 湖南 | E44: 湖南销售部 | F44: 罗敏 | G44: 实习销售 | H44: 男 | I44: 在职 | J44: 46055 | K44: 0 | L44: 1.4
A45: 莫嘉鑫 | B45: 01871 | C45: 46013 | D45: 西南总部 | E45: 营业六部 | F45: 毛富林 | G45: 实习销售 | H45: 女 | I45: 在职 | J45: 46055 | K45: 0 | L45: 1.4
A46: 张凯 | B46: 01868 | C46: 46011 | D46: 山东 | E46: 山东销售部 | F46: 冯洁 | G46: 实习销售 | H46: 男 | I46: 在职 | J46: 46055 | K46: 0 | L46: 1.4666667
A47: 刘超2 | B47: 01869 | C47: 46011 | D47: 湖北 | E47: 湖北1部 | F47: 林浩 | G47: 实习销售 | H47: 男 | I47: 在职 | J47: 46055 | K47: 0 | L47: 1.4666667
A48: 杨璐通 | B48: 01870 | C48: 46011 | D48: 河南 | E48: 河南销售部 | F48: 余金梅 | G48: 实习销售 | H48: 男 | I48: 在职 | J48: 46055 | K48: 0 | L48: 1.4666667
A49: 何娟 | B49: 01051 | C49: 46010 | D49: 河南 | E49: 河南销售部 | F49: 毛孝树 | G49: 实习销售 | H49: 女 | I49: 在职 | J49: 46055 | K49: 0 | L49: 1.5
A50: 米雪琴 | B50: 01866 | C50: 46010 | D50: 西南总部 | E50: 营业五部 | F50: 杨科 | G50: 实习销售 | H50: 女 | I50: 在职 | J50: 46055 | K50: 0 | L50: 1.5
A51: 李杰4 | B51: 01863 | C51: 46008 | D51: 西南总部 | E51: 营业一部 | F51: 张圣梁 | G51: 实习销售 | H51: 男 | I51: 在职 | J51: 46055 | K51: 0 | L51: 1.5666667
A52: 屈文涛 | B52: 01864 | C52: 46008 | D52: 西南总部 | E52: 营业六部 | F52: 郑雄 | G52: 实习销售 | H52: 男 | I52: 在职 | J52: 46055 | K52: 0 | L52: 1.5666667
... A58: 吕亚美 | B58: 01861 | C58: 46004 | D58: 河南 | E58: 河南销售部 | F58: 余金梅 | G58: 实习销售 | H58: 女 | I58: 在职 | J58: 46055 | K58: 0 | L58: 1.7
A59: 王琪 | B59: 01850 | C59: 46003 | D59: 河北 | E59: 河北销售部 | F59: 李港一 | G59: 实习销售 | H59: 女 | I59: 在职 | J59: 46055 | K59: 0 | L59: 1.7333333 | M59: 46055 | N59: 已通过
A60: 曹誉磊 | B60: 01852 | C60: 46003 | D60: 西南总部 | E60: 营业七部 | F60: 申慧 | G60: 实习销售 | H60: 男 | I60: 在职 | J60: 46055 | K60: 0 | L60: 1.7333333 | M60: 46063 | N60: 已通过
A61: 耿腾飞 | B61: 01849 | C61: 46003 | D61: 山东 | E61: 山东销售部 | F61: 肖佳 | G61: 实习销售 | H61: 男 | I61: 在职 | J61: 46055 | K61: 0 | L61: 1.7333333 | M61: 46079 | N61: 已通过
A62: 吴俊芳 | B62: 01851 | C62: 46002 | D62: 湖北 | E62: 湖北2部 | F62: 陈俊儒 | G62: 实习销售 | H62: 女 | I62: 在职 | J62: 46055 | K62: 0 | L62: 1.7666667
A63: 杨晓 | B63: 01846 | C63: 46002 | D63: 陕西 | E63: 陕西1部 | F63: 杨永梅 | G63: 实习销售 | H63: 女 | I63: 在职 | J63: 46055 | K63: 0 | L63: 1.7666667
A64: 陈思竹 | B64: 01848 | C64: 46002 | D64: 河南 | E64: 河南销售部 | F64: 张萍河南 | G64: 实习销售 | H64: 女 | I64: 在职 | J64: 46055 | K64: 0 | L64: 1.7666667
A65: 范仕宽 | B65: 01853 | C65: 46001 | D65: 西南总部 | E65: 营业二部 | F65: 李先洪 | G65: 实习销售 | H65: 男 | I65: 在职 | J65: 46055 | K65: 0 | L65: 1.8
A66: 向戈 | B66: 01845 | C66: 45999 | D66: 西南总部 | E66: 营业六部 | F66: 杨翠茹 | G66: 实习销售 | H66: 男 | I66: 在职 | J66: 46055 | K66: 0 | L66: 1.8666667
A67: 杨诗语 | B67: 01844 | C67: 45999 | D67: 陕西 | E67: 陕西1部 | F67: 张英 | G67: 实习销售 | H67: 女 | I67: 在职 | J67: 46055 | K67: 0 | L67: 1.8666667
A68: 胡凰慧懿 | B68: 01826 | C68: 45998 | D68: 西南总部 | E68: 营业七部 | F68: 陈彪 | G68: 实习销售 | H68: 女 | I68: 在职 | J68: 46055 | K68: 0 | L68: 1.9
A69: 林乔乔 | B69: 01841 | C69: 45998 | D69: 西南总部 | E69: 营业一部 | F69: 雷小金 | G69: 实习销售 | H69: 女 | I69: 在职 | J69: 46055 | K69: 0 | L69: 1.9
A70: 黄倩 | B70: 01827 | C70: 45998 | D70: 西南总部 | E70: 营业三部 | F70: 李海艳 | G70: 实习销售 | H70: 女 | I70: 在职 | J70: 46055 | K70: 0 | L70: 1.9
A71: 王广泰 | B71: 01839 | C71: 45998 | D71: 陕西 | E71: 陕西1部 | F71: 吕瑞仙 | G71: 实习销售 | H71: 男 | I71: 在职 | J71: 46055 | K71: 0 | L71: 1.9
A72: 叶秀慧 | B72: 01837 | C72: 45998 | D72: 西南总部 | E72: 营业六部 | F72: 税锐 | G72: 实习销售 | H72: 女 | I72: 在职 | J72: 46055 | K72: 0 | L72: 1.9
A73: 张钰忠 | B73: 01832 | C73: 45998 | D73: 西南总部 | E73: 营业三部 | F73: 陶再阳 | G73: 实习销售 | H73: 男 | I73: 在职 | J73: 46055 | K73: 0 | L73: 1.9
... A78: 钟亚坤 | B78: 01843 | C78: 45998 | D78: 陕西 | E78: 陕西2部 | F78: 朱全兰 | G78: 实习销售 | H78: 男 | I78: 在职 | J78: 46055 | K78: 0 | L78: 1.9
A79: 郭伟 | B79: 01782 | C79: 45972 | D79: #N/A | E79: #N/A | F79: #N/A | G79: 实习销售 | H79: 男 | I79: #N/A | J79: 46055 | K79: 46029 | L79: 1.9
A80: 胡月2 | B80: 01840 | C80: 45995 | D80: 山西 | E80: 山西销售部 | F80: 郭永曼 | G80: 实习销售 | H80: 女 | I80: 在职 | J80: 46055 | K80: 0 | L80: 2
A81: 章小康 | B81: 01838 | C81: 45994 | D81: 湖北 | E81: 湖北2部 | F81: 陈俊儒 | G81: 实习销售 | H81: 男 | I81: 在职 | J81: 46055 | K81: 0 | L81: 2.0333333
A82: 林兴江 | B82: 01835 | C82: 45994 | D82: 西南总部 | E82: 营业六部 | F82: 袁华 | G82: 实习销售 | H82: 男 | I82: 在职 | J82: 46055 | K82: 0 | L82: 2.0333333
A83: 李强3 | B83: 01833 | C83: 45993 | D83: 湖南 | E83: 湖南销售部 | F83: 刘元发 | G83: 实习销售 | H83: 男 | I83: 在职 | J83: 46055 | K83: 0 | L83: 2.0666667
A84: 李青松 | B84: 01821 | C84: 45992 | D84: 西南总部 | E84: 营业一部 | F84: 白世根 | G84: 实习销售 | H84: 男 | I84: 在职 | J84: 46055 | K84: 0 | L84: 2.1 | M84: 46078 | N84: 已通过
A85: 关志亮 | B85: 01824 | C85: 45992 | D85: 山西 | E85: 山西销售部 | F85: 邓富 | G85: 实习销售 | H85: 男 | I85: 在职 | J85: 46055 | K85: 0 | L85: 2.1 | M85: 46079 | N85: 已通过
A86: 费玲玲 | B86: 01820 | C86: 45992 | D86: 湖南 | E86: 湖南销售部 | F86: 刘进 | G86: 实习销售 | H86: 女 | I86: 在职 | J86: 46055 | K86: 0 | L86: 2.1
A87: 郭希鹏 | B87: 01819 | C87: 45992 | D87: 陕西 | E87: 陕西1部 | F87: 马少波 | G87: 实习销售 | H87: 男 | I87: 在职 | J87: 46055 | K87: 0 | L87: 2.1
A88: 杜文博 | B88: 01823 | C88: 45992 | D88: 陕西 | E88: 陕西2部 | F88: 王晓刚 | G88: 实习销售 | H88: 男 | I88: 在职 | J88: 46055 | K88: 0 | L88: 2.1
A89: 冯光美 | B89: 01818 | C89: 45990 | D89: 西南总部 | E89: 营业三部 | F89: 陶再阳 | G89: 实习销售 | H89: 女 | I89: 在职 | J89: 46055 | K89: 0 | L89: 2.1666667
